Workbook

Sheet 1全量还款明细汇总
A1: 所属文件名称 | B1: 所属Sheet名称 | C1: 资产包编号 | D1: 托管房源编号1 | E1: 当期计划还款金额 | F1: 当期实际还款金额 | G1: 托管房源编号 | H1: 还款日期 | I1: 当前信托计划（已发行）
A2: 美润1号_还款明细表_0529.xlsx | B2: 0325已还款 | C2: 单一-001 | D2: 107113471357 | E2: 3264 | F2: 3264 | G2: 107113471357 | H2: 46106 | I2: =VLOOKUP(G2,'3已发行数据0610（明道云数据）'!B:N,13,FALSE) -> 单一信托,信托3号
A3: 美润1号_还款明细表_0529.xlsx | B3: 0325已还款 | C3: 单一-001 | D3: 107113694737 | E3: 11343.88 | F3: 11343.88 | G3: 107113694737 | H3: 46106 | I3: =VLOOKUP(G3,'3已发行数据0610（明道云数据）'!B:N,13,FALSE) -> 单一信托,信托3号
A4: 美润1号_还款明细表_0529.xlsx | B4: 0325已还款 | C4: 单一-001 | D4: 107113385212 | E4: 10132.92 | F4: 10132.92 | G4: 107113385212 | H4: 46106 | I4: =VLOOKUP(G4,'3已发行数据0610（明道云数据）'!B:N,13,FALSE) -> 单一信托,信托3号
A5: 美润1号_还款明细表_0529.xlsx | B5: 0325已还款 | C5: 单一-001 | D5: 107114212209 | E5: 4920 | F5: 4920 | G5: 107114212209 | H5: 46106 | I5: =VLOOKUP(G5,'3已发行数据0610（明道云数据）'!B:N,13,FALSE) -> 单一信托,信托3号
A6: 美润1号_还款明细表_0529.xlsx | B6: 0325已还款 | C6: 单一-001 | D6: 107113045363 | E6: 4353.1 | F6: 4353.1 | G6: 107113045363 | H6: 46106 | I6: =VLOOKUP(G6,'3已发行数据0610（明道云数据）'!B:N,13,FALSE) -> 单一信托,信托3号
A7: 美润1号_还款明细表_0529.xlsx | B7: 0325已还款 | C7: 单一-001 | D7: 107114495649 | E7: 9136.9 | F7: 9136.9 | G7: 107114495649 | H7: 46106 | I7: =VLOOKUP(G7,'3已发行数据0610（明道云数据）'!B:N,13,FALSE) -> 单一信托,信托3号
A8: 美润1号_还款明细表_0529.xlsx | B8: 0325已还款 | C8: 单一-001 | D8: 107113193877 | E8: 6486 | F8: 6486 | G8: 107113193877 | H8: 46106 | I8: =VLOOKUP(G8,'3已发行数据0610（明道云数据）'!B:N,13,FALSE) -> 单一信托,信托3号
A9: 美润1号_还款明细表_0529.xlsx | B9: 0325已还款 | C9: 单一-001 | D9: 107112417471 | E9: 12384 | F9: 12384 | G9: 107112417471 | H9: 46106 | I9: =VLOOKUP(G9,'3已发行数据0610（明道云数据）'!B:N,13,FALSE) -> 单一信托,信托3号
A10: 美润1号_还款明细表_0529.xlsx | B10: 0325已还款 | C10: 单一-001 | D10: 107114226759 | E10: 12810 | F10: 12810 | G10: 107114226759 | H10: 46106 | I10: =VLOOKUP(G10,'3已发行数据0610（明道云数据）'!B:N,13,FALSE) -> 单一信托,信托3号
A11: 美润1号_还款明细表_0529.xlsx | B11: 0325已还款 | C11: 单一-001 | D11: 107113184658 | E11: 17466 | F11: 17466 | G11: 107113184658 | H11: 46106 | I11: =VLOOKUP(G11,'3已发行数据0610（明道云数据）'!B:N,13,FALSE) -> 单一信托,信托3号
A12: 美润1号_还款明细表_0529.xlsx | B12: 0325已还款 | C12: 单一-001 | D12: 101128210944 | E12: 56000 | F12: 56000 | G12: 101128210944 | H12: 46106 | I12: =VLOOKUP(G12,'3已发行数据0610（明道云数据）'!B:N,13,FALSE) -> 单一信托,信托3号
A13: 美润1号_还款明细表_0529.xlsx | B13: 0325已还款 | C13: 单一-001 | D13: 107114205966 | E13: 8404.71 | F13: 8404.71 | G13: 107114205966 | H13: 46106 | I13: =VLOOKUP(G13,'3已发行数据0610（明道云数据）'!B:N,13,FALSE) -> 单一信托,信托3号
... A215: 美润1号_还款明细表_0529.xlsx | B215: 0529已还款 | C215: 单一-001 | D215: 107112416762 | E215: 1600 | F215: 1600 | G215: 107112416762 | H215: 46171 | I215: =VLOOKUP(G215,'3已发行数据0610（明道云数据）'!B:N,13,FALSE) -> 单一信托
A216: 美好生活3号-还款明细披露信息_20260529_已更新0601.xlsx | B216: 0430已还款 | C216: 3 | D216: 101134445166 | E216: 6861.37 | F216: 6861.37 | G216: 101134445166 | H216: 46142 | I216: =VLOOKUP(G216,'3已发行数据0610（明道云数据）'!B:N,13,FALSE) -> 信托3号
A217: 美好生活3号-还款明细披露信息_20260529_已更新0601.xlsx | B217: 0430已还款 | C217: 3 | D217: 101133822347 | E217: 6650 | F217: 6650 | G217: 101133822347 | H217: 46142 | I217: =VLOOKUP(G217,'3已发行数据0610（明道云数据）'!B:N,13,FALSE) -> 信托3号
A218: 美好生活3号-还款明细披露信息_20260529_已更新0601.xlsx | B218: 0430已还款 | C218: 3 | D218: 107114291360 | E218: 5140 | F218: 5140 | G218: 107114291360 | H218: 46142 | I218: =VLOOKUP(G218,'3已发行数据0610（明道云数据）'!B:N,13,FALSE) -> 信托3号
A219: 美好生活3号-还款明细披露信息_20260529_已更新0601.xlsx | B219: 0430已还款 | C219: 3 | D219: 107114474902 | E219: 5329.87 | F219: 5329.87 | G219: 107114474902 | H219: 46142 | I219: =VLOOKUP(G219,'3已发行数据0610（明道云数据）'!B:N,13,FALSE) -> 信托3号
A220: 美好生活3号-还款明细披露信息_20260529_已更新0601.xlsx | B220: 0430已还款 | C220: 3 | D220: 107114615743 | E220: 4610 | F220: 4610 | G220: 107114615743 | H220: 46142 | I220: =VLOOKUP(G220,'3已发行数据0610（明道云数据）'!B:N,13,FALSE) -> 信托3号
A221: 美好生活3号-还款明细披露信息_20260529_已更新0601.xlsx | B221: 0430已还款 | C221: 3 | D221: 107114233912 | E221: 5743.6 | F221: 5743.6 | G221: 107114233912 | H221: 46142 | I221: =VLOOKUP(G221,'3已发行数据0610（明道云数据）'!B:N,13,FALSE) -> 信托3号
A222: 美好生活3号-还款明细披露信息_20260529_已更新0601.xlsx | B222: 0430已还款 | C222: 3 | D222: 107114591839 | E222: 4632.94 | F222: 4632.94 | G222: 107114591839 | H222: 46142 | I222: =VLOOKUP(G222,'3已发行数据0610（明道云数据）'!B:N,13,FALSE) -> 信托3号
A223: 美好生活3号-还款明细披露信息_20260529_已更新0601.xlsx | B223: 0430已还款 | C223: 3 | D223: 107114187138 | E223: 4662.6 | F223: 4662.6 | G223: 107114187138 | H223: 46142 | I223: =VLOOKUP(G223,'3已发行数据0610（明道云数据）'!B:N,13,FALSE) -> 信托3号
A224: 美好生活3号-还款明细披露信息_20260529_已更新0601.xlsx | B224: 0430已还款 | C224: 3 | D224: 107114218904 | E224: 5580 | F224: 5580 | G224: 107114218904 | H224: 46142 | I224: =VLOOKUP(G224,'3已发行数据0610（明道云数据）'!B:N,13,FALSE) -> 信托3号
A225: 美好生活3号-还款明细披露信息_20260529_已更新0601.xlsx | B225: 0430已还款 | C225: 3 | D225: 107114562119 | E225: 14734.74 | F225: 14734.74 | G225: 107114562119 | H225: 46142 | I225: =VLOOKUP(G225,'3已发行数据0610（明道云数据）'!B:N,13,FALSE) -> 信托3号
A226: 美好生活3号-还款明细披露信息_20260529_已更新0601.xlsx | B226: 0430已还款 | C226: 3 | D226: 107114119448 | E226: 4515 | F226: 4515 | G226: 107114119448 | H226: 46142 | I226: =VLOOKUP(G226,'3已发行数据0610（明道云数据）'!B:N,13,FALSE) -> 信托3号
A227: 美好生活3号-还款明细披露信息_20260529_已更新0601.xlsx | B227: 0430已还款 | C227: 3 | D227: 107114470189 | E227: 4010.14 | F227: 4010.14 | G227: 107114470189 | H227: 46142 | I227: =VLOOKUP(G227,'3已发行数据0610（明道云数据）'!B:N,13,FALSE) -> 信托3号
... A1198: 美好生活2号-还款明细披露信息_20260529_已更新0601.xlsx | B1198: 0119-已还款 | C1198: 2 | D1198: 107113281217 | E1198: 2002.5 | F1198: 2002.5 | G1198: 107113281217 | H1198: 46041 | I1198: =VLOOKUP(G1198,'3已发行数据0610（明道云数据）'!B:N,13,FALSE) -> 信托2号
A1199: 美好生活2号-还款明细披露信息_20260529_已更新0601.xlsx | B1199: 0119-已还款 | C1199: 2 | D1199: 107113281945 | F1199: 2040 | G1199: 107113281945 | H1199: 46041 | I1199: =VLOOKUP(G1199,'3已发行数据0610（明道云数据）'!B:N,13,FALSE) -> 信托2号
A1200: 美好生活2号-还款明细披露信息_20260529_已更新0601.xlsx | B1200: 0119-已还款 | C1200: 2 | D1200: 107113286656 | E1200: 1653 | F1200: 1653 | G1200: 107113286656 | H1200: 46041 | I1200: =VLOOKUP(G1200,'3已发行数据0610（明道云数据）'!B:N,13,FALSE) -> 信托2号
A1201: 美好生活2号-还款明细披露信息_20260529_已更新0601.xlsx | B1201: 0119-已还款 | C1201: 2 | D1201: 107113291829 | E1201: 1840 | F1201: 1840 | G1201: 107113291829 | H1201: 46041 | I1201: =VLOOKUP(G1201,'3已发行数据0610（明道云数据）'!B:N,13,FALSE) -> 信托2号
A1202: 美好生活2号-还款明细披露信息_20260529_已更新0601.xlsx | B1202: 0119-已还款 | C1202: 2 | D1202: 107113296230 | E1202: 2000 | F1202: 2000 | G1202: 107113296230 | H1202: 46041 | I1202: =VLOOKUP(G1202,'3已发行数据0610（明道云数据）'!B:N,13,FALSE) -> 信托2号
A1203: 美好生活2号-还款明细披露信息_20260529_已更新0601.xlsx | B1203: 0119-已还款 | C1203: 2 | D1203: 107113298512 | E1203: 3200 | F1203: 3200 | G1203: 107113298512 | H1203: 46041 | I1203: =VLOOKUP(G1203,'3已发行数据0610（明道云数据）'!B:N,13,FALSE) -> 信托2号
A1204: 美好生活2号-还款明细披露信息_20260529_已更新0601.xlsx | B1204: 0119-已还款 | C1204: 2 | D1204: 107113299896 | E1204: 3528 | F1204: 3528 | G1204: 107113299896 | H1204: 46041 | I1204: =VLOOKUP(G1204,'3已发行数据0610（明道云数据）'!B:N,13,FALSE) -> 信托2号
A1205: 美好生活2号-还款明细披露信息_20260529_已更新0601.xlsx | B1205: 0119-已还款 | C1205: 2 | D1205: 107113304382 | E1205: 2120 | F1205: 2120 | G1205: 107113304382 | H1205: 46041 | I1205: =VLOOKUP(G1205,'3已发行数据0610（明道云数据）'!B:N,13,FALSE) -> 信托2号
A1206: 美好生活2号-还款明细披露信息_20260529_已更新0601.xlsx | B1206: 0119-已还款 | C1206: 2 | D1206: 107113307246 | E1206: 2230 | F1206: 2230 | G1206: 107113307246 | H1206: 46041 | I1206: =VLOOKUP(G1206,'3已发行数据0610（明道云数据）'!B:N,13,FALSE) -> 信托2号
A1207: 美好生活2号-还款明细披露信息_20260529_已更新0601.xlsx | B1207: 0119-已还款 | C1207: 2 | D1207: 107113310327 | E1207: 2450 | F1207: 2450 | G1207: 107113310327 | H1207: 46041 | I1207: =VLOOKUP(G1207,'3已发行数据0610（明道云数据）'!B:N,13,FALSE) -> 信托2号
A1208: 美好生活2号-还款明细披露信息_20260529_已更新0601.xlsx | B1208: 0119-已还款 | C1208: 2 | D1208: 107113314832 | E1208: 2320 | F1208: 2320 | G1208: 107113314832 | H1208: 46041 | I1208: =VLOOKUP(G1208,'3已发行数据0610（明道云数据）'!B:N,13,FALSE) -> 信托2号
A1209: 美好生活2号-还款明细披露信息_20260529_已更新0601.xlsx | B1209: 0119-已还款 | C1209: 2 | D1209: 107113322686 | E1209: 2120 | F1209: 2120 | G1209: 107113322686 | H1209: 46041 | I1209: =VLOOKUP(G1209,'3已发行数据0610（明道云数据）'!B:N,13,FALSE) -> 信托2号
A1210: 美好生活2号-还款明细披露信息_20260529_已更新0601.xlsx | B1210: 0119-已还款 | C1210: 2 | D1210: 107113323285 | E1210: 1720 | F1210: 1720 | G1210: 107113323285 | H1210: 46041 | I1210: =VLOOKUP(G1210,'3已发行数据0610（明道云数据）'!B:N,13,FALSE) -> 信托2号
A1211: 美好生活2号-还款明细披露信息_20260529_已更新0601.xlsx | B1211: 0119-已还款 | C1211: 2 | D1211: 107113323865 | E1211: 2200 | F1211: 2200 | G1211: 107113323865 | H1211: 46041 | I1211: =VLOOKUP(G1211,'3已发行数据0610（明道云数据）'!B:N,13,FALSE) -> 信托2号
... A3422: 美好生活2号-还款明细披露信息_20260529（0608更新） | B3422: 0529-已还款 | C3422: 2 | D3422: 107113422552 | E3422: 3410 | F3422: 3410 | G3422: 107113422552 | H3422: 46171 | I3422: =VLOOKUP(G3422,'3已发行数据0610（明道云数据）'!B:N,13,FALSE) -> 信托2号
A3423: 美好生活1号-还款明细披露信息_20260529_已更新0601_1.xlsx | B3423: 信托还款明细--0929已还款 | C3423: 001 | D3423: 101127075900 | E3423: 0 | F3423: 0 | G3423: 101127075900 | H3423: 45929 | I3423: =VLOOKUP(G3423,'3已发行数据0610（明道云数据）'!B:N,13,FALSE) -> 信托1号
A3424: 美好生活1号-还款明细披露信息_20260529_已更新0601_1.xlsx | B3424: 信托还款明细--0929已还款 | C3424: 001 | D3424: 101127311840 | E3424: 1211.33 | F3424: 1211.33 | G3424: 101127311840 | H3424: 45929 | I3424: =VLOOKUP(G3424,'3已发行数据0610（明道云数据）'!B:N,13,FALSE) -> 信托1号
A3425: 美好生活1号-还款明细披露信息_20260529_已更新0601_1.xlsx | B3425: 信托还款明细--0929已还款 | C3425: 001 | D3425: 101127339909 | E3425: 0 | F3425: 0 | G3425: 101127339909 | H3425: 45929 | I3425: =VLOOKUP(G3425,'3已发行数据0610（明道云数据）'!B:N,13,FALSE) -> 信托1号
A3426: 美好生活1号-还款明细披露信息_20260529_已更新0601_1.xlsx | B3426: 信托还款明细--0929已还款 | C3426: 001 | D3426: 101127524235 | E3426: 2420 | F3426: 2420 | G3426: 101127524235 | H3426: 45929 | I3426: =VLOOKUP(G3426,'3已发行数据0610（明道云数据）'!B:N,13,FALSE) -> 信托1号
A3427: 美好生活1号-还款明细披露信息_20260529_已更新0601_1.xlsx | B3427: 信托还款明细--0929已还款 | C3427: 001 | D3427: 101127626459 | E3427: 0 | F3427: 0 | G3427: 101127626459 | H3427: 45929 | I3427: =VLOOKUP(G3427,'3已发行数据0610（明道云数据）'!B:N,13,FALSE) -> 信托1号
A3428: 美好生活1号-还款明细披露信息_20260529_已更新0601_1.xlsx | B3428: 信托还款明细--0929已还款 | C3428: 001 | D3428: 101127687701 | E3428: 0 | F3428: 0 | G3428: 101127687701 | H3428: 45929 | I3428: =VLOOKUP(G3428,'3已发行数据0610（明道云数据）'!B:N,13,FALSE) -> 信托1号
A3429: 美好生活1号-还款明细披露信息_20260529_已更新0601_1.xlsx | B3429: 信托还款明细--0929已还款 | C3429: 001 | D3429: 101127876784 | E3429: 4160 | F3429: 4160 | G3429: 101127876784 | H3429: 45929 | I3429: =VLOOKUP(G3429,'3已发行数据0610（明道云数据）'!B:N,13,FALSE) -> 信托1号
A3430: 美好生活1号-还款明细披露信息_20260529_已更新0601_1.xlsx | B3430: 信托还款明细--0929已还款 | C3430: 001 | D3430: 101127962550 | E3430: 2835 | F3430: 2835 | G3430: 101127962550 | H3430: 45929 | I3430: =VLOOKUP(G3430,'3已发行数据0610（明道云数据）'!B:N,13,FALSE) -> 信托1号
A3431: 美好生活1号-还款明细披露信息_20260529_已更新0601_1.xlsx | B3431: 信托还款明细--0929已还款 | C3431: 001 | D3431: 101128141006 | E3431: 9263 | F3431: 9263 | G3431: 101128141006 | H3431: 45929 | I3431: =VLOOKUP(G3431,'3已发行数据0610（明道云数据）'!B:N,13,FALSE) -> 信托1号
A3432: 美好生活1号-还款明细披露信息_20260529_已更新0601_1.xlsx | B3432: 信托还款明细--0929已还款 | C3432: 001 | D3432: 101128199395 | E3432: 1719.33 | F3432: 1719.33 | G3432: 101128199395 | H3432: 45929 | I3432: =VLOOKUP(G3432,'3已发行数据0610（明道云数据）'!B:N,13,FALSE) -> 信托1号
A3433: 美好生活1号-还款明细披露信息_20260529_已更新0601_1.xlsx | B3433: 信托还款明细--0929已还款 | C3433: 001 | D3433: 101128199843 | E3433: 3200 | F3433: 3200 | G3433: 101128199843 | H3433: 45929 | I3433: =VLOOKUP(G3433,'3已发行数据0610（明道云数据）'!B:N,13,FALSE) -> 信托1号
A3434: 美好生活1号-还款明细披露信息_20260529_已更新0601_1.xlsx | B3434: 信托还款明细--0929已还款 | C3434: 001 | D3434: 101128209031 | E3434: 1840 | F3434: 1840 | G3434: 101128209031 | H3434: 45929 | I3434: =VLOOKUP(G3434,'3已发行数据0610（明道云数据）'!B:N,13,FALSE) -> 信托1号
... A4582: 美好生活1号-还款明细披露信息_20260529_已更新0601_1.xlsx | B4582: 信托还款明细--0929已还款 | C4582: 001 | D4582: 101127339909 | E4582: 6885 | F4582: 6885 | G4582: 101127339909 | H4582: 45929 | I4582: =VLOOKUP(G4582,'3已发行数据0610（明道云数据）'!B:N,13,FALSE) -> 信托1号
A4583: 美好生活1号-还款明细披露信息_20260529_已更新0601_1.xlsx | B4583: 还款明细--1017已还款 | C4583: 1 | D4583: 101127876784 | E4583: 4160 | F4583: 4160 | G4583: 101127876784 | H4583: 45947 | I4583: =VLOOKUP(G4583,'3已发行数据0610（明道云数据）'!B:N,13,FALSE) -> 信托1号
A4584: 美好生活1号-还款明细披露信息_20260529_已更新0601_1.xlsx | B4584: 还款明细--1017已还款 | C4584: 1 | D4584: 101128199843 | E4584: 3200 | F4584: 3200 | G4584: 101128199843 | H4584: 45947 | I4584: =VLOOKUP(G4584,'3已发行数据0610（明道云数据）'!B:N,13,FALSE) -> 信托1号
A4585: 美好生活1号-还款明细披露信息_20260529_已更新0601_1.xlsx | B4585: 还款明细--1017已还款 | C4585: 1 | D4585: 101128371669 | E4585: 4625 | F4585: 4625 | G4585: 101128371669 | H4585: 45947 | I4585: =VLOOKUP(G4585,'3已发行数据0610（明道云数据）'!B:N,13,FALSE) -> 信托1号
A4586: 美好生活1号-还款明细披露信息_20260529_已更新0601_1.xlsx | B4586: 还款明细--1017已还款 | C4586: 1 | D4586: 101128568095 | E4586: 5035 | F4586: 5035 | G4586: 101128568095 | H4586: 45947 | I4586: =VLOOKUP(G4586,'3已发行数据0610（明道云数据）'!B:N,13,FALSE) -> 信托1号
A4587: 美好生活1号-还款明细披露信息_20260529_已更新0601_1.xlsx | B4587: 还款明细--1017已还款 | C4587: 1 | D4587: 101130798182 | E4587: 5160 | F4587: 5160 | G4587: 101130798182 | H4587: 45947 | I4587: =VLOOKUP(G4587,'3已发行数据0610（明道云数据）'!B:N,13,FALSE) -> 信托1号
A4588: 美好生活1号-还款明细披露信息_20260529_已更新0601_1.xlsx | B4588: 还款明细--1017已还款 | C4588: 1 | D4588: 107112417266 | E4588: 1155 | F4588: 1155 | G4588: 107112417266 | H4588: 45947 | I4588: =VLOOKUP(G4588,'3已发行数据0610（明道云数据）'!B:N,13,FALSE) -> 信托1号
A4589: 美好生活1号-还款明细披露信息_20260529_已更新0601_1.xlsx | B4589: 还款明细--1017已还款 | C4589: 1 | D4589: 107112493987 | E4589: 1118 | F4589: 1118 | G4589: 107112493987 | H4589: 45947 | I4589: =VLOOKUP(G4589,'3已发行数据0610（明道云数据）'!B:N,13,FALSE) -> 信托1号
A4590: 美好生活1号-还款明细披露信息_20260529_已更新0601_1.xlsx | B4590: 还款明细--1017已还款 | C4590: 1 | D4590: 107112594084 | E4590: 3472 | F4590: 3472 | G4590: 107112594084 | H4590: 45947 | I4590: =VLOOKUP(G4590,'3已发行数据0610（明道云数据）'!B:N,13,FALSE) -> 信托1号
A4591: 美好生活1号-还款明细披露信息_20260529_已更新0601_1.xlsx | B4591: 还款明细--1017已还款 | C4591: 1 | D4591: 107112621983 | E4591: 3822 | F4591: 3822 | G4591: 107112621983 | H4591: 45947 | I4591: =VLOOKUP(G4591,'3已发行数据0610（明道云数据）'!B:N,13,FALSE) -> 信托1号
A4592: 美好生活1号-还款明细披露信息_20260529_已更新0601_1.xlsx | B4592: 还款明细--1017已还款 | C4592: 1 | D4592: 107112652329 | E4592: 6624 | F4592: 6624 | G4592: 107112652329 | H4592: 45947 | I4592: =VLOOKUP(G4592,'3已发行数据0610（明道云数据）'!B:N,13,FALSE) -> 信托1号
A4593: 美好生活1号-还款明细披露信息_20260529_已更新0601_1.xlsx | B4593: 还款明细--1017已还款 | C4593: 1 | D4593: 107112719541 | E4593: 864 | F4593: 864 | G4593: 107112719541 | H4593: 45947 | I4593: =VLOOKUP(G4593,'3已发行数据0610（明道云数据）'!B:N,13,FALSE) -> 信托1号
A4594: 美好生活1号-还款明细披露信息_20260529_已更新0601_1.xlsx | B4594: 还款明细--1017已还款 | C4594: 1 | D4594: 107112784036 | E4594: 5292 | F4594: 5292 | G4594: 107112784036 | H4594: 45947 | I4594: =VLOOKUP(G4594,'3已发行数据0610（明道云数据）'!B:N,13,FALSE) -> 信托1号
... A6076: 美好生活1号-还款明细披露信息_20260529_已更新0601_1.xlsx | B6076: 还款明细-0123已还款 | C6076: 1 | D6076: 101127339909 | E6076: 6885 | F6076: 6885 | G6076: 101127339909 | H6076: 46045 | I6076: =VLOOKUP(G6076,'3已发行数据0610（明道云数据）'!B:N,13,FALSE) -> 信托1号
A6077: 美好生活1号-还款明细披露信息_20260529_已更新0601_1.xlsx | B6077: 还款明细-0206已还款 | C6077: 001 | D6077: 107112464864 | E6077: 2736 | F6077: 2736 | G6077: 107112464864 | H6077: 46059 | I6077: =VLOOKUP(G6077,'3已发行数据0610（明道云数据）'!B:N,13,FALSE) -> 信托1号
A6078: 美好生活1号-还款明细披露信息_20260529_已更新0601_1.xlsx | B6078: 还款明细-0206已还款 | C6078: 001 | D6078: 107113022670 | E6078: 4620 | F6078: 4620 | G6078: 107113022670 | H6078: 46059 | I6078: =VLOOKUP(G6078,'3已发行数据0610（明道云数据）'!B:N,13,FALSE) -> 信托1号
A6079: 美好生活1号-还款明细披露信息_20260529_已更新0601_1.xlsx | B6079: 还款明细-0206已还款 | C6079: 001 | D6079: 107113105964 | E6079: 3600 | F6079: 3600 | G6079: 107113105964 | H6079: 46059 | I6079: =VLOOKUP(G6079,'3已发行数据0610（明道云数据）'!B:N,13,FALSE) -> 信托1号
A6080: 美好生活1号-还款明细披露信息_20260529_已更新0601_1.xlsx | B6080: 还款明细-0206已还款 | C6080: 001 | D6080: 101127524235 | E6080: 2420 | F6080: 2420 | G6080: 101127524235 | H6080: 46059 | I6080: =VLOOKUP(G6080,'3已发行数据0610（明道云数据）'!B:N,13,FALSE) -> 信托1号
A6081: 美好生活1号-还款明细披露信息_20260529_已更新0601_1.xlsx | B6081: 还款明细-0206已还款 | C6081: 001 | D6081: 101127876784 | E6081: 4160 | F6081: 4160 | G6081: 101127876784 | H6081: 46059 | I6081: =VLOOKUP(G6081,'3已发行数据0610（明道云数据）'!B:N,13,FALSE) -> 信托1号
A6082: 美好生活1号-还款明细披露信息_20260529_已更新0601_1.xlsx | B6082: 还款明细-0206已还款 | C6082: 001 | D6082: 101127962550 | E6082: 2835 | F6082: 2835 | G6082: 101127962550 | H6082: 46059 | I6082: =VLOOKUP(G6082,'3已发行数据0610（明道云数据）'!B:N,13,FALSE) -> 信托1号
A6083: 美好生活1号-还款明细披露信息_20260529_已更新0601_1.xlsx | B6083: 还款明细-0206已还款 | C6083: 001 | D6083: 101128409796 | E6083: 4853.33 | F6083: 4853.33 | G6083: 101128409796 | H6083: 46059 | I6083: =VLOOKUP(G6083,'3已发行数据0610（明道云数据）'!B:N,13,FALSE) -> 信托1号
A6084: 美好生活1号-还款明细披露信息_20260529_已更新0601_1.xlsx | B6084: 还款明细-0206已还款 | C6084: 001 | D6084: 101130375783 | E6084: 2800 | F6084: 2800 | G6084: 101130375783 | H6084: 46059 | I6084: =VLOOKUP(G6084,'3已发行数据0610（明道云数据）'!B:N,13,FALSE) -> 信托1号
A6085: 美好生活1号-还款明细披露信息_20260529_已更新0601_1.xlsx | B6085: 还款明细-0206已还款 | C6085: 001 | D6085: 101130620233 | E6085: 3840 | F6085: 3840 | G6085: 101130620233 | H6085: 46059 | I6085: =VLOOKUP(G6085,'3已发行数据0610（明道云数据）'!B:N,13,FALSE) -> 信托1号
A6086: 美好生活1号-还款明细披露信息_20260529_已更新0601_1.xlsx | B6086: 还款明细-0206已还款 | C6086: 001 | D6086: 101130708066 | E6086: 2660 | F6086: 2660 | G6086: 101130708066 | H6086: 46059 | I6086: =VLOOKUP(G6086,'3已发行数据0610（明道云数据）'!B:N,13,FALSE) -> 信托1号
A6087: 美好生活1号-还款明细披露信息_20260529_已更新0601_1.xlsx | B6087: 还款明细-0206已还款 | C6087: 001 | D6087: 101130763989 | E6087: 3850 | F6087: 3850 | G6087: 101130763989 | H6087: 46059 | I6087: =VLOOKUP(G6087,'3已发行数据0610（明道云数据）'!B:N,13,FALSE) -> 信托1号
A6088: 美好生活1号-还款明细披露信息_20260529_已更新0601_1.xlsx | B6088: 还款明细-0206已还款 | C6088: 001 | D6088: 101130959533 | E6088: 2250 | F6088: 2250 | G6088: 101130959533 | H6088: 46059 | I6088: =VLOOKUP(G6088,'3已发行数据0610（明道云数据）'!B:N,13,FALSE) -> 信托1号
... A6231: 美好生活1号-还款明细披露信息_20260529_已更新0601_1.xlsx | B6231: 还款明细-0206已还款 | C6231: 001 | D6231: 101129291267 | E6231: 4165 | F6231: 4165 | G6231: 101129291267 | H6231: 46059 | I6231: =VLOOKUP(G6231,'3已发行数据0610（明道云数据）'!B:N,13,FALSE) -> 信托1号
A6232: 美好生活1号-还款明细披露信息_20260529_已更新0601_1.xlsx | B6232: 还款明细-0228已还款 | C6232: 1 | D6232: 107112637443 | E6232: 3240 | F6232: 3240 | G6232: 107112637443 | H6232: 46081 | I6232: =VLOOKUP(G6232,'3已发行数据0610（明道云数据）'!B:N,13,FALSE) -> 信托1号
A6233: 美好生活1号-还款明细披露信息_20260529_已更新0601_1.xlsx | B6233: 还款明细-0228已还款 | C6233: 1 | D6233: 101131458617 | E6233: 2470 | F6233: 2470 | G6233: 101131458617 | H6233: 46081 | I6233: =VLOOKUP(G6233,'3已发行数据0610（明道云数据）'!B:N,13,FALSE) -> 信托1号
A6234: 美好生活1号-还款明细披露信息_20260529_已更新0601_1.xlsx | B6234: 还款明细-0228已还款 | C6234: 1 | D6234: 107112637443 | E6234: 3240 | F6234: 3240 | G6234: 107112637443 | H6234: 46081 | I6234: =VLOOKUP(G6234,'3已发行数据0610（明道云数据）'!B:N,13,FALSE) -> 信托1号
A6235: 美好生活1号-还款明细披露信息_20260529_已更新0601_1.xlsx | B6235: 还款明细-0228已还款 | C6235: 1 | D6235: 101127311840 | E6235: 1132.33 | F6235: 1132.33 | G6235: 101127311840 | H6235: 46081 | I6235: =VLOOKUP(G6235,'3已发行数据0610（明道云数据）'!B:N,13,FALSE) -> 信托1号
A6236: 美好生活1号-还款明细披露信息_20260529_已更新0601_1.xlsx | B6236: 还款明细-0228已还款 | C6236: 1 | D6236: 101128141006 | E6236: 9263 | F6236: 9263 | G6236: 101128141006 | H6236: 46081 | I6236: =VLOOKUP(G6236,'3已发行数据0610（明道云数据）'!B:N,13,FALSE) -> 信托1号
A6237: 美好生活1号-还款明细披露信息_20260529_已更新0601_1.xlsx | B6237: 还款明细-0228已还款 | C6237: 1 | D6237: 101128199843 | E6237: 3200 | F6237: 3200 | G6237: 101128199843 | H6237: 46081 | I6237: =VLOOKUP(G6237,'3已发行数据0610（明道云数据）'!B:N,13,FALSE) -> 信托1号
A6238: 美好生活1号-还款明细披露信息_20260529_已更新0601_1.xlsx | B6238: 还款明细-0228已还款 | C6238: 1 | D6238: 101128371669 | E6238: 4625 | F6238: 4625 | G6238: 101128371669 | H6238: 46081 | I6238: =VLOOKUP(G6238,'3已发行数据0610（明道云数据）'!B:N,13,FALSE) -> 信托1号
A6239: 美好生活1号-还款明细披露信息_20260529_已更新0601_1.xlsx | B6239: 还款明细-0228已还款 | C6239: 1 | D6239: 101128568095 | E6239: 5035 | F6239: 5035 | G6239: 101128568095 | H6239: 46081 | I6239: =VLOOKUP(G6239,'3已发行数据0610（明道云数据）'!B:N,13,FALSE) -> 信托1号
A6240: 美好生活1号-还款明细披露信息_20260529_已更新0601_1.xlsx | B6240: 还款明细-0228已还款 | C6240: 1 | D6240: 101130950078 | E6240: 4216 | F6240: 4216 | G6240: 101130950078 | H6240: 46081 | I6240: =VLOOKUP(G6240,'3已发行数据0610（明道云数据）'!B:N,13,FALSE) -> 信托1号
A6241: 美好生活1号-还款明细披露信息_20260529_已更新0601_1.xlsx | B6241: 还款明细-0228已还款 | C6241: 1 | D6241: 107112417266 | E6241: 1155 | F6241: 1155 | G6241: 107112417266 | H6241: 46081 | I6241: =VLOOKUP(G6241,'3已发行数据0610（明道云数据）'!B:N,13,FALSE) -> 信托1号
A6242: 美好生活1号-还款明细披露信息_20260529_已更新0601_1.xlsx | B6242: 还款明细-0228已还款 | C6242: 1 | D6242: 107112493987 | E6242: 1118 | F6242: 1118 | G6242: 107112493987 | H6242: 46081 | I6242: =VLOOKUP(G6242,'3已发行数据0610（明道云数据）'!B:N,13,FALSE) -> 信托1号
A6243: 美好生活1号-还款明细披露信息_20260529_已更新0601_1.xlsx | B6243: 还款明细-0228已还款 | C6243: 1 | D6243: 107112621983 | E6243: 3822 | F6243: 3822 | G6243: 107112621983 | H6243: 46081 | I6243: =VLOOKUP(G6243,'3已发行数据0610（明道云数据）'!B:N,13,FALSE) -> 信托1号
... A7974: 美好生活3号-还款明细披露信息_20260605.xlsx | B7974: 0605已还款 | C7974: 3 | D7974: 101128210944 | E7974: 7000 | F7974: 7000 | G7974: 101128210944 | H7974: 46178 | I7974: =VLOOKUP(G7974,'3已发行数据0610（明道云数据）'!B:N,13,FALSE) -> 单一信托,信托3号
A7975: 美润1号_还款明细表_0605.xlsx | B7975: 0605已还款 | C7975: 单一-001 | D7975: 107112256785 | E7975: 1972 | F7975: 1972 | G7975: 107112256785 | H7975: 46178 | I7975: =VLOOKUP(G7975,'3已发行数据0610（明道云数据）'!B:N,13,FALSE) -> 单一信托
A7976: 美润1号_还款明细表_0605.xlsx | B7976: 0605已还款 | C7976: 单一-001 | D7976: 107113089723 | E7976: 2800 | F7976: 2800 | G7976: 107113089723 | H7976: 46178 | I7976: =VLOOKUP(G7976,'3已发行数据0610（明道云数据）'!B:N,13,FALSE) -> 单一信托
A7977: 美润1号_还款明细表_0605.xlsx | B7977: 0605已还款 | C7977: 单一-001 | D7977: 107112390518 | E7977: 2610 | F7977: 2610 | G7977: 107112390518 | H7977: 46178 | I7977: =VLOOKUP(G7977,'3已发行数据0610（明道云数据）'!B:N,13,FALSE) -> 单一信托
A7978: 美润1号_还款明细表_0605.xlsx | B7978: 0605已还款 | C7978: 单一-001 | D7978: 107112311362 | E7978: 1368 | F7978: 1368 | G7978: 107112311362 | H7978: 46178 | I7978: =VLOOKUP(G7978,'3已发行数据0610（明道云数据）'!B:N,13,FALSE) -> 单一信托
A7979: 美润1号_还款明细表_0605.xlsx | B7979: 0605已还款 | C7979: 单一-001 | D7979: 107112371893 | E7979: 3825 | F7979: 3825 | G7979: 107112371893 | H7979: 46178 | I7979: =VLOOKUP(G7979,'3已发行数据0610（明道云数据）'!B:N,13,FALSE) -> 单一信托
A7980: 美润1号_还款明细表_0605.xlsx | B7980: 0605已还款 | C7980: 单一-001 | D7980: 107112573096 | E7980: 9100 | F7980: 9100 | G7980: 107112573096 | H7980: 46178 | I7980: =VLOOKUP(G7980,'3已发行数据0610（明道云数据）'!B:N,13,FALSE) -> 单一信托
A7981: 美润1号_还款明细表_0605.xlsx | B7981: 0605已还款 | C7981: 单一-001 | D7981: 107112457173 | E7981: 1755 | F7981: 1755 | G7981: 107112457173 | H7981: 46178 | I7981: =VLOOKUP(G7981,'3已发行数据0610（明道云数据）'!B:N,13,FALSE) -> 单一信托
...

Sheet 2更新的资产数据表
A1: 文件名 | B1: 资产包编号 | C1: 托管房源编码 | D1: 统计日期 | E1: 初始受让金额 | F1: 已还款金额 | G1: 剩余还款金额 | H1: 资产状态 | I1: 最后一期装修款付款时间 | J1: 城市 | K1: 当前信托计划（已发行）
A2: 美好生活1号-资产监控表_0612 | B2: 1 | C2: 107112824234 | D2: 46185 | E2: 94000 | F2: 32800 | G2: 61200 | H2: 正常 | I2: 46794 | J2: 上海 | K2: =VLOOKUP(C2,'3已发行数据0610（明道云数据）'!B:N,13,FALSE) -> 信托1号
A3: 美好生活1号-资产监控表_0612 | B3: 1 | C3: 107111763962 | D3: 46185 | E3: 19454 | F3: 12155 | G3: 7299 | H3: 正常 | I3: 46367 | J3: 上海 | K3: =VLOOKUP(C3,'3已发行数据0610（明道云数据）'!B:N,13,FALSE) -> 信托1号
A4: 美好生活1号-资产监控表_0612 | B4: 1 | C4: 107112807713 | D4: 46185 | E4: 88800 | F4: 27753 | G4: 61047 | H4: 正常 | I4: 46794 | J4: 上海 | K4: =VLOOKUP(C4,'3已发行数据0610（明道云数据）'!B:N,13,FALSE) -> 信托1号
A5: 美好生活1号-资产监控表_0612 | B5: 1 | C5: 107112466550 | D5: 46185 | E5: 118000 | F5: 44370 | G5: 73630 | H5: 正常 | I5: 46794 | J5: 上海 | K5: =VLOOKUP(C5,'3已发行数据0610（明道云数据）'!B:N,13,FALSE) -> 信托1号
A6: 美好生活1号-资产监控表_0612 | B6: 1 | C6: 101129877193 | D6: 46185 | E6: 100000 | F6: 58703.33 | G6: 41296.67 | H6: 正常 | I6: 46429 | J6: 北京 | K6: =VLOOKUP(C6,'3已发行数据0610（明道云数据）'!B:N,13,FALSE) -> 信托1号
A7: 美好生活1号-资产监控表_0612 | B7: 1 | C7: 101131064033 | D7: 46185 | E7: 82153 | F7: 29700 | G7: 52453 | H7: 正常 | I7: 46732 | J7: 北京 | K7: =VLOOKUP(C7,'3已发行数据0610（明道云数据）'!B:N,13,FALSE) -> 信托1号
A8: 美好生活1号-资产监控表_0612 | B8: 1 | C8: 107113051629 | D8: 46185 | E8: 100146 | F8: 33188 | G8: 66958 | H8: 正常 | I8: 46794 | J8: 上海 | K8: =VLOOKUP(C8,'3已发行数据0610（明道云数据）'!B:N,13,FALSE) -> 信托1号
A9: 美好生活1号-资产监控表_0612 | B9: 1 | C9: 107112808068 | D9: 46185 | E9: 92468 | F9: 29370 | G9: 63098 | H9: 正常 | I9: 46854 | J9: 上海 | K9: =VLOOKUP(C9,'3已发行数据0610（明道云数据）'!B:N,13,FALSE) -> 信托1号
A10: 美好生活1号-资产监控表_0612 | B10: 1 | C10: 101128689163 | D10: 46185 | E10: 160000 | F10: 58000 | G10: 102000 | H10: 正常 | I10: 46732 | J10: 北京 | K10: =VLOOKUP(C10,'3已发行数据0610（明道云数据）'!B:N,13,FALSE) -> 信托1号
A11: 美好生活1号-资产监控表_0612 | B11: 1 | C11: 107112571761 | D11: 46185 | E11: 110000 | F11: 37490 | G11: 72510 | H11: 正常 | I11: 46763 | J11: 上海 | K11: =VLOOKUP(C11,'3已发行数据0610（明道云数据）'!B:N,13,FALSE) -> 信托1号
A12: 美好生活1号-资产监控表_0612 | B12: 1 | C12: 107113057210 | D12: 46185 | E12: 70000 | F12: 20375 | G12: 49625 | H12: 正常 | I12: 46823 | J12: 上海 | K12: =VLOOKUP(C12,'3已发行数据0610（明道云数据）'!B:N,13,FALSE) -> 信托1号
A13: 美好生活1号-资产监控表_0612 | B13: 1 | C13: 107112464864 | D13: 46185 | E13: 89000 | F13: 22650 | G13: 66350 | H13: 正常 | I13: 46854 | J13: 上海 | K13: =VLOOKUP(C13,'3已发行数据0610（明道云数据）'!B:N,13,FALSE) -> 信托1号
... A1130: 美好生活3号-资产监控表_0612 | B1130: 3 | C1130: 107112417471 | D1130: 46185 | E1130: 7267 | F1130: 2304 | G1130: 4963 | H1130: 正常 | I1130: 46272 | J1130: 上海 | K1130: =VLOOKUP(C1130,'3已发行数据0610（明道云数据）'!B:N,13,FALSE) -> 单一信托,信托3号
A1131: 美润1号资产监控表_0612 | B1131: 单一001 | C1131: 107112271059 | D1131: 46185 | E1131: 99000 | F1131: 24570 | G1131: 74430 | H1131: 正常 | I1131: 47294 | J1131: 上海 | K1131: =VLOOKUP(C1131,'3已发行数据0610（明道云数据）'!B:N,13,FALSE) -> 单一信托
A1132: 美润1号资产监控表_0612 | B1132: 单一001 | C1132: 107112256785 | D1132: 46186 | E1132: 96716 | F1132: 27699 | G1132: 69017 | H1132: 正常 | I1132: 47213 | J1132: 上海 | K1132: =VLOOKUP(C1132,'3已发行数据0610（明道云数据）'!B:N,13,FALSE) -> 单一信托
A1133: 美润1号资产监控表_0612 | B1133: 单一001 | C1133: 107112225568 | D1133: 46187 | E1133: 88000 | F1133: 22827 | G1133: 65173 | H1133: 正常 | I1133: 47197 | J1133: 上海 | K1133: =VLOOKUP(C1133,'3已发行数据0610（明道云数据）'!B:N,13,FALSE) -> 单一信托
A1134: 美润1号资产监控表_0612 | B1134: 单一001 | C1134: 107113089723 | D1134: 46188 | E1134: 107797 | F1134: 20850 | G1134: 86947 | H1134: 正常 | I1134: 47148 | J1134: 上海 | K1134: =VLOOKUP(C1134,'3已发行数据0610（明道云数据）'!B:N,13,FALSE) -> 单一信托
A1135: 美润1号资产监控表_0612 | B1135: 单一001 | C1135: 107112317928 | D1135: 46189 | E1135: 83000 | F1135: 20844 | G1135: 62156 | H1135: 正常 | I1135: 47255 | J1135: 上海 | K1135: =VLOOKUP(C1135,'3已发行数据0610（明道云数据）'!B:N,13,FALSE) -> 单一信托
A1136: 美润1号资产监控表_0612 | B1136: 单一001 | C1136: 107112727179 | D1136: 46190 | E1136: 82000 | F1136: 18876 | G1136: 63124 | H1136: 正常 | I1136: 47411 | J1136: 上海 | K1136: =VLOOKUP(C1136,'3已发行数据0610（明道云数据）'!B:N,13,FALSE) -> 单一信托
A1137: 美润1号资产监控表_0612 | B1137: 单一001 | C1137: 107112384180 | D1137: 46191 | E1137: 159424 | F1137: 40262 | G1137: 119162 | H1137: 正常 | I1137: 47283 | J1137: 上海 | K1137: =VLOOKUP(C1137,'3已发行数据0610（明道云数据）'!B:N,13,FALSE) -> 单一信托
A1138: 美润1号资产监控表_0612 | B1138: 单一001 | C1138: 107112483866 | D1138: 46192 | E1138: 80000 | F1138: 19980 | G1138: 60020 | H1138: 正常 | I1138: 47447 | J1138: 上海 | K1138: =VLOOKUP(C1138,'3已发行数据0610（明道云数据）'!B:N,13,FALSE) -> 单一信托
A1139: 美润1号资产监控表_0612 | B1139: 单一001 | C1139: 107112390518 | D1139: 46193 | E1139: 130000 | F1139: 28919 | G1139: 101081 | H1139: 正常 | I1139: 47289 | J1139: 上海 | K1139: =VLOOKUP(C1139,'3已发行数据0610（明道云数据）'!B:N,13,FALSE) -> 单一信托
A1140: 美润1号资产监控表_0612 | B1140: 单一001 | C1140: 107112311362 | D1140: 46194 | E1140: 68500 | F1140: 16416 | G1140: 52084 | H1140: 正常 | I1140: 47389 | J1140: 上海 | K1140: =VLOOKUP(C1140,'3已发行数据0610（明道云数据）'!B:N,13,FALSE) -> 单一信托
A1141: 美润1号资产监控表_0612 | B1141: 单一001 | C1141: 107112488326 | D1141: 46195 | E1141: 97000 | F1141: 24096 | G1141: 72904 | H1141: 正常 | I1141: 47316 | J1141: 上海 | K1141: =VLOOKUP(C1141,'3已发行数据0610（明道云数据）'!B:N,13,FALSE) -> 单一信托
A1142: 美润1号资产监控表_0612 | B1142: 单一001 | C1142: 107112218005 | D1142: 46196 | E1142: 121680 | F1142: 24440 | G1142: 97240 | H1142: 正常 | I1142: 47401 | J1142: 上海 | K1142: =VLOOKUP(C1142,'3已发行数据0610（明道云数据）'!B:N,13,FALSE) -> 单一信托
... A1257: 美润1号资产监控表_0612 | B1257: 单一001 | C1257: 107113468759 | D1257: 46311 | E1257: 385000 | F1257: 29160 | G1257: 355840 | H1257: 正常 | I1257: 47305 | J1257: 上海 | K1257: =VLOOKUP(C1257,'3已发行数据0610（明道云数据）'!B:N,13,FALSE) -> 单一信托（2号）

Sheet 3已发行数据0610（明道云数据）
A1: 预计代扣周期-最初 | B1: 房源编码 | C1: 房源地址 | D1: 所属城市 | E1: 品牌 | F1: 签约日期 | G1: 实际成交价（应收账款合同金额） | H1: 代扣金额 | I1: 装修付款形式 | J1: 业主付款金额 | K1: 施工方名称 | L1: 入池批次 | M1: 信托计划期数 | N1: 当前信托计划（已发行） | O1: 检查核对发行情况
A2: 8 | B2: 107112524298 | C2: 上海市青浦区灿耀星城徐安路28弄21号-1302 | D2: 上海 | E2: 山念 | F2: 45795 | G2: 24963 | H2: 24963 | I2: 租金代扣 | J2: 0 | K2: 天津冠唯装饰工程有限公司 | L2: 412批次 | M2: 412批次 | N2: 信托1号 | O2: =VLOOKUP(B2,'4已发行数据（原始入池数据表格）'!C:C,1,FALSE) -> 107112524298
A3: 9 | B3: 107112765383 | C3: 上海市青浦区徐泾镇沪青平公路1758弄逸品名邸（中铁 虹桥逸都）48号302 | D3: 上海 | E3: 山念 | F3: 45792 | G3: 23283 | H3: 23283 | I3: 租金代扣 | J3: 0 | K3: 天津冠唯装饰工程有限公司 | L3: 412批次 | M3: 412批次 | N3: 信托1号 | O3: =VLOOKUP(B3,'4已发行数据（原始入池数据表格）'!C:C,1,FALSE) -> 107112765383
A4: 7 | B4: 107112708646 | C4: 徐泾镇沪青平公路1758弄48号1001室 | D4: 上海 | E4: 山念 | F4: 45792 | G4: 22732 | H4: 22732 | I4: 租金代扣 | J4: 0 | K4: 天津冠唯装饰工程有限公司 | L4: 412批次 | M4: 412批次 | N4: 信托1号 | O4: =VLOOKUP(B4,'4已发行数据（原始入池数据表格）'!C:C,1,FALSE) -> 107112708646
A5: 10 | B5: 107112795213 | C5: 上海市黄浦区瑞宁路8弄御江廷3号2505 | D5: 上海 | E5: 山念 | F5: 45787 | G5: 25732 | H5: 25732 | I5: 租金代扣 | J5: 0 | K5: 住与家（上海）装饰设计有限公司 | L5: 第二批 | M5: 第二批 | N5: 信托2号 | O5: =VLOOKUP(B5,'4已发行数据（原始入池数据表格）'!C:C,1,FALSE) -> 107112795213
A6: 7 | B6: 107112775650 | C6: 松江区九亭镇伴亭路855弄14号601 | D6: 上海 | E6: 山念 | F6: 45781 | G6: 30538 | H6: 30583 | I6: 租金代扣 | J6: 0 | K6: 天津冠唯装饰工程有限公司 | L6: 412批次 | M6: 412批次 | N6: 信托1号 | O6: =VLOOKUP(B6,'4已发行数据（原始入池数据表格）'!C:C,1,FALSE) -> 107112775650
A7: 20 | B7: 107112675513 | C7: 上海市静安区泰兴路362弄25号103 | D7: 上海 | E7: 山念 | F7: 45770 | G7: 68787 | H7: 68787 | I7: 租金代扣 | J7: 0 | K7: 上海沪慧荣建筑装饰有限公司 | L7: 412批次 | M7: 412批次 | N7: 信托1号 | O7: =VLOOKUP(B7,'4已发行数据（原始入池数据表格）'!C:C,1,FALSE) -> 107112675513
A8: 20 | B8: 101129590806 | C8: 北京市东城区安定门外大街10-1303 | D8: 北京 | E8: 焕新租 | F8: 45769 | G8: 94515.6 | H8: 94515 | I8: 租金代扣 | J8: 0 | K8: 北京致一建设有限公司 | L8: 412批次 | M8: 412批次 | N8: 信托1号 | O8: =VLOOKUP(B8,'4已发行数据（原始入池数据表格）'!C:C,1,FALSE) -> 101129590806
A9: 6 | B9: 107112663876 | C9: 上海市浦东新区中企云萃森林(东区)钟晓路257弄27号2004室 | D9: 上海 | E9: 怡穗 | F9: 45768 | G9: 19087 | H9: 19087 | I9: 租金代扣 | J9: 0 | K9: 上海庆苑建筑装饰集团有限公司 | L9: 412批次 | M9: 412批次 | N9: 信托1号 | O9: =VLOOKUP(B9,'4已发行数据（原始入池数据表格）'!C:C,1,FALSE) -> 107112663876
A10: 20 | B10: 107112654601 | C10: 上海市宝山区宝林八村97号502 | D10: 上海 | E10: 山念 | F10: 45768 | G10: 136196 | H10: 107595 | I10: 业主付款+租金代扣 | J10: 28601 | K10: 上海千盛邦建筑装饰有限公司 | L10: 412批次 | M10: 412批次 | N10: 信托1号 | O10: =VLOOKUP(B10,'4已发行数据（原始入池数据表格）'!C:C,1,FALSE) -> 107112654601
A11: 9 | B11: 101129927216 | C11: 北京市朝阳区裕民路4号院1号楼3单元8号 | D11: 北京 | E11: 焕新租 | F11: 45768 | G11: 86485 | H11: 86485 | I11: 租金代扣 | J11: 0 | K11: 北京致一建设有限公司 | L11: 412批次 | M11: 412批次 | N11: 信托1号 | O11: =VLOOKUP(B11,'4已发行数据（原始入池数据表格）'!C:C,1,FALSE) -> 101129927216
A12: 20 | B12: 107112556607 | C12: 上海市长宁区新泾镇仙霞路1225弄113号302 | D12: 上海 | E12: 山念 | F12: 45768 | G12: 119603 | H12: 119603 | I12: 租金代扣 | J12: 0 | K12: 天津冠唯装饰工程有限公司 | L12: 412批次 | M12: 412批次 | N12: 信托1号 | O12: =VLOOKUP(B12,'4已发行数据（原始入池数据表格）'!C:C,1,FALSE) -> 107112556607
A13: 6 | B13: 107112705537 | C13: 徐泾镇沪青平公路1758弄52号楼1101室 | D13: 上海 | E13: 山念 | F13: 45767 | G13: 24606 | H13: 24606 | I13: 租金代扣 | J13: 0 | K13: 天津冠唯装饰工程有限公司 | L13: 412批次 | M13: 412批次 | N13: 信托1号 | O13: =VLOOKUP(B13,'4已发行数据（原始入池数据表格）'!C:C,1,FALSE) -> 107112705537
A14: 26 | B14: 107112660445 | C14: 上海市普陀区宜川五村47号104室 | D14: 上海 | E14: 山念 | F14: 45767 | G14: 97000 | H14: 95414 | I14: 租金代扣 | K14: 上海千盛邦建筑装饰有限公司 | L14: 412批次 | M14: 412批次 | N14: 信托1号 | O14: =VLOOKUP(B14,'4已发行数据（原始入池数据表格）'!C:C,1,FALSE) -> 107112660445
A15: 8 | B15: 107112610123 | C15: 徐泾镇泾南河路79弄璀璨名邸49号16层1602室 | D15: 上海 | E15: 山念 | F15: 45767 | G15: 25490 | H15: 25490 | I15: 租金代扣 | J15: 0 | K15: 天津冠唯装饰工程有限公司 | L15: 412批次 | M15: 412批次 | N15: 信托1号 | O15: =VLOOKUP(B15,'4已发行数据（原始入池数据表格）'!C:C,1,FALSE) -> 107112610123
A16: 6 | B16: 107112587444 | C16: 徐泾镇蟠和路188弄蟠龙云邸25号5层502 | D16: 上海 | E16: 山念 | F16: 45766 | G16: 27578 | H16: 27578 | I16: 租金代扣 | J16: 0 | K16: 天津冠唯装饰工程有限公司 | L16: 412批次 | M16: 412批次 | N16: 信托1号 | O16: =VLOOKUP(B16,'4已发行数据（原始入池数据表格）'!C:C,1,FALSE) -> 107112587444
A17: 7 | B17: 107112575884 | C17: 徐泾镇沪青平公路1758弄逸品名邸26号1层101室 | D17: 上海 | E17: 山念 | F17: 45766 | G17: 23001 | H17: 23001 | I17: 租金代扣 | J17: 0 | K17: 天津冠唯装饰工程有限公司 | L17: 412批次 | M17: 412批次 | N17: 信托1号 | O17: =VLOOKUP(B17,'4已发行数据（原始入池数据表格）'!C:C,1,FALSE) -> 107112575884
A18: 9 | B18: 107112629770 | C18: 上海市闵行区通海路268弄23号701 | D18: 上海 | E18: 山念 | F18: 45766 | G18: 25912 | H18: 25912 | I18: 租金代扣 | J18: 0 | K18: 南京和艺优装饰工程有限公司 | L18: 412批次 | M18: 412批次 | N18: 信托1号 | O18: =VLOOKUP(B18,'4已发行数据（原始入池数据表格）'!C:C,1,FALSE) -> 107112629770
A19: 19 | B19: 107112640254 | C19: 上海宝山中怡家园09号楼09单元2301 | D19: 上海 | E19: 山念 | F19: 45765 | G19: 37493 | H19: 37493 | I19: 租金代扣 | J19: 0 | K19: 上海长聚建筑工程有限公司 | L19: 412批次 | M19: 412批次 | N19: 信托1号 | O19: =VLOOKUP(B19,'4已发行数据（原始入池数据表格）'!C:C,1,FALSE) -> 107112640254
A20: 20 | B20: 107112509729 | C20: 宝山区松南镇一二八纪念路55弄100号401 | D20: 上海 | E20: 山念 | F20: 45764 | G20: 132000 | H20: 132000 | I20: 租金代扣 | J20: 0 | K20: 上海速信佳装饰工程有限公司 | L20: 412批次 | M20: 412批次 | N20: 信托1号 | O20: =VLOOKUP(B20,'4已发行数据（原始入池数据表格）'!C:C,1,FALSE) -> 107112509729
A21: 19 | B21: 107112499423 | C21: 上海市宝山共江小区136号602 | D21: 上海 | E21: 山念 | F21: 45764 | G21: 77000 | H21: 77000 | I21: 租金代扣 | J21: 0 | K21: 上海速信佳装饰工程有限公司 | L21: 412批次 | M21: 412批次 | N21: 信托1号 | O21: =VLOOKUP(B21,'4已发行数据（原始入池数据表格）'!C:C,1,FALSE) -> 107112499423
A22: 20 | B22: 107112602426 | C22: 上海市浦东新区临沂路181弄1号504室 | D22: 上海 | E22: 山念 | F22: 45763 | G22: 101368.6 | H22: 101368 | I22: 租金代扣 | J22: 0 | K22: 上海庆苑建筑装饰集团有限公司 | L22: 412批次 | M22: 412批次 | N22: 信托1号 | O22: =VLOOKUP(B22,'4已发行数据（原始入池数据表格）'!C:C,1,FALSE) -> 107112602426
A23: 8 | B23: 107112617499 | C23: 上海市闵行区通海路268弄2号楼101室 | D23: 上海 | E23: 山念 | F23: 45762 | G23: 25912 | H23: 25912 | I23: 租金代扣 | K23: 南京和艺优装饰工程有限公司 | L23: 412批次 | M23: 412批次 | N23: 信托1号 | O23: =VLOOKUP(B23,'4已发行数据（原始入池数据表格）'!C:C,1,FALSE) -> 107112617499
A24: 8 | B24: 107112652640 | C24: 徐泾镇沪青平公路1758弄逸品名邸12号7层702室 | D24: 上海 | E24: 山念 | F24: 45762 | G24: 27758 | H24: 27758 | I24: 租金代扣 | J24: 0 | K24: 天津冠唯装饰工程有限公司 | L24: 412批次 | M24: 412批次 | N24: 信托1号 | O24: =VLOOKUP(B24,'4已发行数据（原始入池数据表格）'!C:C,1,FALSE) -> 107112652640
A25: 22 | B25: 107112596941 | C25: 上海市徐汇区大木小区237弄8号501室 | D25: 上海 | E25: 山念 | F25: 45761 | G25: 106330 | H25: 106330 | I25: 租金代扣 | J25: 0 | K25: 上海沪慧荣建筑装饰有限公司 | L25: 第二批 | M25: 第二批 | N25: 信托2号 | O25: =VLOOKUP(B25,'4已发行数据（原始入池数据表格）'!C:C,1,FALSE) -> 107112596941
A26: 19 | B26: 107112608464 | C26: 上海市中山南一路1109弄康衢小区1号307室 | D26: 上海 | E26: 山念 | F26: 45761 | G26: 78025 | H26: 78025 | I26: 租金代扣 | J26: 0 | K26: 上海沪慧荣建筑装饰有限公司 | L26: 412批次 | M26: 412批次 | N26: 信托1号 | O26: =VLOOKUP(B26,'4已发行数据（原始入池数据表格）'!C:C,1,FALSE) -> 107112608464
A27: 19 | B27: 101129954626 | C27: 北京市朝阳区东大桥路57号楼3门10 | D27: 北京 | E27: 焕新租 | F27: 45761 | G27: 83860 | H27: 83860 | I27: 租金代扣 | J27: 0 | K27: 北京贝乐禾装饰有限公司 | L27: 412批次 | M27: 412批次 | N27: 信托1号 | O27: =VLOOKUP(B27,'4已发行数据（原始入池数据表格）'!C:C,1,FALSE) -> 101129954626
A28: 20 | B28: 107112587852 | C28: 上海市长宁区仙霞新村街道茅台路 500 弄茅台花苑小区 6-1109 | D28: 上海 | E28: 山念 | F28: 45761 | G28: 135731 | H28: 135731 | I28: 租金代扣 | J28: 0 | K28: 天津冠唯装饰工程有限公司 | L28: 412批次 | M28: 412批次 | N28: 信托1号 | O28: =VLOOKUP(B28,'4已发行数据（原始入池数据表格）'!C:C,1,FALSE) -> 107112587852
A29: 27 | B29: 107112535561 | C29: 上海静安区长乐路1232弄610 | D29: 上海 | E29: 山念 | F29: 45760 | G29: 101346 | H29: 101346 | I29: 租金代扣 | J29: 0 | K29: 上海沪慧荣建筑装饰有限公司 | L29: 412批次 | M29: 412批次 | N29: 信托1号 | O29: =VLOOKUP(B29,'4已发行数据（原始入池数据表格）'!C:C,1,FALSE) -> 107112535561
A30: 8 | B30: 101129460405 | C30: 北京市海淀区中关村南大街12号院四区12号楼2单元405 | D30: 北京 | E30: 焕新租 | F30: 45760 | G30: 73000 | H30: 73000 | I30: 租金代扣 | K30: 上海虬诗建设有限公司 | L30: 412批次 | M30: 412批次 | N30: 信托1号 | O30: =VLOOKUP(B30,'4已发行数据（原始入池数据表格）'!C:C,1,FALSE) -> 101129460405
A31: 6 | B31: 107112568721 | C31: 上海市乐中路 66 弄 10 号 701 | D31: 上海 | E31: 怡穗 | F31: 45759 | G31: 44480 | H31: 44480 | I31: 租金代扣 | K31: 南京和艺优装饰工程有限公司 | L31: 412批次 | M31: 412批次 | N31: 信托1号 | O31: =VLOOKUP(B31,'4已发行数据（原始入池数据表格）'!C:C,1,FALSE) -> 107112568721
A32: 22 | B32: 107112589042 | C32: 上海宝山古北菊翔苑菊联路232弄21单元0403 | D32: 上海 | E32: 山念 | F32: 45759 | G32: 130000 | H32: 130000 | I32: 租金代扣 | J32: 0 | K32: 上海长聚建筑工程有限公司 | L32: 第二批 | M32: 第二批 | N32: 信托2号 | O32: =VLOOKUP(B32,'4已发行数据（原始入池数据表格）'!C:C,1,FALSE) -> 107112589042
A33: 8 | B33: 107112552822 | C33: 上海市松江区广富林路658弄215号402室 | D33: 上海 | E33: 山念 | F33: 45758 | G33: 8910 | H33: 8910 | I33: 租金代扣 | J33: 0 | K33: 上海沪慧荣建筑装饰有限公司 | L33: 412批次 | M33: 412批次 | N33: 信托1号 | O33: =VLOOKUP(B33,'4已发行数据（原始入池数据表格）'!C:C,1,FALSE) -> 107112552822
A34: 7 | B34: 107112504607 | C34: 上海市青浦区赵巷镇佳杰路金地虹桥峯汇23-1101 | D34: 上海 | E34: 山念 | F34: 45758 | G34: 28225 | H34: 28225 | I34: 租金代扣 | J34: 0 | K34: 天津冠唯装饰工程有限公司 | L34: 412批次 | M34: 412批次 | N34: 信托1号 | O34: =VLOOKUP(B34,'4已发行数据（原始入池数据表格）'!C:C,1,FALSE) -> 107112504607
A35: 20 | B35: 107112562410 | C35: 上海市长宁区虹桥街道虹梅路 3888 弄延北小区 23 号 402 | D35: 上海 | E35: 山念 | F35: 45758 | G35: 78200 | H35: 78200 | I35: 租金代扣 | J35: 0 | K35: 天津冠唯装饰工程有限公司 | L35: 412批次 | M35: 412批次 | N35: 信托1号 | O35: =VLOOKUP(B35,'4已发行数据（原始入池数据表格）'!C:C,1,FALSE) -> 107112562410
A36: 7 | B36: 107112576388 | C36: 徐泾镇沪青平公路1758弄虹桥逸都26号1层102室 | D36: 上海 | E36: 山念 | F36: 45758 | G36: 31400 | H36: 31400 | I36: 租金代扣 | J36: 0 | K36: 天津冠唯装饰工程有限公司 | L36: 412批次 | M36: 412批次 | N36: 信托1号 | O36: =VLOOKUP(B36,'4已发行数据（原始入池数据表格）'!C:C,1,FALSE) -> 107112576388
A37: 9 | B37: 101129734313 | C37: 北京市朝阳区麦子店街7号楼5单元401室 | D37: 北京 | E37: 焕新租 | F37: 45758 | G37: 79477 | H37: 79477 | I37: 租金代扣 | J37: 0 | K37: 北京致一建设有限公司 | L37: 412批次 | M37: 412批次 | N37: 信托1号 | O37: =VLOOKUP(B37,'4已发行数据（原始入池数据表格）'!C:C,1,FALSE) -> 101129734313
A38: 20 | B38: 107112538502 | C38: 上海市浦东新区崂山六村浦东大道290弄21号203室 | D38: 上海 | E38: 山念 | F38: 45757 | G38: 99900 | H38: 99900 | I38: 租金代扣 | K38: 上海庆苑建筑装饰集团有限公司 | L38: 412批次 | M38: 412批次 | N38: 信托1号 | O38: =VLOOKUP(B38,'4已发行数据（原始入池数据表格）'!C:C,1,FALSE) -> 107112538502
A39: 20 | B39: 107112557175 | C39: 上海杨浦双阳路 490 弄 03 号楼 03 单元 0504 | D39: 上海 | E39: 山念 | F39: 45757 | G39: 90192 | H39: 90192 | I39: 租金代扣 | K39: 上海美速家建筑装饰有限公司 | L39: 412批次 | M39: 412批次 | N39: 信托1号 | O39: =VLOOKUP(B39,'4已发行数据（原始入池数据表格）'!C:C,1,FALSE) -> 107112557175
A40: -11 | B40: 107112551587 | C40: 上海市普陀区宜川路宜川二村小区124号415室 | D40: 上海 | E40: 山念 | F40: 45756 | G40: 78000 | H40: 78000 | I40: 租金代扣 | J40: 0 | K40: 上海千盛邦建筑装饰有限公司 | L40: 单一信托 | M40: 单一信托 | N40: 单一信托 | O40: =VLOOKUP(B40,'4已发行数据（原始入池数据表格）'!C:C,1,FALSE) -> 107112551587
A41: -10 | B41: 107112468531 | C41: 上海静安升平街41弄20号301室 | D41: 上海 | E41: 山念 | F41: 45756 | G41: 120151 | H41: 120151 | I41: 租金代扣 | J41: 0 | K41: 上海沪慧荣建筑装饰有限公司 | L41: 单一信托 | M41: 单一信托 | N41: 单一信托 | O41: =VLOOKUP(B41,'4已发行数据（原始入池数据表格）'!C:C,1,FALSE) -> 107112468531
A42: 20 | B42: 107112792457 | C42: 上海市宝山区海滨新村176号103室 | D42: 上海 | E42: 山念 | F42: 45755 | G42: 93858 | H42: 80999 | I42: 业主付款+租金代扣 | J42: 12859 | K42: 上海千盛邦建筑装饰有限公司 | L42: 412批次 | M42: 412批次 | N42: 信托1号 | O42: =VLOOKUP(B42,'4已发行数据（原始入池数据表格）'!C:C,1,FALSE) -> 107112792457
A43: 21 | B43: 107112516665 | C43: 上海市虹口区虹湾路6号1202室 | D43: 上海 | E43: 山念 | F43: 45754 | G43: 109196 | H43: 109196 | I43: 租金代扣 | K43: 上海千盛邦建筑装饰有限公司 | L43: 412批次 | M43: 412批次 | N43: 信托1号 | O43: =VLOOKUP(B43,'4已发行数据（原始入池数据表格）'!C:C,1,FALSE) -> 107112516665
A44: 8 | B44: 107112529588 | C44: 上海市闵行区通海路268弄31号1102 | D44: 上海 | E44: 山念 | F44: 45753 | G44: 30363 | H44: 30363 | I44: 租金代扣 | J44: 0 | K44: 南京和艺优装饰工程有限公司 | L44: 412批次 | M44: 412批次 | N44: 信托1号 | O44: =VLOOKUP(B44,'4已发行数据（原始入池数据表格）'!C:C,1,FALSE) -> 107112529588
A45: 20 | B45: 107112466550 | C45: 上海市宝山区淞南一村32号102室 | D45: 上海 | E45: 山念 | F45: 45753 | G45: 118000 | H45: 118000 | I45: 租金代扣 | K45: 上海千盛邦建筑装饰有限公司 | L45: 412批次 | M45: 412批次 | N45: 信托1号 | O45: =VLOOKUP(B45,'4已发行数据（原始入池数据表格）'!C:C,1,FALSE) -> 107112466550
A46: 13 | B46: 101129984712 | C46: 北京市西城区如意里11号楼1门132 | D46: 北京 | E46: 焕新租 | F46: 45753 | G46: 73660 | H46: 73660 | I46: 租金代扣 | K46: 北京省心装工程管理有限公司 | L46: 412批次 | M46: 412批次 | N46: 信托1号 | O46: =VLOOKUP(B46,'4已发行数据（原始入池数据表格）'!C:C,1,FALSE) -> 101129984712
A47: 20 | B47: 101129894230 | C47: 北京市石景山区苹果园三区3号楼2层202号 | D47: 北京 | E47: 焕新租 | F47: 45753 | G47: 86000 | H47: 86000 | I47: 租金代扣 | J47: 0 | K47: 上海虬诗建设有限公司 | L47: 412批次 | M47: 412批次 | N47: 信托1号 | O47: =VLOOKUP(B47,'4已发行数据（原始入池数据表格）'!C:C,1,FALSE) -> 101129894230
A48: -11 | B48: 107112518699 | C48: 上海市浦东新区南码头路1675弄1号404室 | D48: 上海 | E48: 山念 | F48: 45752 | G48: 120000 | H48: 120000 | I48: 租金代扣 | J48: 0 | K48: 上海庆苑建筑装饰集团有限公司 | L48: 单一信托 | M48: 单一信托 | N48: 单一信托 | O48: =VLOOKUP(B48,'4已发行数据（原始入池数据表格）'!C:C,1,FALSE) -> 107112518699
A49: 6 | B49: 107112470213 | C49: 碧桂园柏悦前湾季乐路33弄35号13层1302室 | D49: 上海 | E49: 山念 | F49: 45750 | G49: 23863 | H49: 23863 | I49: 租金代扣 | J49: 0 | K49: 天津冠唯装饰工程有限公司 | L49: 412批次 | M49: 412批次 | N49: 信托1号 | O49: =VLOOKUP(B49,'4已发行数据（原始入池数据表格）'!C:C,1,FALSE) -> 107112470213
A50: 9 | B50: 101129088736 | C50: 北京西城西黄城根南街一区8号楼8单元601室 | D50: 北京 | E50: 焕新租 | F50: 45749 | G50: 76400 | H50: 76400 | I50: 租金代扣 | J50: 0 | K50: 北京省心装工程管理有限公司 | L50: 412批次 | M50: 412批次 | N50: 信托1号 | O50: =VLOOKUP(B50,'4已发行数据（原始入池数据表格）'!C:C,1,FALSE) -> 101129088736
A51: 7 | B51: 107112462651 | C51: 上海嘉定柏悦翔湾18号楼46单元801 | D51: 上海 | E51: 山念 | F51: 45749 | G51: 22853 | H51: 22853 | I51: 租金代扣 | J51: 0 | K51: 上海优匠优装饰工程有限公司 | L51: 412批次 | M51: 412批次 | N51: 信托1号 | O51: =VLOOKUP(B51,'4已发行数据（原始入池数据表格）'!C:C,1,FALSE) -> 107112462651
A52: 22 | B52: 107112479350 | C52: 上海普陀光复西路2163弄123号楼123单元0601 | D52: 上海 | E52: 山念 | F52: 45749 | G52: 90000 | H52: 90000 | I52: 租金代扣 | J52: 0 | K52: 上海优匠优装饰工程有限公司 | L52: 412批次 | M52: 412批次 | N52: 信托1号 | O52: =VLOOKUP(B52,'4已发行数据（原始入池数据表格）'!C:C,1,FALSE) -> 107112479350
A53: -11 | B53: 107112483866 | C53: 上海市浦东新区上钢九村8号604室 | D53: 上海 | E53: 山念 | F53: 45749 | G53: 80000 | H53: 80000 | I53: 租金代扣 | J53: 0 | K53: 上海庆苑建筑装饰集团有限公司 | L53: 单一信托 | M53: 单一信托 | N53: 单一信托 | O53: =VLOOKUP(B53,'4已发行数据（原始入池数据表格）'!C:C,1,FALSE) -> 107112483866
A54: -11 | B54: 107112488326 | C54: 上海市浦东新区枣庄路998弄4号504室 | D54: 上海 | E54: 山念 | F54: 45749 | G54: 97000 | H54: 97000 | I54: 租金代扣 | K54: 华朗（杭州）装饰设计有限公司 | L54: 单一信托 | M54: 单一信托 | N54: 单一信托 | O54: =VLOOKUP(B54,'4已发行数据（原始入池数据表格）'!C:C,1,FALSE) -> 107112488326
A55: 7 | B55: 101129266919 | C55: 八里庄路61号院2号楼4单元412 | D55: 北京 | E55: 焕新租 | F55: 45748 | G55: 75868 | H55: 75868 | I55: 租金代扣 | K55: 上海虬诗建设有限公司 | L55: 412批次 | M55: 412批次 | N55: 信托1号 | O55: =VLOOKUP(B55,'4已发行数据（原始入池数据表格）'!C:C,1,FALSE) -> 101129266919
A56: 9 | B56: 101129311618 | C56: 北京市海淀区西三环北路23号院3号楼5门504 | D56: 北京 | E56: 焕新租 | F56: 45748 | G56: 78000 | H56: 78000 | I56: 租金代扣 | K56: 北京省心装工程管理有限公司 | L56: 412批次 | M56: 412批次 | N56: 信托1号 | O56: =VLOOKUP(B56,'4已发行数据（原始入池数据表格）'!C:C,1,FALSE) -> 101129311618
A57: 19 | B57: 101129616917 | C57: 北京市朝阳区安翔南里3号楼2单元504 | D57: 北京 | E57: 焕新租 | F57: 45748 | G57: 98883 | H57: 98883 | I57: 租金代扣 | J57: 0 | K57: 北京致一建设有限公司 | L57: 412批次 | M57: 412批次 | N57: 信托1号 | O57: =VLOOKUP(B57,'4已发行数据（原始入池数据表格）'!C:C,1,FALSE) -> 101129616917
A58: -12 | B58: 107112362852 | C58: 上海市杨浦区延吉七村51号403 | D58: 上海 | E58: 山念 | F58: 45748 | G58: 111526 | H58: 111526 | I58: 租金代扣 | K58: 上海美速家建筑装饰有限公司 | L58: 单一信托 | M58: 单一信托 | N58: 单一信托 | O58: =VLOOKUP(B58,'4已发行数据（原始入池数据表格）'!C:C,1,FALSE) -> 107112362852
A59: -11 | B59: 107112452710 | C59: 上海虹口天宝路388弄11号楼11单元0503 | D59: 上海 | E59: 山念 | F59: 45748 | G59: 104141 | H59: 104141 | I59: 租金代扣 | K59: 上海美速家建筑装饰有限公司 | L59: 单一信托 | M59: 单一信托 | N59: 单一信托 | O59: =VLOOKUP(B59,'4已发行数据（原始入池数据表格）'!C:C,1,FALSE) -> 107112452710
A60: 8 | B60: 107112476987 | C60: 上海市闵行区通海路268弄21号1801 | D60: 上海 | E60: 山念 | F60: 45747 | G60: 29297 | H60: 29297 | I60: 租金代扣 | J60: 0 | K60: 南京和艺优装饰工程有限公司 | L60: 412批次 | M60: 412批次 | N60: 信托1号 | O60: =VLOOKUP(B60,'4已发行数据（原始入池数据表格）'!C:C,1,FALSE) -> 107112476987
A61: -11 | B61: 107112453175 | C61: 上海市宝山区大场镇市台路408号1715 | D61: 上海 | E61: 山念 | F61: 45747 | G61: 147377 | H61: 147377 | I61: 租金代扣 | J61: 0 | K61: 上海长聚建筑工程有限公司 | L61: 单一信托 | M61: 单一信托 | N61: 单一信托 | O61: =VLOOKUP(B61,'4已发行数据（原始入池数据表格）'!C:C,1,FALSE) -> 107112453175
A62: 19 | B62: 101129694480 | C62: 北京市海淀区科技大学35号楼1单元504 | D62: 北京 | E62: 焕新租 | F62: 45747 | G62: 81225 | H62: 81225 | I62: 租金代扣 | J62: 0 | K62: 上海虬诗建设有限公司 | L62: 412批次 | M62: 412批次 | N62: 信托1号 | O62: =VLOOKUP(B62,'4已发行数据（原始入池数据表格）'!C:C,1,FALSE) -> 101129694480
A63: 23 | B63: 107112333315 | C63: 上海市浦东新区胶南小区2366号1602 | D63: 上海 | E63: 山念 | F63: 45747 | G63: 89000 | H63: 89000 | I63: 租金代扣 | K63: 上海欣暄装饰工程设计有限公司 | L63: 412批次 | M63: 412批次 | N63: 信托1号 | O63: =VLOOKUP(B63,'4已发行数据（原始入池数据表格）'!C:C,1,FALSE) -> 107112333315
A64: 19 | B64: 101129727695 | C64: 朝阳区水碓子北里4号楼6层5单元601 | D64: 北京 | E64: 焕新租 | F64: 45747 | G64: 104637 | H64: 104637 | I64: 租金代扣 | J64: 0 | K64: 北京贝乐禾装饰有限公司 | L64: 412批次 | M64: 412批次 | N64: 信托1号 | O64: =VLOOKUP(B64,'4已发行数据（原始入池数据表格）'!C:C,1,FALSE) -> 101129727695
A65: 20 | B65: 107112460003 | C65: 上海市长宁区仙霞新村街道茅台路601弄水霞小区12号204 | D65: 上海 | E65: 山念 | F65: 45747 | G65: 112715 | H65: 112715 | I65: 租金代扣 | J65: 0 | K65: 天津冠唯装饰工程有限公司 | L65: 412批次 | M65: 412批次 | N65: 信托1号 | O65: =VLOOKUP(B65,'4已发行数据（原始入池数据表格）'!C:C,1,FALSE) -> 107112460003
A66: 26 | B66: 107112404846 | C66: 上海市宝山区永清二村24号302 | D66: 上海 | E66: 山念 | F66: 45745 | G66: 106836 | H66: 106836 | I66: 租金代扣 | J66: 0 | K66: 上海千盛邦建筑装饰有限公司 | L66: 412批次 | M66: 412批次 | N66: 信托1号 | O66: =VLOOKUP(B66,'4已发行数据（原始入池数据表格）'!C:C,1,FALSE) -> 107112404846
A67: -12 | B67: 107112428344 | C67: 上海市浦东新区芳华路580弄14号601室 | D67: 上海 | E67: 山念 | F67: 45745 | G67: 92000 | H67: 92000 | I67: 租金代扣 | J67: 0 | K67: 上海庆苑建筑装饰集团有限公司 | L67: 单一信托 | M67: 单一信托 | N67: 单一信托 | O67: =VLOOKUP(B67,'4已发行数据（原始入池数据表格）'!C:C,1,FALSE) -> 107112428344
A68: -11 | B68: 107112271059 | C68: 上海市宝山区三门路489弄16号楼0502室 | D68: 上海 | E68: 山念 | F68: 45744 | G68: 99000 | H68: 99000 | I68: 租金代扣 | K68: 上海千盛邦建筑装饰有限公司 | L68: 单一信托 | M68: 单一信托 | N68: 单一信托 | O68: =VLOOKUP(B68,'4已发行数据（原始入池数据表格）'!C:C,1,FALSE) -> 107112271059
A69: 20 | B69: 107112444178 | C69: 上海徐汇钦江大楼单栋单栋0502 | D69: 上海 | E69: 山念 | F69: 45744 | G69: 118888 | H69: 118888 | I69: 租金代扣 | K69: 南京和艺优装饰工程有限公司 | L69: 412批次 | M69: 412批次 | N69: 信托1号 | O69: =VLOOKUP(B69,'4已发行数据（原始入池数据表格）'!C:C,1,FALSE) -> 107112444178
A70: 26 | B70: 107112435822 | C70: 上海市徐汇区高安路 60 号一层 7 号 | D70: 上海 | E70: 山念 | F70: 45744 | G70: 66238 | H70: 66238 | I70: 租金代扣 | J70: 0 | K70: 上海沪慧荣建筑装饰有限公司 | L70: 412批次 | M70: 412批次 | N70: 信托1号 | O70: =VLOOKUP(B70,'4已发行数据（原始入池数据表格）'!C:C,1,FALSE) -> 107112435822
A71: -11 | B71: 107112439381 | C71: 上海嘉定江桥一村12号楼12单元0601 | D71: 上海 | E71: 山念 | F71: 45743 | G71: 145000 | H71: 145000 | I71: 租金代扣 | J71: 0 | K71: 上海优匠优装饰工程有限公司 | L71: 单一信托 | M71: 单一信托 | N71: 单一信托 | O71: =VLOOKUP(B71,'4已发行数据（原始入池数据表格）'!C:C,1,FALSE) -> 107112439381
A72: 19 | B72: 101128682630 | C72: 北京市西城区富国里14号楼4门303 | D72: 北京 | E72: 焕新租 | F72: 45743 | G72: 94000 | H72: 94000 | I72: 租金代扣 | K72: 北京省心装工程管理有限公司 | L72: 412批次 | M72: 412批次 | N72: 信托1号 | O72: =VLOOKUP(B72,'4已发行数据（原始入池数据表格）'!C:C,1,FALSE) -> 101128682630
A73: 20 | B73: 101129491687 | C73: 北京市朝阳区和平街十一区39号楼0单元904室 | D73: 北京 | E73: 焕新租 | F73: 45743 | G73: 160091 | H73: 160091 | I73: 租金代扣 | J73: 0 | K73: 北京致一建设有限公司 | L73: 412批次 | M73: 412批次 | N73: 信托1号 | O73: =VLOOKUP(B73,'4已发行数据（原始入池数据表格）'!C:C,1,FALSE) -> 101129491687
A74: -11 | B74: 107112422787 | C74: 上海市普陀区新村路50弄38号601室 | D74: 上海 | E74: 山念 | F74: 45742 | G74: 89023 | H74: 89023 | I74: 租金代扣 | K74: 上海千盛邦建筑装饰有限公司 | L74: 单一信托 | M74: 单一信托 | N74: 单一信托 | O74: =VLOOKUP(B74,'4已发行数据（原始入池数据表格）'!C:C,1,FALSE) -> 107112422787
A75: 23 | B75: 101129692832 | C75: 北京市西城区如意里10号楼7-721 | D75: 北京 | E75: 焕新租 | F75: 45742 | G75: 78000 | H75: 78000 | I75: 租金代扣 | K75: 北京省心装工程管理有限公司 | L75: 412批次 | M75: 412批次 | N75: 信托1号 | O75: =VLOOKUP(B75,'4已发行数据（原始入池数据表格）'!C:C,1,FALSE) -> 101129692832
A76: 8 | B76: 101129684632 | C76: 北京市朝阳区朝悦居2-3-303 | D76: 北京 | E76: 焕新租 | F76: 45742 | G76: 98888 | H76: 98888 | I76: 租金代扣 | J76: 0 | K76: 北京致一建设有限公司 | L76: 412批次 | M76: 412批次 | N76: 信托1号 | O76: =VLOOKUP(B76,'4已发行数据（原始入池数据表格）'!C:C,1,FALSE) -> 101129684632
A77: -11 | B77: 107112246075 | C77: 上海闵行莘松三村32乙501 | D77: 上海 | E77: 山念 | F77: 45742 | G77: 92300 | H77: 92300 | I77: 租金代扣 | K77: 南京和艺优装饰工程有限公司 | L77: 单一信托 | M77: 单一信托 | N77: 单一信托 | O77: =VLOOKUP(B77,'4已发行数据（原始入池数据表格）'!C:C,1,FALSE) -> 107112246075
A78: -12 | B78: 107112424527 | C78: 上海市普陀新沪小区新村路39弄23号303室 | D78: 上海 | E78: 山念 | F78: 45742 | G78: 93500 | H78: 93500 | I78: 租金代扣 | J78: 0 | K78: 上海千盛邦建筑装饰有限公司 | L78: 单一信托 | M78: 单一信托 | N78: 单一信托 | O78: =VLOOKUP(B78,'4已发行数据（原始入池数据表格）'!C:C,1,FALSE) -> 107112424527
A79: 16 | B79: 107112361831 | C79: 上海市杨浦区国泓路 818弄10-501 | D79: 上海 | E79: 山念 | F79: 45742 | G79: 22053 | H79: 22053 | I79: 租金代扣 | K79: 上海美速家建筑装饰有限公司 | L79: 412批次 | M79: 412批次 | N79: 信托1号 | O79: =VLOOKUP(B79,'4已发行数据（原始入池数据表格）'!C:C,1,FALSE) -> 107112361831
A80: 8 | B80: 101129685066 | C80: 北京市朝阳区朝悦居4号楼2单元2402 | D80: 北京 | E80: 焕新租 | F80: 45742 | G80: 98888 | H80: 98888 | I80: 租金代扣 | J80: 0 | K80: 北京致一建设有限公司 | L80: 412批次 | M80: 412批次 | N80: 信托1号 | O80: =VLOOKUP(B80,'4已发行数据（原始入池数据表格）'!C:C,1,FALSE) -> 101129685066
A81: -12 | B81: 107112416833 | C81: 上海市浦东新区崂山二村8号405室 | D81: 上海 | E81: 山念 | F81: 45742 | G81: 75293 | H81: 75293 | I81: 租金代扣 | J81: 0 | K81: 上海庆苑建筑装饰集团有限公司 | L81: 单一信托 | M81: 单一信托 | N81: 单一信托 | O81: =VLOOKUP(B81,'4已发行数据（原始入池数据表格）'!C:C,1,FALSE) -> 107112416833
A82: -11 | B82: 107112416762 | C82: 上海市浦东新区崂山二村8号406室 | D82: 上海 | E82: 山念 | F82: 45742 | G82: 78142 | H82: 78142 | I82: 租金代扣 | J82: 0 | K82: 上海庆苑建筑装饰集团有限公司 | L82: 单一信托 | M82: 单一信托 | N82: 单一信托 | O82: =VLOOKUP(B82,'4已发行数据（原始入池数据表格）'!C:C,1,FALSE) -> 107112416762
A83: 18 | B83: 107112391867 | C83: 上海市浦东新区蓝高小区蓝村路30弄6号204室 | D83: 上海 | E83: 山念 | F83: 45741 | G83: 71000 | H83: 71000 | I83: 租金代扣 | J83: 0 | K83: 上海庆苑建筑装饰集团有限公司 | L83: 412批次 | M83: 412批次 | N83: 信托1号 | O83: =VLOOKUP(B83,'4已发行数据（原始入池数据表格）'!C:C,1,FALSE) -> 107112391867
A84: 24 | B84: 107112417847 | C84: 上海市静安区平顺路825弄10号0102室 | D84: 上海 | E84: 山念 | F84: 45741 | G84: 108800 | H84: 108800 | I84: 租金代扣 | K84: 上海千盛邦建筑装饰有限公司 | L84: 第二批 | M84: 第二批 | N84: 信托2号 | O84: =VLOOKUP(B84,'4已发行数据（原始入池数据表格）'!C:C,1,FALSE) -> 107112417847
A85: 7 | B85: 107112322289 | C85: 上海市浦东新区首善街99弄155号1601室 | D85: 上海 | E85: 山念 | F85: 45741 | G85: 29000 | H85: 29000 | I85: 租金代扣 | J85: 0 | K85: 上海庆苑建筑装饰集团有限公司 | L85: 第二批 | M85: 第二批 | N85: 信托2号 | O85: =VLOOKUP(B85,'4已发行数据（原始入池数据表格）'!C:C,1,FALSE) -> 107112322289
A86: 26 | B86: 107106888322 | C86: 上海市浦东新区城南居委小区城南路267弄11号501室 | D86: 上海 | E86: 山念 | F86: 45740 | G86: 98000 | H86: 98000 | I86: 租金代扣 | J86: 0 | K86: 上海庆苑建筑装饰集团有限公司 | L86: 412批次 | M86: 412批次 | N86: 信托1号 | O86: =VLOOKUP(B86,'4已发行数据（原始入池数据表格）'!C:C,1,FALSE) -> 107106888322
A87: 7 | B87: 107112283513 | C87: 上海闵行紫龙路211弄12号1602 | D87: 上海 | E87: 山念 | F87: 45740 | G87: 27000 | H87: 27000 | I87: 租金代扣 | K87: 南京和艺优装饰工程有限公司 | L87: 412批次 | M87: 412批次 | N87: 信托1号 | O87: =VLOOKUP(B87,'4已发行数据（原始入池数据表格）'!C:C,1,FALSE) -> 107112283513
A88: 20 | B88: 107106308722 | C88: 上海普陀武宁一村22号楼22单元0301 | D88: 上海 | E88: 山念 | F88: 45740 | G88: 90000 | H88: 88414 | I88: 租金代扣 | J88: 0 | K88: 上海优匠优装饰工程有限公司 | L88: 412批次 | M88: 412批次 | N88: 信托1号 | O88: =VLOOKUP(B88,'4已发行数据（原始入池数据表格）'!C:C,1,FALSE) -> 107106308722
A89: -11 | B89: 107112395278 | C89: 上海市普陀区交通路2285弄13号204室 | D89: 上海 | E89: 山念 | F89: 45740 | G89: 80000 | H89: 80000 | I89: 租金代扣 | K89: 上海千盛邦建筑装饰有限公司 | L89: 单一信托 | M89: 单一信托 | N89: 单一信托 | O89: =VLOOKUP(B89,'4已发行数据（原始入池数据表格）'!C:C,1,FALSE) -> 107112395278
A90: -12 | B90: 107112272406 | C90: 上海闵行航华三村三街坊 213 号 502 | D90: 上海 | E90: 山念 | F90: 45740 | G90: 95000 | H90: 95000 | I90: 租金代扣 | K90: 南京和艺优装饰工程有限公司 | L90: 单一信托 | M90: 单一信托 | N90: 单一信托 | O90: =VLOOKUP(B90,'4已发行数据（原始入池数据表格）'!C:C,1,FALSE) -> 107112272406
A91: 19 | B91: 107112389753 | C91: 上海徐汇长桥一村58号楼58单元0104 | D91: 上海 | E91: 山念 | F91: 45740 | G91: 76666 | H91: 76666 | I91: 租金代扣 | K91: 南京和艺优装饰工程有限公司 | L91: 412批次 | M91: 412批次 | N91: 信托1号 | O91: =VLOOKUP(B91,'4已发行数据（原始入池数据表格）'!C:C,1,FALSE) -> 107112389753
A92: 6 | B92: 107112233335 | C92: 上海闵行紫琅路 188 弄 24 号 1202 室 | D92: 上海 | E92: 怡穗 | F92: 45740 | G92: 33828 | H92: 33828 | I92: 租金代扣 | K92: 南京和艺优装饰工程有限公司 | L92: 412批次 | M92: 412批次 | N92: 信托1号 | O92: =VLOOKUP(B92,'4已发行数据（原始入池数据表格）'!C:C,1,FALSE) -> 107112233335
A93: -12 | B93: 107112350721 | C93: 上海嘉定迎园新村七坊迎园新村七坊16号楼迎园新村七坊16单元0602 | D93: 上海 | E93: 山念 | F93: 45740 | G93: 108000 | H93: 108000 | I93: 租金代扣 | J93: 0 | K93: 上海优匠优装饰工程有限公司 | L93: 单一信托 | M93: 单一信托 | N93: 单一信托 | O93: =VLOOKUP(B93,'4已发行数据（原始入池数据表格）'!C:C,1,FALSE) -> 107112350721
A94: 21 | B94: 107112379629 | C94: 上海普陀梅六小区梅川路916弄21号楼梅川路916弄21单元0101 | D94: 上海 | E94: 山念 | F94: 45740 | G94: 83000 | H94: 79554 | I94: 租金代扣 | J94: 0 | K94: 上海优匠优装饰工程有限公司 | L94: 412批次 | M94: 412批次 | N94: 信托1号 | O94: =VLOOKUP(B94,'4已发行数据（原始入池数据表格）'!C:C,1,FALSE) -> 107112379629
A95: -12 | B95: 107112379854 | C95: 上海市浦东新区北中路408弄2号1405室 | D95: 上海 | E95: 山念 | F95: 45740 | G95: 136000 | H95: 136000 | I95: 租金代扣 | J95: 0 | K95: 上海庆苑建筑装饰集团有限公司 | L95: 单一信托 | M95: 单一信托 | N95: 单一信托 | O95: =VLOOKUP(B95,'4已发行数据（原始入池数据表格）'!C:C,1,FALSE) -> 107112379854
A96: 7 | B96: 107112327557 | C96: 上海闵行紫龙路211弄40号502 | D96: 上海 | E96: 山念 | F96: 45739 | G96: 26749 | H96: 26749 | I96: 租金代扣 | K96: 南京和艺优装饰工程有限公司 | L96: 412批次 | M96: 412批次 | N96: 信托1号 | O96: =VLOOKUP(B96,'4已发行数据（原始入池数据表格）'!C:C,1,FALSE) -> 107112327557
A97: 25 | B97: 107112396034 | C97: 上海市闵行区古北中央萃2号1304 | D97: 上海 | E97: 山念 | F97: 45739 | G97: 272270 | H97: 259970 | I97: 租金代扣 | J97: 0 | K97: 上海沪慧荣建筑装饰有限公司 | L97: 第二批 | M97: 第二批 | N97: 信托2号 | O97: =VLOOKUP(B97,'4已发行数据（原始入池数据表格）'!C:C,1,FALSE) -> 107112396034
A98: 7 | B98: 107112376144 | C98: 上海闵行紫龙路211弄11号101室 | D98: 上海 | E98: 山念 | F98: 45739 | G98: 20000 | H98: 20000 | I98: 租金代扣 | K98: 南京和艺优装饰工程有限公司 | L98: 412批次 | M98: 412批次 | N98: 信托1号 | O98: =VLOOKUP(B98,'4已发行数据（原始入池数据表格）'!C:C,1,FALSE) -> 107112376144
A99: 26 | B99: 107112392532 | C99: 上海市浦东新区德州四村成山路24弄10号302室 | D99: 上海 | E99: 山念 | F99: 45739 | G99: 69900 | H99: 69900 | I99: 租金代扣 | J99: 0 | K99: 上海庆苑建筑装饰集团有限公司 | L99: 412批次 | M99: 412批次 | N99: 信托1号 | O99: =VLOOKUP(B99,'4已发行数据（原始入池数据表格）'!C:C,1,FALSE) -> 107112392532
A100: -10 | B100: 107112382613 | C100: 上海嘉定南华小区20号楼20单元0502 | D100: 上海 | E100: 山念 | F100: 45738 | G100: 75000 | H100: 75000 | I100: 租金代扣 | J100: 0 | K100: 上海优匠优装饰工程有限公司 | L100: 单一信托 | M100: 单一信托 | N100: 单一信托 | O100: =VLOOKUP(B100,'4已发行数据（原始入池数据表格）'!C:C,1,FALSE) -> 107112382613
...

Sheet 4已发行数据（原始入池数据表格）
A1: 文件名 | B1: sheet名称 | C1: 房源编号 | D1: 应收账款合同金额 | E1: 资产转让折扣率 | F1: 应收账款转让价款 | G1: 预计应收账款到期日 | H1: 每期应付金额 | I1: 出房价格 | J1: 当前信托计划 | K1: 代扣金额 | L1: 已代扣未付款 | M1: 贝壳已租金代扣金额合计 | N1: 已代扣已回款 | O1: 首次付款日期
A2: 美润1号服务信托房源明细（首期转让）.xlsx | B2: 合同 | C2: 107112551587 | D2: 78000 | E2: 0.83 | F2: 64740 | G2: 2029-04-16
A3: 美润1号服务信托房源明细（首期转让）.xlsx | B3: 合同 | C3: 107112468531 | D3: 120151 | E3: 0.83 | F3: 99725.33 | G3: 2030-11-22
A4: 美润1号服务信托房源明细（首期转让）.xlsx | B4: 合同 | C4: 107112488326 | D4: 97000 | E4: 0.83 | F4: 80510 | G4: 2029-07-17
A5: 美润1号服务信托房源明细（首期转让）.xlsx | B5: 合同 | C5: 107112518699 | D5: 120000 | E5: 0.83 | F5: 99600 | G5: 2029-09-07
A6: 美润1号服务信托房源明细（首期转让）.xlsx | B6: 合同 | C6: 107112483866 | D6: 80000 | E6: 0.83 | F6: 66400 | G6: 2029-11-25
A7: 美润1号服务信托房源明细（首期转让）.xlsx | B7: 合同 | C7: 107112428344 | D7: 92000 | E7: 0.83 | F7: 76360 | G7: 2029-10-25
A8: 美润1号服务信托房源明细（首期转让）.xlsx | B8: 合同 | C8: 107112362852 | D8: 111526 | E8: 0.83 | F8: 92566.58 | G8: 2029-06-10
A9: 美润1号服务信托房源明细（首期转让）.xlsx | B9: 合同 | C9: 107112271059 | D9: 99000 | E9: 0.83 | F9: 82170 | G9: 2029-06-25
A10: 美润1号服务信托房源明细（首期转让）.xlsx | B10: 合同 | C10: 107112452710 | D10: 104141 | E10: 0.83 | F10: 86437.03 | G10: 2029-07-20
A11: 美润1号服务信托房源明细（首期转让）.xlsx | B11: 合同 | C11: 107112453175 | D11: 147377 | E11: 0.83 | F11: 122322.91 | G11: 2029-11-05
A12: 美润1号服务信托房源明细（首期转让）.xlsx | B12: 合同 | C12: 107112439381 | D12: 145000 | E12: 0.83 | F12: 120350 | G12: 2029-04-25
A13: 美润1号服务信托房源明细（首期转让）.xlsx | B13: 合同 | C13: 107112424527 | D13: 93500 | E13: 0.83 | F13: 77605 | G13: 2029-07-10
... A111: 美润1号服务信托房源明细（首期转让）.xlsx | B111: 合同 | C111: 101130770124 | D111: 25000 | E111: 0.95 | F111: 23750 | G111: 2026-06-27
A112: 附件1：美好生活3号-基础资产清单.xlsx | B112: 房源维度结算底表 | C112: 107113470959 | D112: 90139 | E112: 0.88 | F112: 71386.48 | G112: 2028-11-15 | H112: 2496 | I112: 5200 | J112: 单一信托 | K112: 90139 | M112: 9018 | N112: 9018 | O112: 2025-11-15
A113: 附件1：美好生活3号-基础资产清单.xlsx | B113: 房源维度结算底表 | C113: 107113475157 | D113: 134976 | E113: 0.88 | F113: 108880.62 | G113: 2028-10-20 | H113: 3749.34 | I113: 4500 | J113: 单一信托 | K113: 134976 | M113: 11248.02 | N113: 11248.02 | O113: 2025-10-20
A114: 附件1：美好生活3号-基础资产清单.xlsx | B114: 房源维度结算底表 | C114: 107113418192 | D114: 84000 | E114: 0.88 | F114: 73920 | G114: 2028-10-07 | H114: 2450 | I114: 3500 | K114: 84000 | L114: 8500 | M114: 8500 | N114: 0 | O114: 2025-11-07
A115: 附件1：美好生活3号-基础资产清单.xlsx | B115: 房源维度结算底表 | C115: 101131715168 | D115: 70000 | E115: 0.88 | F115: 61600 | G115: 2028-10-01 | H115: 2029.5 | I115: 4950 | K115: 70000 | L115: 8118 | M115: 8118 | N115: 0 | O115: 2025-11-01
A116: 附件1：美好生活3号-基础资产清单.xlsx | B116: 房源维度结算底表 | C116: 107113391820 | D116: 118021 | E116: 0.88 | F116: 89412.4 | G116: 2028-09-29 | H116: 3384 | I116: 7200 | J116: 单一信托 | K116: 118021 | M116: 16416 | N116: 16416 | O116: 2025-10-29
A117: 附件1：美好生活3号-基础资产清单.xlsx | B117: 房源维度结算底表 | C117: 107113428544 | D117: 86296 | E117: 0.88 | F117: 67994.08 | G117: 2028-09-28 | H117: 2560 | I117: 4000 | J117: 单一信托 | K117: 86296 | M117: 9030 | N117: 9030 | O117: 2025-11-28
A118: 附件1：美好生活3号-基础资产清单.xlsx | B118: 房源维度结算底表 | C118: 107114425879 | D118: 108645 | E118: 0.88 | F118: 95607.6 | G118: 2028-09-21 | H118: 3333.34 | I118: 4500 | K118: 108645 | L118: 5133.34 | M118: 5133.34 | N118: 0 | O118: 2026-01-21
A119: 附件1：美好生活3号-基础资产清单.xlsx | B119: 房源维度结算底表 | C119: 107114728897 | D119: 96309 | E119: 0.88 | F119: 84751.92 | G119: 2028-09-18 | H119: 3210.3 | I119: 4600 | K119: 96309 | L119: 0 | M119: 0 | N119: 0 | O119: 2026-03-18
A120: 附件1：美好生活3号-基础资产清单.xlsx | B120: 房源维度结算底表 | C120: 107114599756 | D120: 189869 | E120: 0.88 | F120: 167084.72 | G120: 2028-09-16 | H120: 6328.97 | I120: 7200 | K120: 189869 | L120: 0 | M120: 0 | N120: 0 | O120: 2026-03-16
A121: 附件1：美好生活3号-基础资产清单.xlsx | B121: 房源维度结算底表 | C121: 107114578480 | D121: 103000 | E121: 0.88 | F121: 90640 | G121: 2028-09-15 | H121: 3433.34 | I121: 4500 | K121: 103000 | L121: 0 | M121: 0 | N121: 0 | O121: 2026-03-15
A122: 附件1：美好生活3号-基础资产清单.xlsx | B122: 房源维度结算底表 | C122: 107114340868 | D122: 88000 | E122: 0.88 | F122: 77440 | G122: 2028-09-15 | H122: 2933.34 | I122: 6500 | K122: 88000 | L122: 0 | M122: 0 | N122: 0 | O122: 2026-03-15
A123: 附件1：美好生活3号-基础资产清单.xlsx | B123: 房源维度结算底表 | C123: 107114528246 | D123: 85500 | E123: 0.88 | F123: 75240 | G123: 2028-09-14 | H123: 2850 | I123: 5200 | K123: 85500 | L123: 0 | M123: 0 | N123: 0 | O123: 2026-03-14
A124: 附件1：美好生活3号-基础资产清单.xlsx | B124: 房源维度结算底表 | C124: 107114607489 | D124: 105000 | E124: 0.88 | F124: 92400 | G124: 2028-09-14 | H124: 3500 | I124: 6000 | K124: 105000 | L124: 0 | M124: 0 | N124: 0 | O124: 2026-03-14
A125: 附件1：美好生活3号-基础资产清单.xlsx | B125: 房源维度结算底表 | C125: 107114521434 | D125: 78806 | E125: 0.88 | F125: 69349.28 | G125: 2028-09-11 | H125: 2626.87 | I125: 4600 | K125: 78806 | L125: 1840 | M125: 1840 | N125: 0 | O125: 2026-02-11
A126: 附件1：美好生活3号-基础资产清单.xlsx | B126: 房源维度结算底表 | C126: 107114574891 | D126: 99781 | E126: 0.88 | F126: 87807.28 | G126: 2028-09-10 | H126: 3326.04 | I126: 5000 | K126: 99781 | L126: 0 | M126: 0 | N126: 0 | O126: 2026-03-10
A127: 附件1：美好生活3号-基础资产清单.xlsx | B127: 房源维度结算底表 | C127: 107114542517 | D127: 163216 | E127: 0.88 | F127: 143630.08 | G127: 2028-09-10 | H127: 5440.54 | I127: 11500 | K127: 163216 | L127: 0 | M127: 0 | N127: 0 | O127: 2026-03-10
A128: 附件1：美好生活3号-基础资产清单.xlsx | B128: 房源维度结算底表 | C128: 107114694595 | D128: 83000 | E128: 0.88 | F128: 73040 | G128: 2028-09-10 | H128: 2766.67 | I128: 4800 | K128: 83000 | L128: 0 | M128: 0 | N128: 0 | O128: 2026-03-10
A129: 附件1：美好生活3号-基础资产清单.xlsx | B129: 房源维度结算底表 | C129: 107114319301 | D129: 72000 | E129: 0.88 | F129: 63360 | G129: 2028-09-10 | H129: 2400 | I129: 4900 | K129: 72000 | L129: 0 | M129: 0 | N129: 0 | O129: 2026-03-10
... A180: 附件1：美好生活3号-基础资产清单.xlsx | B180: 房源维度结算底表 | C180: 107114464006 | D180: 100000 | E180: 0.88 | F180: 88000 | G180: 2028-09-01 | H180: 3333.34 | I180: 6000 | K180: 100000 | L180: 2400 | M180: 2400 | N180: 0 | O180: 2026-03-01
A181: 附件1：美好生活3号-基础资产清单.xlsx | B181: 房源维度结算底表 | C181: 107113985127 | D181: 83091 | E181: 0.88 | F181: 68949.14 | G181: 2028-09-01 | H181: 2769.7 | I181: 5300 | J181: 单一信托 | K181: 83091 | M181: 4739.7 | N181: 4739.7 | O181: 2026-02-01
A182: 附件1：美好生活3号-基础资产清单.xlsx | B182: 房源维度结算底表 | C182: 107114090684 | D182: 82707 | E182: 0.88 | F182: 72782.16 | G182: 2028-08-31 | H182: 2756.9 | I182: 3400 | K182: 82707 | L182: 4066.9 | M182: 4066.9 | N182: 0 | O182: 2026-01-31
A183: 附件1：美好生活3号-基础资产清单.xlsx | B183: 房源维度结算底表 | C183: 107114451939 | D183: 110000 | E183: 0.88 | F183: 96800 | G183: 2028-08-31 | H183: 3666.67 | I183: 4300 | K183: 110000 | L183: 5486.67 | M183: 5486.67 | N183: 0 | O183: 2026-01-31
A184: 附件1：美好生活3号-基础资产清单.xlsx | B184: 房源维度结算底表 | C184: 107114386970 | D184: 94000 | E184: 0.88 | F184: 82720 | G184: 2028-08-31 | H184: 3133.34 | I184: 3600 | K184: 94000 | L184: 4573.34 | M184: 4573.34 | N184: 0 | O184: 2026-01-31
A185: 附件1：美好生活3号-基础资产清单.xlsx | B185: 房源维度结算底表 | C185: 107114252859 | D185: 83732 | E185: 0.88 | F185: 73684.16 | G185: 2028-08-30 | H185: 2791.07 | I185: 3700 | K185: 83732 | L185: 4121.07 | M185: 4121.07 | N185: 0 | O185: 2026-01-30
A186: 附件1：美好生活3号-基础资产清单.xlsx | B186: 房源维度结算底表 | C186: 107114066861 | D186: 316712 | E186: 0.88 | F186: 278706.56 | G186: 2028-08-30 | H186: 10557.07 | I186: 15500 | K186: 316712 | L186: 16007.07 | M186: 16007.07 | N186: 0 | O186: 2026-01-30
A187: 附件1：美好生活3号-基础资产清单.xlsx | B187: 房源维度结算底表 | C187: 107114562119 | D187: 325000 | E187: 0.88 | F187: 267187.36 | G187: 2028-08-28 | H187: 10120.74 | I187: 12960 | K187: 303622 | L187: 4614 | M187: 4614 | N187: 0 | O187: 2026-02-28
A188: 附件1：美好生活3号-基础资产清单.xlsx | B188: 房源维度结算底表 | C188: 107114119448 | D188: 82950 | E188: 0.88 | F188: 72996 | G188: 2028-08-28 | H188: 2765 | I188: 5000 | K188: 82950 | L188: 1750 | M188: 1750 | N188: 0 | O188: 2026-02-28
A189: 附件1：美好生活3号-基础资产清单.xlsx | B189: 房源维度结算底表 | C189: 107114588202 | D189: 93822 | E189: 0.88 | F189: 82563.36 | G189: 2028-08-28 | H189: 3127.4 | I189: 3500 | K189: 93822 | L189: 1400 | M189: 1400 | N189: 0 | O189: 2026-02-28
A190: 附件1：美好生活3号-基础资产清单.xlsx | B190: 房源维度结算底表 | C190: 107114571075 | D190: 97000 | E190: 0.88 | F190: 85360 | G190: 2028-08-28 | H190: 3233.34 | I190: 3700 | K190: 97000 | L190: 1480 | M190: 1480 | N190: 0 | O190: 2026-02-28
A191: 附件1：美好生活3号-基础资产清单.xlsx | B191: 房源维度结算底表 | C191: 107114607041 | D191: 84811 | E191: 0.88 | F191: 74633.68 | G191: 2028-08-28 | H191: 2827.04 | I191: 4500 | K191: 84811 | L191: 1800 | M191: 1800 | N191: 0 | O191: 2026-02-28
A192: 附件1：美好生活3号-基础资产清单.xlsx | B192: 房源维度结算底表 | C192: 107114505097 | D192: 85600 | E192: 0.88 | F192: 75328 | G192: 2028-08-28 | H192: 2853.34 | I192: 4600 | K192: 85600 | L192: 4693.34 | M192: 4693.34 | N192: 0 | O192: 2026-01-28
A193: 附件1：美好生活3号-基础资产清单.xlsx | B193: 房源维度结算底表 | C193: 107114568532 | D193: 89270 | E193: 0.88 | F193: 78557.6 | G193: 2028-08-27 | H193: 2975.67 | I193: 4725 | K193: 89270 | L193: 2002.5 | M193: 2002.5 | N193: 0 | O193: 2026-02-27
... A224: 附件1：美好生活3号-基础资产清单.xlsx | B224: 房源维度结算底表 | C224: 107114353409 | D224: 86000 | E224: 0.88 | F224: 75680 | G224: 2028-08-18 | H224: 2866.67 | I224: 4200 | K224: 86000 | L224: 4646.67 | M224: 4646.67 | N224: 0 | O224: 2026-01-18
A225: 附件1：美好生活3号-基础资产清单.xlsx | B225: 房源维度结算底表 | C225: 107113327732 | D225: 95000 | E225: 0.88 | F225: 72446 | G225: 2028-08-18 | H225: 2850 | I225: 3750 | J225: 单一信托 | K225: 95000 | M225: 12675 | N225: 12675 | O225: 2025-10-18
A226: 附件1：美好生活3号-基础资产清单.xlsx | B226: 房源维度结算底表 | C226: 107114679771 | D226: 119629 | E226: 0.88 | F226: 105273.52 | G226: 2028-08-17 | H226: 3987.64 | I226: 5500 | K226: 119629 | L226: 2200 | M226: 2200 | N226: 0 | O226: 2026-02-17
A227: 附件1：美好生活3号-基础资产清单.xlsx | B227: 房源维度结算底表 | C227: 107114658116 | D227: 90000 | E227: 0.88 | F227: 79200 | G227: 2028-08-16 | H227: 3000 | I227: 5300 | K227: 90000 | L227: 2120 | M227: 2120 | N227: 0 | O227: 2026-02-16
A228: 附件1：美好生活3号-基础资产清单.xlsx | B228: 房源维度结算底表 | C228: 107114520860 | D228: 86551 | E228: 0.88 | F228: 76164.88 | G228: 2028-08-15 | H228: 2885.04 | I228: 4300 | K228: 86551 | L228: 1720 | M228: 1720 | N228: 0 | O228: 2026-02-15
A229: 附件1：美好生活3号-基础资产清单.xlsx | B229: 房源维度结算底表 | C229: 107114522533 | D229: 108000 | E229: 0.88 | F229: 95040 | G229: 2028-08-15 | H229: 3600 | I229: 4200 | K229: 108000 | L229: 1680 | M229: 1680 | N229: 0 | O229: 2026-02-15
A230: 附件1：美好生活3号-基础资产清单.xlsx | B230: 房源维度结算底表 | C230: 107114460716 | D230: 99994 | E230: 0.88 | F230: 87994.72 | G230: 2028-08-15 | H230: 3333.2 | I230: 4800 | K230: 99996 | L230: 1920 | M230: 1920 | N230: 0 | O230: 2026-02-15
A231: 附件1：美好生活3号-基础资产清单.xlsx | B231: 房源维度结算底表 | C231: 107114431517 | D231: 82600 | E231: 0.88 | F231: 72688 | G231: 2028-08-15 | H231: 2753.34 | I231: 3000 | K231: 82600 | L231: 1200 | M231: 1200 | N231: 0 | O231: 2026-02-15
A232: 附件1：美好生活3号-基础资产清单.xlsx | B232: 房源维度结算底表 | C232: 107114527823 | D232: 118888 | E232: 0.88 | F232: 104621.44 | G232: 2028-08-15 | H232: 3962.94 | I232: 4410 | K232: 118888 | L232: 1764 | M232: 1764 | N232: 0 | O232: 2026-02-15
A233: 附件1：美好生活3号-基础资产清单.xlsx | B233: 房源维度结算底表 | C233: 107114356225 | D233: 78835 | E233: 0.88 | F233: 69374.8 | G233: 2028-08-15 | H233: 2627.84 | I233: 6500 | K233: 78835 | L233: 5227.84 | M233: 5227.84 | N233: 0 | O233: 2026-01-15
A234: 附件1：美好生活3号-基础资产清单.xlsx | B234: 房源维度结算底表 | C234: 107114258201 | D234: 141460 | E234: 0.88 | F234: 124484.8 | G234: 2028-08-15 | H234: 4715.34 | I234: 7100 | K234: 141460 | L234: 7555.34 | M234: 7555.34 | N234: 0 | O234: 2026-01-15
A235: 附件1：美好生活3号-基础资产清单.xlsx | B235: 房源维度结算底表 | C235: 107114173043 | D235: 106000 | E235: 0.88 | F235: 93280 | G235: 2028-08-15 | H235: 3533.34 | I235: 4400 | K235: 106000 | L235: 4993.34 | M235: 4993.34 | N235: 0 | O235: 2026-01-15
A236: 附件1：美好生活3号-基础资产清单.xlsx | B236: 房源维度结算底表 | C236: 107114098565 | D236: 97948 | E236: 0.88 | F236: 86194.24 | G236: 2028-08-15 | H236: 3264.94 | I236: 4400 | K236: 97948 | L236: 4724.94 | M236: 4724.94 | N236: 0 | O236: 2026-01-15
A237: 附件1：美好生活3号-基础资产清单.xlsx | B237: 房源维度结算底表 | C237: 101130889310 | D237: 113500 | E237: 0.88 | F237: 99880 | G237: 2028-08-14 | H237: 3250 | I237: 6500 | K237: 113500 | L237: 9750 | M237: 9750 | N237: 0 | O237: 2025-09-14
... A241: 附件1：美好生活3号-基础资产清单.xlsx | B241: 房源维度结算底表 | C241: 107114205069 | D241: 133649 | E241: 0.88 | F241: 114048 | G241: 2028-08-12 | H241: 4320 | I241: 4500 | K241: 129600 | L241: 1650 | M241: 1650 | N241: 0 | O241: 2026-02-12
A242: 附件1：美好生活3号-基础资产清单.xlsx | B242: 房源维度结算底表 | C242: 107113184658 | D242: 164500 | E242: 0.88 | F242: 129389.92 | G242: 2028-08-12 | H242: 5032 | I242: 6800 | J242: 单一信托 | K242: 164500 | M242: 17466 | N242: 17466 | O242: 2025-11-12
A243: 附件1：美好生活3号-基础资产清单.xlsx | B243: 房源维度结算底表 | C243: 107114124146 | D243: 68800 | E243: 0.88 | F243: 60544 | G243: 2028-08-11 | H243: 2293.34 | I243: 3200 | K243: 68800 | L243: 380 | M243: 380 | N243: 0 | O243: 2026-02-11
A244: 附件1：美好生活3号-基础资产清单.xlsx | B244: 房源维度结算底表 | C244: 107114354505 | D244: 217000 | E244: 0.88 | F244: 190960 | G244: 2028-08-10 | H244: 7233.34 | I244: 11000 | K244: 217000 | L244: 4400 | M244: 4400 | N244: 0 | O244: 2026-02-10
A245: 附件1：美好生活3号-基础资产清单.xlsx | B245: 房源维度结算底表 | C245: 107114610062 | D245: 78584 | E245: 0.88 | F245: 69153.92 | G245: 2028-08-10 | H245: 2619.47 | I245: 3600 | K245: 78584 | L245: 1440 | M245: 1440 | N245: 0 | O245: 2026-02-10
A246: 附件1：美好生活3号-基础资产清单.xlsx | B246: 房源维度结算底表 | C246: 107114623296 | D246: 92000 | E246: 0.88 | F246: 80960 | G246: 2028-08-10 | H246: 3066.67 | I246: 4000 | K246: 92000 | L246: 1600 | M246: 1600 | N246: 0 | O246: 2026-02-10
A247: 附件1：美好生活3号-基础资产清单.xlsx | B247: 房源维度结算底表 | C247: 107114246083 | D247: 88000 | E247: 0.88 | F247: 77440 | G247: 2028-08-10 | H247: 2933.34 | I247: 5800 | K247: 88000 | L247: 2320 | M247: 2320 | N247: 0 | O247: 2026-02-10
A248: 附件1：美好生活3号-基础资产清单.xlsx | B248: 房源维度结算底表 | C248: 107114252280 | D248: 97566 | E248: 0.88 | F248: 85858.08 | G248: 2028-08-10 | H248: 3252.2 | I248: 7800 | K248: 97566 | L248: 3120 | M248: 3120 | N248: 0 | O248: 2026-02-10
A249: 附件1：美好生活3号-基础资产清单.xlsx | B249: 房源维度结算底表 | C249: 107114229132 | D249: 106888 | E249: 0.88 | F249: 94061.44 | G249: 2028-08-10 | H249: 3562.94 | I249: 4600 | K249: 106888 | L249: 1840 | M249: 1840 | N249: 0 | O249: 2026-02-10
A250: 附件1：美好生活3号-基础资产清单.xlsx | B250: 房源维度结算底表 | C250: 107114358898 | D250: 93773 | E250: 0.88 | F250: 82520.24 | G250: 2028-08-10 | H250: 3125.77 | I250: 6500 | K250: 93773 | L250: 5875.77 | M250: 5875.77 | N250: 0 | O250: 2026-01-10
A251: 附件1：美好生活3号-基础资产清单.xlsx | B251: 房源维度结算底表 | C251: 107114287611 | D251: 108008 | E251: 0.88 | F251: 95047.04 | G251: 2028-08-10 | H251: 3600.27 | I251: 5000 | K251: 108008 | L251: 5600.27 | M251: 5600.27 | N251: 0 | O251: 2026-01-10
A252: 附件1：美好生活3号-基础资产清单.xlsx | B252: 房源维度结算底表 | C252: 107114046870 | D252: 85764 | E252: 0.88 | F252: 75472.32 | G252: 2028-08-10 | H252: 2858.8 | I252: 7700 | K252: 85764 | L252: 5717.6 | M252: 5717.6 | N252: 0 | O252: 2026-01-10
A253: 附件1：美好生活3号-基础资产清单.xlsx | B253: 房源维度结算底表 | C253: 107114156623 | D253: 86252 | E253: 0.88 | F253: 75901.76 | G253: 2028-08-10 | H253: 2875.07 | I253: 4400 | K253: 86252 | L253: 4585.07 | M253: 4585.07 | N253: 0 | O253: 2026-01-10
A254: 附件1：美好生活3号-基础资产清单.xlsx | B254: 房源维度结算底表 | C254: 107114644478 | D254: 98467 | E254: 0.88 | F254: 86650.96 | G254: 2028-08-09 | H254: 3282.24 | I254: 5000 | K254: 98467 | L254: 2000 | M254: 2000 | N254: 0 | O254: 2026-02-09
... A267: 附件1：美好生活3号-基础资产清单.xlsx | B267: 房源维度结算底表 | C267: 107114104300 | D267: 85816 | E267: 0.88 | F267: 75518.08 | G267: 2028-08-07 | H267: 2860.54 | I267: 3800 | K267: 85816 | L267: 4280.54 | M267: 4280.54 | N267: 0 | O267: 2026-01-07
A268: 附件1：美好生活3号-基础资产清单.xlsx | B268: 房源维度结算底表 | C268: 107114292583 | D268: 74900 | E268: 0.88 | F268: 61517.86 | G268: 2028-08-07 | H268: 2496.67 | I268: 13000 | J268: 单一信托 | K268: 74900 | M268: 4993.34 | N268: 4993.34 | O268: 2026-01-07
A269: 附件1：美好生活3号-基础资产清单.xlsx | B269: 房源维度结算底表 | C269: 107114213548 | D269: 98000 | E269: 0.88 | F269: 86240 | G269: 2028-08-06 | H269: 3266.67 | I269: 4900 | K269: 98000 | L269: 1910 | M269: 1910 | N269: 0 | O269: 2026-02-06
A270: 附件1：美好生活3号-基础资产清单.xlsx | B270: 房源维度结算底表 | C270: 107114642982 | D270: 54163 | E270: 0.88 | F270: 47663.44 | G270: 2028-08-06 | H270: 1805.44 | I270: 4000 | K270: 54163 | L270: 1600 | M270: 1600 | N270: 0 | O270: 2026-02-06
A271: 附件1：美好生活3号-基础资产清单.xlsx | B271: 房源维度结算底表 | C271: 107114228020 | D271: 118881 | E271: 0.88 | F271: 104615.28 | G271: 2028-08-06 | H271: 3962.7 | I271: 5800 | K271: 118881 | L271: 6282.7 | M271: 6282.7 | N271: 0 | O271: 2026-01-06
A272: 附件1：美好生活3号-基础资产清单.xlsx | B272: 房源维度结算底表 | C272: 107114285441 | D272: 76500 | E272: 0.88 | F272: 67320 | G272: 2028-08-05 | H272: 2550 | I272: 4800 | K272: 76500 | L272: 1820 | M272: 1820 | N272: 0 | O272: 2026-02-05
A273: 附件1：美好生活3号-基础资产清单.xlsx | B273: 房源维度结算底表 | C273: 107114644319 | D273: 96812 | E273: 0.88 | F273: 85194.56 | G273: 2028-08-05 | H273: 3250.84 | I273: 4600 | K273: 96812 | L273: 1890 | M273: 1890 | N273: 0 | O273: 2026-02-05
A274: 附件1：美好生活3号-基础资产清单.xlsx | B274: 房源维度结算底表 | C274: 107114348733 | D274: 112000 | E274: 0.88 | F274: 98560 | G274: 2028-08-05 | H274: 3733.34 | I274: 5500 | K274: 112000 | L274: 2200 | M274: 2200 | N274: 0 | O274: 2026-02-05
A275: 附件1：美好生活3号-基础资产清单.xlsx | B275: 房源维度结算底表 | C275: 107114502274 | D275: 126609 | E275: 0.88 | F275: 111415.92 | G275: 2028-08-05 | H275: 4220.3 | I275: 5000 | K275: 126609 | L275: 2000 | M275: 2000 | N275: 0 | O275: 2026-02-05
A276: 附件1：美好生活3号-基础资产清单.xlsx | B276: 房源维度结算底表 | C276: 107114311994 | D276: 93814 | E276: 0.88 | F276: 82556.32 | G276: 2028-08-05 | H276: 3127.14 | I276: 4000 | K276: 93814 | L276: 5927.14 | M276: 5927.14 | N276: 0 | O276: 2026-01-05
A277: 附件1：美好生活3号-基础资产清单.xlsx | B277: 房源维度结算底表 | C277: 107113193877 | D277: 79145 | E277: 0.88 | F277: 63939.92 | G277: 2028-08-05 | H277: 2478 | I277: 4200 | J277: 单一信托 | K277: 79145 | M277: 6486 | N277: 6486 | O277: 2025-12-05
A278: 附件1：美好生活3号-基础资产清单.xlsx | B278: 房源维度结算底表 | C278: 107114319782 | D278: 72000 | E278: 0.88 | F278: 63360 | G278: 2028-08-04 | H278: 2400 | I278: 3000 | K278: 72000 | L278: 3600 | M278: 3600 | N278: 0 | O278: 2026-02-04
A279: 附件1：美好生活3号-基础资产清单.xlsx | B279: 房源维度结算底表 | C279: 107114393435 | D279: 58501 | E279: 0.88 | F279: 51480.88 | G279: 2028-08-04 | H279: 1950.04 | I279: 2170 | K279: 58501 | L279: 2818.04 | M279: 2818.04 | N279: 0 | O279: 2026-02-04
A280: 附件1：美好生活3号-基础资产清单.xlsx | B280: 房源维度结算底表 | C280: 107114364175 | D280: 101000 | E280: 0.88 | F280: 88880 | G280: 2028-08-04 | H280: 3366.67 | I280: 4800 | K280: 101000 | L280: 8653.34 | M280: 8653.34 | N280: 0 | O280: 2026-01-04
A281: 附件1：美好生活3号-基础资产清单.xlsx | B281: 房源维度结算底表 | C281: 107114224366 | D281: 69139 | E281: 0.88 | F281: 60842.32 | G281: 2028-08-03 | H281: 2304.64 | I281: 5000 | K281: 69139 | L281: 6609.28 | M281: 6609.28 | N281: 0 | O281: 2026-01-03
A282: 附件1：美好生活3号-基础资产清单.xlsx | B282: 房源维度结算底表 | C282: 107114340992 | D282: 103800 | E282: 0.88 | F282: 91344 | G282: 2028-08-03 | H282: 3460 | I282: 6500 | K282: 103800 | L282: 9570 | M282: 9570 | N282: 0 | O282: 2026-01-03
A283: 附件1：美好生活3号-基础资产清单.xlsx | B283: 房源维度结算底表 | C283: 107114009527 | D283: 98800 | E283: 0.88 | F283: 79827.72 | G283: 2028-08-03 | H283: 3293.34 | I283: 4000 | J283: 单一信托 | K283: 98800 | M283: 8086.68 | N283: 8086.68 | O283: 2026-01-03
A284: 附件1：美好生活3号-基础资产清单.xlsx | B284: 房源维度结算底表 | C284: 107114266874 | D284: 126026 | E284: 0.88 | F284: 110902.88 | G284: 2028-08-02 | H284: 4332.24 | I284: 7800 | K284: 126026 | L284: 7502.24 | M284: 7502.24 | N284: 0 | O284: 2026-02-02
A285: 附件1：美好生活3号-基础资产清单.xlsx | B285: 房源维度结算底表 | C285: 107114299652 | D285: 137164 | E285: 0.88 | F285: 120704.32 | G285: 2028-08-02 | H285: 4572.14 | I285: 6300 | K285: 137164 | L285: 6742.14 | M285: 6742.14 | N285: 0 | O285: 2026-02-02
A286: 附件1：美好生活3号-基础资产清单.xlsx | B286: 房源维度结算底表 | C286: 107114416552 | D286: 90000 | E286: 0.88 | F286: 79200 | G286: 2028-08-02 | H286: 3000 | I286: 4200 | K286: 90000 | L286: 7680 | M286: 7680 | N286: 0 | O286: 2026-01-02
A287: 附件1：美好生活3号-基础资产清单.xlsx | B287: 房源维度结算底表 | C287: 107113471357 | D287: 74100 | E287: 0.88 | F287: 62335.68 | G287: 2028-08-02 | H287: 2124 | I287: 3600 | J287: 单一信托 | K287: 74100 | M287: 3264 | N287: 3264 | O287: 2026-02-02
A288: 附件1：美好生活3号-基础资产清单.xlsx | B288: 房源维度结算底表 | C288: 107114544990 | D288: 87000 | E288: 0.88 | F288: 76560 | G288: 2028-08-01 | H288: 2900 | I288: 3600 | K288: 87000 | L288: 4340 | M288: 4340 | N288: 0 | O288: 2026-02-01
A289: 附件1：美好生活3号-基础资产清单.xlsx | B289: 房源维度结算底表 | C289: 107114476726 | D289: 134000 | E289: 0.88 | F289: 117920 | G289: 2028-08-01 | H289: 4466.67 | I289: 6500 | K289: 134000 | L289: 7066.67 | M289: 7066.67 | N289: 0 | O289: 2026-02-01
A290: 附件1：美好生活3号-基础资产清单.xlsx | B290: 房源维度结算底表 | C290: 107114561079 | D290: 95149 | E290: 0.88 | F290: 83731.12 | G290: 2028-08-01 | H290: 3171.64 | I290: 4100 | K290: 95149 | L290: 4861.64 | M290: 4861.64 | N290: 0 | O290: 2026-02-01
A291: 附件1：美好生活3号-基础资产清单.xlsx | B291: 房源维度结算底表 | C291: 107114314552 | D291: 85436 | E291: 0.88 | F291: 75183.68 | G291: 2028-08-01 | H291: 2847.87 | I291: 3500 | K291: 85436 | L291: 4247.87 | M291: 4247.87 | N291: 0 | O291: 2026-02-01
A292: 附件1：美好生活3号-基础资产清单.xlsx | B292: 房源维度结算底表 | C292: 107114366409 | D292: 91569 | E292: 0.88 | F292: 80580.72 | G292: 2028-08-01 | H292: 3052.3 | I292: 4000 | K292: 91569 | L292: 7704.6 | M292: 7704.6 | N292: 0 | O292: 2026-01-01
...

Sheet 数量和金额统计
C1: Values | G1: 当前信托计划（已发行） | H1: 求和项:剩余还款金额
A2: 所属文件名称 | B2: 所属Sheet名称 | C2: 计数项:托管房源编号 | D2: 求和项:当期实际还款金额 | G2: 信托1号 | H2: 22377504
A3: 美润1号_还款明细表_0529.xlsx | B3: 0325已还款 | C3: 47 | D3: 525012.9 | G3: 信托2号 | H3: 21481551
B4: 0430已还款 | C4: 60 | D4: 248346.52 | G4: 信托3号 | H4: 30650364
B5: 0508已还款 | C5: 15 | D5: 38367.96 | G5: 单一信托,信托3号 | H5: 3149041.2
B6: 0515已还款 | C6: 14 | D6: 29446 | G6: 单一信托 | H6: 5604531.3
B7: 0522已还款 | C7: 61 | D7: 1293329 | G7: 单一信托（2号） | H7: 1464129.7
B8: 0529已还款 | C8: 17 | D8: 35232.8 | G8: #N/A | H8: 32004
A9: 美润1号_还款明细表_0529.xlsx 汇总 | C9: 214 | D9: 2169735.2 | G9: (空白)
A10: 美好生活3号-还款明细披露信息_20260529_已更新0601.xlsx | B10: 0430已还款 | C10: 392 | D10: 2188927.8 | G10: 总计 | H10: 84759125
B11: 0508已还款 | C11: 154 | D11: 499210.87
B12: 0515已还款 | C12: 71 | D12: 232550.55
B13: 0522已还款 | C13: 76 | D13: 246265.95
B14: 0529已还款 | C14: 73 | D14: 234744.91
A15: 美好生活3号-还款明细披露信息_20260529_已更新0601.xlsx 汇总 | C15: 766 | D15: 3401700.1
A16: 美好生活2号-还款明细披露信息_20260529_已更新0601.xlsx | B16: 0119-已还款 | C16: 1198 | D16: 3720077.7
B17: 0123-已还款 | C17: 138 | D17: 442029.46 | H17: Values
B18: 0206-已还款 | C18: 131 | D18: 454421.13 | G18: 文件名 | H18: 计数项:房源编号 | I18: 求和项:应收账款合同金额 | J18: 求和项:应收账款转让价款 | K18: 平均值项:资产转让折扣率
B19: 0228-已还款 | C19: 216 | D19: 708416.09 | G19: 美润1号服务信托房源明细（首期转让）.xlsx | H19: 110 | I19: 11650165 | J19: 9718918.9 | K19: 0.85127273
B20: 0320-已还款 | C20: 157 | D20: 507948.69 | G20: 附件1：美好生活3号-基础资产清单.xlsx | H20: 407 | I20: 38924635 | J20: 33628584 | K20: 0.88223587
B21: 0327-已还款 | C21: 21 | D21: 61754 | G21: 附件1：美好生活2号-基础资产清单 1120.xlsx | H21: 310 | I21: 30219957 | J21: 26319602 | K21: 0.88
B22: 0403-已还款 | C22: 60 | D22: 198906.2 | G22: 附件1：基础资产清单（美好生活1号）.xlsx | H22: 412 | I22: 36302527 | J22: 31531666 | K22: 0.88
B23: 0410-已还款 | C23: 80 | D23: 256140.75 | G23: (空白)
B24: 0417-已还款 | C24: 48 | D24: 165122.67 | G24: 总计 | H24: 1239 | I24: 1.1709728e+08 | J24: 1.0119877e+08 | K24: 0.87818402
B25: 0424-已还款 | C25: 69 | D25: 233793.9 | H25: =I22/H22 -> 88112.929
B26: 0430-已还款 | C26: 60 | D26: 199421
B27: 0508-已还款 | C27: 93 | D27: 306345.95
B28: 0515-已还款 | C28: 45 | D28: 147068.67
B29: 0522-已还款 | C29: 49 | D29: 167413.16
A30: 美好生活2号-还款明细披露信息_20260529_已更新0601.xlsx 汇总 | C30: 2365 | D30: 7568859.4
A31: 美好生活2号-还款明细披露信息_20260529（0608更新） | B31: 0529-已还款 | C31: 117 | D31: 632993.18
A32: 美好生活2号-还款明细披露信息_20260529（0608更新） 汇总 | C32: 117 | D32: 632993.18
A33: 美好生活1号-还款明细披露信息_20260529_已更新0601_1.xlsx | B33: 0424-已还款 | C33: 107 | D33: 331200.16
B34: 0508-已还款 | C34: 150 | D34: 481547.02
B35: 0515-已还款 | C35: 50 | D35: 161472.5
B36: 0522-已还款 | C36: 87 | D36: 330394.66
B37: 信托还款明细--0929已还款 | C37: 1160 | D37: 3215725.3
B38: 还款明细--1017已还款 | C38: 185 | D38: 586239.92
B39: 还款明细-1031已还款 | C39: 215 | D39: 682172.05
B40: 还款明细-1114已还款 | C40: 166 | D40: 511457.25
B41: 还款明细-1128已还款 | C41: 213 | D41: 678347.05
B42: 还款明细-1212已还款 | C42: 168 | D42: 536119.33
B43: 还款明细-1226已还款 | C43: 218 | D43: 680095.04
B44: 还款明细-0109已还款 | C44: 151 | D44: 568018.46
B45: 还款明细-0123已还款 | C45: 178 | D45: 554166.52
... B53: 0501-已还款 | C53: 71 | D53: 272218.35
A54: 美好生活1号-还款明细披露信息_20260529_已更新0601_1.xlsx 汇总 | C54: 4097 | D54: 12640257
A55: 美好生活1号-还款明细披露信息_20260529（0608更新） | B55: 0529-已还款 | C55: 112 | D55: 409659.47
A56: 美好生活1号-还款明细披露信息_20260529（0608更新） 汇总 | C56: 112 | D56: 409659.47
A57: 美好生活1号-还款明细披露信息_20260605.xlsx | B57: 0605已还款 | C57: 112 | D57: 362704.2
A58: 美好生活1号-还款明细披露信息_20260605.xlsx 汇总 | C58: 112 | D58: 362704.2
A59: 美好生活2号-还款明细披露信息_20260605.xlsx | B59: 0605-已还款 | C59: 63 | D59: 226912.21
A60: 美好生活2号-还款明细披露信息_20260605.xlsx 汇总 | C60: 63 | D60: 226912.21
A61: 美好生活3号-还款明细披露信息_20260605.xlsx | B61: 0605已还款 | C61: 127 | D61: 645690.8
A62: 美好生活3号-还款明细披露信息_20260605.xlsx 汇总 | C62: 127 | D62: 645690.8
A63: 美润1号_还款明细表_0605.xlsx | B63: 0605已还款 | C63: 68 | D63: 577402.34
A64: 美润1号_还款明细表_0605.xlsx 汇总 | C64: 68 | D64: 577402.34
A65: 美好生活1号-还款明细披露信息_20260612 | B65: 0612已还款 | C65: 65 | D65: 205787.28
A66: 美好生活1号-还款明细披露信息_20260612 汇总 | C66: 65 | D66: 205787.28
A67: 美好生活2号-还款明细披露信息_20260612 | B67: 0612-已还款 | C67: 63 | D67: 198563.43
A68: 美好生活2号-还款明细披露信息_20260612 汇总 | C68: 63 | D68: 198563.43
A69: 美好生活3号-还款明细披露信息_20260612 | B69: 0612已还款 | C69: 111 | D69: 343177.02
A70: 美好生活3号-还款明细披露信息_20260612 汇总 | C70: 111 | D70: 343177.02
A71: 美润1号_还款明细表_0612 | B71: 0612已还款 | C71: 18 | D71: 68593.96
A72: 美润1号_还款明细表_0612 汇总 | C72: 18 | D72: 68593.96
A73: (空白) | B73: (空白)
A74: (空白) 汇总
A75: 总计 | C75: 8298 | D75: 29452035

Sheet 房源最后还款日
A1: 当期实际还款金额 | B1: (全部)
B3: Values
A4: 托管房源编号 | B4: 最大值项:还款日期 | C4: 标准偏差项:当期实际还款金额
A5: 107113471357 | B5: 46185 | C5: 554.17886
A6: 107113694737 | B6: 46178 | C6: 6016.0009
A7: 107113385212 | B7: 46171 | C7: 3377.64
A8: 107114212209 | B8: 46171 | C8: 1766.2673
A9: 107113045363 | B9: 46171 | C9: 1812.3401
A10: 107114495649 | B10: 46185 | C10: 2313.9541
A11: 107113193877 | B11: 46185 | C11: 1811.7111
A12: 107112417471 | B12: 46185 | C12: 7127.6364
A13: 107114226759 | B13: 46178 | C13: 5025
A14: 107113184658 | B14: 46178 | C14: 5867.5092
A15: 101128210944 | B15: 46178 | C15: 24500
A16: 107114205966 | B16: 46185 | C16: 6824.5839
... A111: 107112416833 | B111: 46185 | C111: 6153.9995
A112: 107112381197 | B112: 46164 | C112: #DIV/0!
A113: 107112234817 | B113: 46164 | C113: #DIV/0!
A114: 101134445166 | B114: 46178 | C114: 1339.4526
A115: 101133822347 | B115: 46185 | C115: 1616.5808
A116: 107114291360 | B116: 46178 | C116: 1062.3245
A117: 107114474902 | B117: 46185 | C117: 1223.9826
A118: 107114615743 | B118: 46185 | C118: 993.04246
A119: 107114233912 | B119: 46185 | C119: 1658.0345
A120: 107114591839 | B120: 46185 | C120: 1050.7775
A121: 107114187138 | B121: 46178 | C121: 2391.8594
A122: 107114218904 | B122: 46178 | C122: 1431.8287
A123: 107114562119 | B123: 46178 | C123: 2663.8941
A124: 107114119448 | B124: 46178 | C124: 1010.363
A125: 107114470189 | B125: 46178 | C125: 0
... A339: 107114212597 | B339: 46178 | C339: 4.3158373e-05
A340: 107114216499 | B340: 46142 | C340: #DIV/0!
A341: 107114214318 | B341: 46171 | C341: 2021.1021
A342: 107114217194 | B342: 46171 | C342: 3780.6454
A343: 107114196146 | B343: 46164 | C343: 2233.6089
A344: 107114187667 | B344: 46164 | C344: 1780.6363
A345: 107114173043 | B345: 46164 | C345: 2498.4487
A346: 107114046870 | B346: 46157 | C346: 2021.4769
A347: 107114168313 | B347: 46185 | C347: 1794.7484
A348: 107114163298 | B348: 46185 | C348: 1355.5154
A349: 107114156623 | B349: 46157 | C349: 2032.9815
A350: 107114168845 | B350: 46164 | C350: 1868.6287
A351: 107114154638 | B351: 46164 | C351: 2192.031
A352: 107114153092 | B352: 46171 | C352: 2176.1706
... A355: 107114144525 | B355: 46171 | C355: 1609.7781
A356: 107114130134 | B356: 46142 | C356: #DIV/0!
A357: 107114104300 | B357: 46164 | C357: 2560.1084
A358: 107114128993 | B358: 46171 | C358: 2538.8669
A359: 107114049788 | B359: 46171 | C359: 2380.5952
A360: 107114127132 | B360: 46171 | C360: 2644.3248
A361: 107114124215 | B361: 46178 | C361: 8.6316746e-05
A362: 107114121781 | B362: 46164 | C362: 1885.6204
A363: 107114107610 | B363: 46171 | C363: 1697.0563
A364: 107114114159 | B364: 46157 | C364: 1649.9205
A365: 107114080459 | B365: 46185 | C365: 2047.427
A366: 107114098565 | B366: 46164 | C366: 2308.6612
A367: 107114107378 | B367: 46185 | C367: 174.61821
A368: 107114087340 | B368: 46164 | C368: 1697.0563
... A775: 107113518726 | B775: 46041 | C775: 0
A776: 214225739872 | B776: 46101 | C776: #DIV/0!
A777: 101127075900 | B777: 46164 | C777: 2176.4282
A778: 101127311840 | B778: 46171 | C778: 41.636656
A779: 101127339909 | B779: 46185 | C779: 3038.6566
A780: 101127524235 | B780: 46164 | C780: 18.335
A781: 101127626459 | B781: 46157 | C781: 1463.3696
A782: 101127687701 | B782: 46178 | C782: 1261.7514
A783: 101127876784 | B783: 46171 | C783: 387.90711
A784: 101127962550 | B784: 46171 | C784: 0
A785: 101128141006 | B785: 46185 | C785: 943.30743
A786: 101128199395 | B786: 46171 | C786: 552.05705
A787: 101128199843 | B787: 46178 | C787: 0
A788: 101128209031 | B788: 46157 | C788: 0
... A1188: 107113387330 | B1188: 46178 | C1188: 248.55502
A1189: 107114866922 | B1189: 46171 | C1189: #DIV/0!
A1190: 107114931134 | B1190: 46171 | C1190: #DIV/0!
A1191: 107114266874 | B1191: 46185 | C1191: 2993.183
A1192: 107114252213 | B1192: 46185 | C1192: 543.88532
A1193: 107114071026 | B1193: 46185 | C1193: 7780.4232
A1194: 107114066861 | B1194: 46178 | C1194: #DIV/0!
A1195: 107114097097 | B1195: 46185 | C1195: 6987.3959
A1196: 107114057892 | B1196: 46185 | C1196: 9585.5395
A1197: 107113468720 | B1197: 46178 | C1197: #DIV/0!
A1198: 101131095241 | B1198: 46178 | C1198: #DIV/0!
A1199: 101134151279 | B1199: 46178 | C1199: #DIV/0!
A1200: 101131517600 | B1200: 46178 | C1200: #DIV/0!
A1201: 101134126007 | B1201: 46178 | C1201: #DIV/0!
A1202: 101134405206 | B1202: 46178 | C1202: #DIV/0!
A1203: 101133437865 | B1203: 46178 | C1203: #DIV/0!
A1204: 101133841636 | B1204: 46178 | C1204: #DIV/0!
A1205: 101133424088 | B1205: 46178 | C1205: #DIV/0!
A1206: 101133459027 | B1206: 46178 | C1206: #DIV/0!
A1207: 101135016159 | B1207: 46185 | C1207: 6717.5144
A1208: 101127099270 | B1208: 46178 | C1208: #DIV/0!
A1209: 101134681653 | B1209: 46178 | C1209: #DIV/0!
A1210: 101133949419 | B1210: 46178 | C1210: #DIV/0!
A1211: 101135016271 | B1211: 46178 | C1211: #DIV/0!
A1212: 101135049654 | B1212: 46178 | C1212: #DIV/0!
A1213: 101133641794 | B1213: 46178 | C1213: #DIV/0!
A1214: 101133235360 | B1214: 46178 | C1214: #DIV/0!
A1215: 101134387614 | B1215: 46178 | C1215: #DIV/0!
...

Sheet 提前还款
A1: 所属文件名称 | B1: 房源编号
A2: 美润1号 | B2: 107112381197
A3: 美好生活2号 | B3: 107112396048
A4: 美好生活2号 | B4: 101127824384
A5: 美好生活1号 | B5: 107112700446
A6: 美好生活1号 | B6: 101130093956
A7: 美好生活1号 | B7: 101130834372
A8: 美好生活2号 | B8: 107113347933
A9: 美好生活2号 | B9: 101130970695
A10: 美好生活3号 | B10: 101132159673
A11: 美好生活3号 | B11: 101132273734
A12: 美润1号 | B12: 101130772992
... A14: 美好生活3号 | B14: 101130770124

Sheet 逾期自检0618
A1: 托管房源编号 | B1: 发行 | C1: 城市 | D1: 最大值项:还款日期 | E1: 剩余还款金额 | F1: 是否是提前还款 | G1: 信托已经要求逾期反馈
A2: 101116255967 | B2: =VLOOKUP(A2,'3已发行数据0610（明道云数据）'!B:N,13,FALSE) -> 单一信托（2号） | C2: =VLOOKUP(A2,'3已发行数据0610（明道云数据）'!B:D,3,FALSE) -> 北京 | D2: =VLOOKUP(A2,房源最后还款日!A:B,2,FALSE) -> 46178 | E2: =VLOOKUP(A2,'2更新的资产数据表'!C:G,5,FALSE) -> 7480 | F2: =VLOOKUP(A2,提前还款!B:B,1,FALSE) -> #N/A | G2: =VLOOKUP(A2,信托逾期反馈!A:A,1,FALSE) -> #N/A
A3: 101117377965 | B3: =VLOOKUP(A3,'3已发行数据0610（明道云数据）'!B:N,13,FALSE) -> 信托2号 | C3: =VLOOKUP(A3,'3已发行数据0610（明道云数据）'!B:D,3,FALSE) -> 北京 | D3: =VLOOKUP(A3,房源最后还款日!A:B,2,FALSE) -> 46164 | E3: =VLOOKUP(A3,'2更新的资产数据表'!C:G,5,FALSE) -> 36749 | F3: =VLOOKUP(A3,提前还款!B:B,1,FALSE) -> #N/A | G3: =VLOOKUP(A3,信托逾期反馈!A:A,1,FALSE) -> #N/A
A4: 101127075900 | B4: =VLOOKUP(A4,'3已发行数据0610（明道云数据）'!B:N,13,FALSE) -> 信托1号 | C4: =VLOOKUP(A4,'3已发行数据0610（明道云数据）'!B:D,3,FALSE) -> 北京 | D4: =VLOOKUP(A4,房源最后还款日!A:B,2,FALSE) -> 46164 | E4: =VLOOKUP(A4,'2更新的资产数据表'!C:G,5,FALSE) -> 34719 | F4: =VLOOKUP(A4,提前还款!B:B,1,FALSE) -> #N/A | G4: =VLOOKUP(A4,信托逾期反馈!A:A,1,FALSE) -> #N/A
A5: 101127099270 | B5: =VLOOKUP(A5,'3已发行数据0610（明道云数据）'!B:N,13,FALSE) -> 单一信托（2号） | C5: =VLOOKUP(A5,'3已发行数据0610（明道云数据）'!B:D,3,FALSE) -> 北京 | D5: =VLOOKUP(A5,房源最后还款日!A:B,2,FALSE) -> 46178 | E5: =VLOOKUP(A5,'2更新的资产数据表'!C:G,5,FALSE) -> 17140 | F5: =VLOOKUP(A5,提前还款!B:B,1,FALSE) -> #N/A | G5: =VLOOKUP(A5,信托逾期反馈!A:A,1,FALSE) -> #N/A
A6: 101127311840 | B6: =VLOOKUP(A6,'3已发行数据0610（明道云数据）'!B:N,13,FALSE) -> 信托1号 | C6: =VLOOKUP(A6,'3已发行数据0610（明道云数据）'!B:D,3,FALSE) -> 北京 | D6: =VLOOKUP(A6,房源最后还款日!A:B,2,FALSE) -> 46171 | E6: =VLOOKUP(A6,'2更新的资产数据表'!C:G,5,FALSE) -> 38576.03 | F6: =VLOOKUP(A6,提前还款!B:B,1,FALSE) -> #N/A | G6: =VLOOKUP(A6,信托逾期反馈!A:A,1,FALSE) -> 101127311840
A7: 101127339909 | B7: =VLOOKUP(A7,'3已发行数据0610（明道云数据）'!B:N,13,FALSE) -> 信托1号 | C7: =VLOOKUP(A7,'3已发行数据0610（明道云数据）'!B:D,3,FALSE) -> 北京 | D7: =VLOOKUP(A7,房源最后还款日!A:B,2,FALSE) -> 46185 | E7: =VLOOKUP(A7,'2更新的资产数据表'!C:G,5,FALSE) -> 16745 | F7: =VLOOKUP(A7,提前还款!B:B,1,FALSE) -> #N/A | G7: =VLOOKUP(A7,信托逾期反馈!A:A,1,FALSE) -> #N/A
A8: 101127524235 | B8: =VLOOKUP(A8,'3已发行数据0610（明道云数据）'!B:N,13,FALSE) -> 信托1号 | C8: =VLOOKUP(A8,'3已发行数据0610（明道云数据）'!B:D,3,FALSE) -> 北京 | D8: =VLOOKUP(A8,房源最后还款日!A:B,2,FALSE) -> 46164 | E8: =VLOOKUP(A8,'2更新的资产数据表'!C:G,5,FALSE) -> 28330.01 | F8: =VLOOKUP(A8,提前还款!B:B,1,FALSE) -> #N/A | G8: =VLOOKUP(A8,信托逾期反馈!A:A,1,FALSE) -> 101127524235
A9: 101127526338 | B9: =VLOOKUP(A9,'3已发行数据0610（明道云数据）'!B:N,13,FALSE) -> 信托2号 | C9: =VLOOKUP(A9,'3已发行数据0610（明道云数据）'!B:D,3,FALSE) -> 北京 | D9: =VLOOKUP(A9,房源最后还款日!A:B,2,FALSE) -> 46171 | E9: =VLOOKUP(A9,'2更新的资产数据表'!C:G,5,FALSE) -> 63350 | F9: =VLOOKUP(A9,提前还款!B:B,1,FALSE) -> #N/A | G9: =VLOOKUP(A9,信托逾期反馈!A:A,1,FALSE) -> #N/A
A10: 101127626459 | B10: =VLOOKUP(A10,'3已发行数据0610（明道云数据）'!B:N,13,FALSE) -> 信托1号 | C10: =VLOOKUP(A10,'3已发行数据0610（明道云数据）'!B:D,3,FALSE) -> 北京 | D10: =VLOOKUP(A10,房源最后还款日!A:B,2,FALSE) -> 46157 | E10: =VLOOKUP(A10,'2更新的资产数据表'!C:G,5,FALSE) -> 55205 | F10: =VLOOKUP(A10,提前还款!B:B,1,FALSE) -> #N/A | G10: =VLOOKUP(A10,信托逾期反馈!A:A,1,FALSE) -> #N/A
A11: 101127659284 | B11: =VLOOKUP(A11,'3已发行数据0610（明道云数据）'!B:N,13,FALSE) -> 信托2号 | C11: =VLOOKUP(A11,'3已发行数据0610（明道云数据）'!B:D,3,FALSE) -> 北京 | D11: =VLOOKUP(A11,房源最后还款日!A:B,2,FALSE) -> 46185 | E11: =VLOOKUP(A11,'2更新的资产数据表'!C:G,5,FALSE) -> 85640 | F11: =VLOOKUP(A11,提前还款!B:B,1,FALSE) -> #N/A | G11: =VLOOKUP(A11,信托逾期反馈!A:A,1,FALSE) -> #N/A
A12: 101127687701 | B12: =VLOOKUP(A12,'3已发行数据0610（明道云数据）'!B:N,13,FALSE) -> 信托1号 | C12: =VLOOKUP(A12,'3已发行数据0610（明道云数据）'!B:D,3,FALSE) -> 北京 | D12: =VLOOKUP(A12,房源最后还款日!A:B,2,FALSE) -> 46178 | E12: =VLOOKUP(A12,'2更新的资产数据表'!C:G,5,FALSE) -> 34251.33 | F12: =VLOOKUP(A12,提前还款!B:B,1,FALSE) -> #N/A | G12: =VLOOKUP(A12,信托逾期反馈!A:A,1,FALSE) -> #N/A
A13: 101127783856 | B13: =VLOOKUP(A13,'3已发行数据0610（明道云数据）'!B:N,13,FALSE) -> 信托2号 | C13: =VLOOKUP(A13,'3已发行数据0610（明道云数据）'!B:D,3,FALSE) -> 北京 | D13: =VLOOKUP(A13,房源最后还款日!A:B,2,FALSE) -> 46164 | E13: =VLOOKUP(A13,'2更新的资产数据表'!C:G,5,FALSE) -> 64628 | F13: =VLOOKUP(A13,提前还款!B:B,1,FALSE) -> #N/A | G13: =VLOOKUP(A13,信托逾期反馈!A:A,1,FALSE) -> #N/A
... A59: 101129405710 | B59: =VLOOKUP(A59,'3已发行数据0610（明道云数据）'!B:N,13,FALSE) -> 信托1号 | C59: =VLOOKUP(A59,'3已发行数据0610（明道云数据）'!B:D,3,FALSE) -> 北京 | D59: =VLOOKUP(A59,房源最后还款日!A:B,2,FALSE) -> 46157 | E59: =VLOOKUP(A59,'2更新的资产数据表'!C:G,5,FALSE) -> 37390 | F59: =VLOOKUP(A59,提前还款!B:B,1,FALSE) -> #N/A | G59: =VLOOKUP(A59,信托逾期反馈!A:A,1,FALSE) -> #N/A
A60: 101129422479 | B60: =VLOOKUP(A60,'3已发行数据0610（明道云数据）'!B:N,13,FALSE) -> 信托1号 | C60: =VLOOKUP(A60,'3已发行数据0610（明道云数据）'!B:D,3,FALSE) -> 北京 | D60: =VLOOKUP(A60,房源最后还款日!A:B,2,FALSE) -> 46150 | E60: =VLOOKUP(A60,'2更新的资产数据表'!C:G,5,FALSE) -> 33785 | F60: =VLOOKUP(A60,提前还款!B:B,1,FALSE) -> #N/A | G60: =VLOOKUP(A60,信托逾期反馈!A:A,1,FALSE) -> #N/A | H60: =VLOOKUP(G60,信托逾期反馈!A:G,7,FALSE) -> #N/A
A61: 101129442765 | B61: =VLOOKUP(A61,'3已发行数据0610（明道云数据）'!B:N,13,FALSE) -> 信托1号 | C61: =VLOOKUP(A61,'3已发行数据0610（明道云数据）'!B:D,3,FALSE) -> 北京 | D61: =VLOOKUP(A61,房源最后还款日!A:B,2,FALSE) -> 46178 | E61: =VLOOKUP(A61,'2更新的资产数据表'!C:G,5,FALSE) -> 56884 | F61: =VLOOKUP(A61,提前还款!B:B,1,FALSE) -> #N/A | G61: =VLOOKUP(A61,信托逾期反馈!A:A,1,FALSE) -> #N/A
A62: 101129452604 | B62: =VLOOKUP(A62,'3已发行数据0610（明道云数据）'!B:N,13,FALSE) -> 信托1号 | C62: =VLOOKUP(A62,'3已发行数据0610（明道云数据）'!B:D,3,FALSE) -> 北京 | D62: =VLOOKUP(A62,房源最后还款日!A:B,2,FALSE) -> 46185 | E62: =VLOOKUP(A62,'2更新的资产数据表'!C:G,5,FALSE) -> 53865 | F62: =VLOOKUP(A62,提前还款!B:B,1,FALSE) -> #N/A | G62: =VLOOKUP(A62,信托逾期反馈!A:A,1,FALSE) -> #N/A
A63: 101129460405 | B63: =VLOOKUP(A63,'3已发行数据0610（明道云数据）'!B:N,13,FALSE) -> 信托1号 | C63: =VLOOKUP(A63,'3已发行数据0610（明道云数据）'!B:D,3,FALSE) -> 北京 | D63: =VLOOKUP(A63,房源最后还款日!A:B,2,FALSE) -> 46171 | E63: =VLOOKUP(A63,'2更新的资产数据表'!C:G,5,FALSE) -> 30770 | F63: =VLOOKUP(A63,提前还款!B:B,1,FALSE) -> #N/A | G63: =VLOOKUP(A63,信托逾期反馈!A:A,1,FALSE) -> #N/A
A64: 101129472286 | B64: =VLOOKUP(A64,'3已发行数据0610（明道云数据）'!B:N,13,FALSE) -> 信托1号 | C64: =VLOOKUP(A64,'3已发行数据0610（明道云数据）'!B:D,3,FALSE) -> 北京 | D64: =VLOOKUP(A64,房源最后还款日!A:B,2,FALSE) -> 46185 | E64: =VLOOKUP(A64,'2更新的资产数据表'!C:G,5,FALSE) -> 54658 | F64: =VLOOKUP(A64,提前还款!B:B,1,FALSE) -> #N/A | G64: =VLOOKUP(A64,信托逾期反馈!A:A,1,FALSE) -> #N/A
A65: 101129491687 | B65: =VLOOKUP(A65,'3已发行数据0610（明道云数据）'!B:N,13,FALSE) -> 信托1号 | C65: =VLOOKUP(A65,'3已发行数据0610（明道云数据）'!B:D,3,FALSE) -> 北京 | D65: =VLOOKUP(A65,房源最后还款日!A:B,2,FALSE) -> 46164 | E65: =VLOOKUP(A65,'2更新的资产数据表'!C:G,5,FALSE) -> 97211 | F65: =VLOOKUP(A65,提前还款!B:B,1,FALSE) -> #N/A | G65: =VLOOKUP(A65,信托逾期反馈!A:A,1,FALSE) -> #N/A
A66: 101129492083 | B66: =VLOOKUP(A66,'3已发行数据0610（明道云数据）'!B:N,13,FALSE) -> 信托1号 | C66: =VLOOKUP(A66,'3已发行数据0610（明道云数据）'!B:D,3,FALSE) -> 北京 | D66: =VLOOKUP(A66,房源最后还款日!A:B,2,FALSE) -> 46178 | E66: =VLOOKUP(A66,'2更新的资产数据表'!C:G,5,FALSE) -> 37585 | F66: =VLOOKUP(A66,提前还款!B:B,1,FALSE) -> #N/A | G66: =VLOOKUP(A66,信托逾期反馈!A:A,1,FALSE) -> #N/A
A67: 101129508743 | B67: =VLOOKUP(A67,'3已发行数据0610（明道云数据）'!B:N,13,FALSE) -> 信托1号 | C67: =VLOOKUP(A67,'3已发行数据0610（明道云数据）'!B:D,3,FALSE) -> 北京 | D67: =VLOOKUP(A67,房源最后还款日!A:B,2,FALSE) -> 46157 | E67: =VLOOKUP(A67,'2更新的资产数据表'!C:G,5,FALSE) -> 45280 | F67: =VLOOKUP(A67,提前还款!B:B,1,FALSE) -> #N/A | G67: =VLOOKUP(A67,信托逾期反馈!A:A,1,FALSE) -> #N/A
A68: 101129527798 | B68: =VLOOKUP(A68,'3已发行数据0610（明道云数据）'!B:N,13,FALSE) -> 信托1号 | C68: =VLOOKUP(A68,'3已发行数据0610（明道云数据）'!B:D,3,FALSE) -> 北京 | D68: =VLOOKUP(A68,房源最后还款日!A:B,2,FALSE) -> 46178 | E68: =VLOOKUP(A68,'2更新的资产数据表'!C:G,5,FALSE) -> 58920 | F68: =VLOOKUP(A68,提前还款!B:B,1,FALSE) -> #N/A | G68: =VLOOKUP(A68,信托逾期反馈!A:A,1,FALSE) -> #N/A
A69: 101129543144 | B69: =VLOOKUP(A69,'3已发行数据0610（明道云数据）'!B:N,13,FALSE) -> 信托1号 | C69: =VLOOKUP(A69,'3已发行数据0610（明道云数据）'!B:D,3,FALSE) -> 北京 | D69: =VLOOKUP(A69,房源最后还款日!A:B,2,FALSE) -> 46171 | E69: =VLOOKUP(A69,'2更新的资产数据表'!C:G,5,FALSE) -> 30751.33 | F69: =VLOOKUP(A69,提前还款!B:B,1,FALSE) -> #N/A | G69: =VLOOKUP(A69,信托逾期反馈!A:A,1,FALSE) -> #N/A
A70: 101129550929 | B70: =VLOOKUP(A70,'3已发行数据0610（明道云数据）'!B:N,13,FALSE) -> 信托1号 | C70: =VLOOKUP(A70,'3已发行数据0610（明道云数据）'!B:D,3,FALSE) -> 北京 | D70: =VLOOKUP(A70,房源最后还款日!A:B,2,FALSE) -> 46185 | E70: =VLOOKUP(A70,'2更新的资产数据表'!C:G,5,FALSE) -> 48073 | F70: =VLOOKUP(A70,提前还款!B:B,1,FALSE) -> #N/A | G70: =VLOOKUP(A70,信托逾期反馈!A:A,1,FALSE) -> #N/A
A71: 101129554327 | B71: =VLOOKUP(A71,'3已发行数据0610（明道云数据）'!B:N,13,FALSE) -> 信托1号 | C71: =VLOOKUP(A71,'3已发行数据0610（明道云数据）'!B:D,3,FALSE) -> 北京 | D71: =VLOOKUP(A71,房源最后还款日!A:B,2,FALSE) -> 46171 | E71: =VLOOKUP(A71,'2更新的资产数据表'!C:G,5,FALSE) -> 51381.66 | F71: =VLOOKUP(A71,提前还款!B:B,1,FALSE) -> #N/A | G71: =VLOOKUP(A71,信托逾期反馈!A:A,1,FALSE) -> #N/A
A72: 101129560839 | B72: =VLOOKUP(A72,'3已发行数据0610（明道云数据）'!B:N,13,FALSE) -> 信托1号 | C72: =VLOOKUP(A72,'3已发行数据0610（明道云数据）'!B:D,3,FALSE) -> 北京 | D72: =VLOOKUP(A72,房源最后还款日!A:B,2,FALSE) -> 46178 | E72: =VLOOKUP(A72,'2更新的资产数据表'!C:G,5,FALSE) -> 56568 | F72: =VLOOKUP(A72,提前还款!B:B,1,FALSE) -> #N/A | G72: =VLOOKUP(A72,信托逾期反馈!A:A,1,FALSE) -> #N/A
... A101: 101130017111 | B101: =VLOOKUP(A101,'3已发行数据0610（明道云数据）'!B:N,13,FALSE) -> 信托1号 | C101: =VLOOKUP(A101,'3已发行数据0610（明道云数据）'!B:D,3,FALSE) -> 北京 | D101: =VLOOKUP(A101,房源最后还款日!A:B,2,FALSE) -> 46171 | E101: =VLOOKUP(A101,'2更新的资产数据表'!C:G,5,FALSE) -> 39486 | F101: =VLOOKUP(A101,提前还款!B:B,1,FALSE) -> #N/A | G101: =VLOOKUP(A101,信托逾期反馈!A:A,1,FALSE) -> #N/A
A102: 101130021966 | B102: =VLOOKUP(A102,'3已发行数据0610（明道云数据）'!B:N,13,FALSE) -> 信托1号 | C102: =VLOOKUP(A102,'3已发行数据0610（明道云数据）'!B:D,3,FALSE) -> 北京 | D102: =VLOOKUP(A102,房源最后还款日!A:B,2,FALSE) -> 46150 | E102: =VLOOKUP(A102,'2更新的资产数据表'!C:G,5,FALSE) -> 55736.67 | F102: =VLOOKUP(A102,提前还款!B:B,1,FALSE) -> #N/A | G102: =VLOOKUP(A102,信托逾期反馈!A:A,1,FALSE) -> #N/A | H102: =VLOOKUP(G102,信托逾期反馈!A:G,7,FALSE) -> #N/A
A103: 101130063714 | B103: =VLOOKUP(A103,'3已发行数据0610（明道云数据）'!B:N,13,FALSE) -> 信托1号 | C103: =VLOOKUP(A103,'3已发行数据0610（明道云数据）'!B:D,3,FALSE) -> 北京 | D103: =VLOOKUP(A103,房源最后还款日!A:B,2,FALSE) -> 46178 | E103: =VLOOKUP(A103,'2更新的资产数据表'!C:G,5,FALSE) -> 45310 | F103: =VLOOKUP(A103,提前还款!B:B,1,FALSE) -> #N/A | G103: =VLOOKUP(A103,信托逾期反馈!A:A,1,FALSE) -> #N/A
A104: 101130065851 | B104: =VLOOKUP(A104,'3已发行数据0610（明道云数据）'!B:N,13,FALSE) -> 信托1号 | C104: =VLOOKUP(A104,'3已发行数据0610（明道云数据）'!B:D,3,FALSE) -> 北京 | D104: =VLOOKUP(A104,房源最后还款日!A:B,2,FALSE) -> 46178 | E104: =VLOOKUP(A104,'2更新的资产数据表'!C:G,5,FALSE) -> 50842 | F104: =VLOOKUP(A104,提前还款!B:B,1,FALSE) -> #N/A | G104: =VLOOKUP(A104,信托逾期反馈!A:A,1,FALSE) -> #N/A
A105: 101130093956 | B105: =VLOOKUP(A105,'3已发行数据0610（明道云数据）'!B:N,13,FALSE) -> 信托1号 | C105: =VLOOKUP(A105,'3已发行数据0610（明道云数据）'!B:D,3,FALSE) -> 北京 | D105: =VLOOKUP(A105,房源最后还款日!A:B,2,FALSE) -> 46143 | E105: =VLOOKUP(A105,'2更新的资产数据表'!C:G,5,FALSE) -> 0 | F105: =VLOOKUP(A105,提前还款!B:B,1,FALSE) -> 101130093956 | G105: =VLOOKUP(A105,信托逾期反馈!A:A,1,FALSE) -> 101130093956
A106: 101130107192 | B106: =VLOOKUP(A106,'3已发行数据0610（明道云数据）'!B:N,13,FALSE) -> 信托1号 | C106: =VLOOKUP(A106,'3已发行数据0610（明道云数据）'!B:D,3,FALSE) -> 北京 | D106: =VLOOKUP(A106,房源最后还款日!A:B,2,FALSE) -> 46185 | E106: =VLOOKUP(A106,'2更新的资产数据表'!C:G,5,FALSE) -> 27429 | F106: =VLOOKUP(A106,提前还款!B:B,1,FALSE) -> #N/A | G106: =VLOOKUP(A106,信托逾期反馈!A:A,1,FALSE) -> #N/A
A107: 101130115346 | B107: =VLOOKUP(A107,'3已发行数据0610（明道云数据）'!B:N,13,FALSE) -> 信托1号 | C107: =VLOOKUP(A107,'3已发行数据0610（明道云数据）'!B:D,3,FALSE) -> 北京 | D107: =VLOOKUP(A107,房源最后还款日!A:B,2,FALSE) -> 46185 | E107: =VLOOKUP(A107,'2更新的资产数据表'!C:G,5,FALSE) -> 34563 | F107: =VLOOKUP(A107,提前还款!B:B,1,FALSE) -> #N/A | G107: =VLOOKUP(A107,信托逾期反馈!A:A,1,FALSE) -> #N/A
A108: 101130125068 | B108: =VLOOKUP(A108,'3已发行数据0610（明道云数据）'!B:N,13,FALSE) -> 信托1号 | C108: =VLOOKUP(A108,'3已发行数据0610（明道云数据）'!B:D,3,FALSE) -> 北京 | D108: =VLOOKUP(A108,房源最后还款日!A:B,2,FALSE) -> 46178 | E108: =VLOOKUP(A108,'2更新的资产数据表'!C:G,5,FALSE) -> 44060 | F108: =VLOOKUP(A108,提前还款!B:B,1,FALSE) -> #N/A | G108: =VLOOKUP(A108,信托逾期反馈!A:A,1,FALSE) -> #N/A
A109: 101130133766 | B109: =VLOOKUP(A109,'3已发行数据0610（明道云数据）'!B:N,13,FALSE) -> 信托1号 | C109: =VLOOKUP(A109,'3已发行数据0610（明道云数据）'!B:D,3,FALSE) -> 北京 | D109: =VLOOKUP(A109,房源最后还款日!A:B,2,FALSE) -> 46157 | E109: =VLOOKUP(A109,'2更新的资产数据表'!C:G,5,FALSE) -> 54236.67 | F109: =VLOOKUP(A109,提前还款!B:B,1,FALSE) -> #N/A | G109: =VLOOKUP(A109,信托逾期反馈!A:A,1,FALSE) -> #N/A
A110: 101130133837 | B110: =VLOOKUP(A110,'3已发行数据0610（明道云数据）'!B:N,13,FALSE) -> 信托1号 | C110: =VLOOKUP(A110,'3已发行数据0610（明道云数据）'!B:D,3,FALSE) -> 北京 | D110: =VLOOKUP(A110,房源最后还款日!A:B,2,FALSE) -> 46185 | E110: =VLOOKUP(A110,'2更新的资产数据表'!C:G,5,FALSE) -> 35525 | F110: =VLOOKUP(A110,提前还款!B:B,1,FALSE) -> #N/A | G110: =VLOOKUP(A110,信托逾期反馈!A:A,1,FALSE) -> #N/A
A111: 101130154248 | B111: =VLOOKUP(A111,'3已发行数据0610（明道云数据）'!B:N,13,FALSE) -> 信托2号 | C111: =VLOOKUP(A111,'3已发行数据0610（明道云数据）'!B:D,3,FALSE) -> 北京 | D111: =VLOOKUP(A111,房源最后还款日!A:B,2,FALSE) -> 46171 | E111: =VLOOKUP(A111,'2更新的资产数据表'!C:G,5,FALSE) -> 53132 | F111: =VLOOKUP(A111,提前还款!B:B,1,FALSE) -> #N/A | G111: =VLOOKUP(A111,信托逾期反馈!A:A,1,FALSE) -> #N/A
A112: 101130177828 | B112: =VLOOKUP(A112,'3已发行数据0610（明道云数据）'!B:N,13,FALSE) -> 信托2号 | C112: =VLOOKUP(A112,'3已发行数据0610（明道云数据）'!B:D,3,FALSE) -> 北京 | D112: =VLOOKUP(A112,房源最后还款日!A:B,2,FALSE) -> 46171 | E112: =VLOOKUP(A112,'2更新的资产数据表'!C:G,5,FALSE) -> 132320 | F112: =VLOOKUP(A112,提前还款!B:B,1,FALSE) -> #N/A | G112: =VLOOKUP(A112,信托逾期反馈!A:A,1,FALSE) -> #N/A
A113: 101130181968 | B113: =VLOOKUP(A113,'3已发行数据0610（明道云数据）'!B:N,13,FALSE) -> 信托2号 | C113: =VLOOKUP(A113,'3已发行数据0610（明道云数据）'!B:D,3,FALSE) -> 北京 | D113: =VLOOKUP(A113,房源最后还款日!A:B,2,FALSE) -> 46171 | E113: =VLOOKUP(A113,'2更新的资产数据表'!C:G,5,FALSE) -> 84738.67 | F113: =VLOOKUP(A113,提前还款!B:B,1,FALSE) -> #N/A | G113: =VLOOKUP(A113,信托逾期反馈!A:A,1,FALSE) -> #N/A
A114: 101130183387 | B114: =VLOOKUP(A114,'3已发行数据0610（明道云数据）'!B:N,13,FALSE) -> 信托1号 | C114: =VLOOKUP(A114,'3已发行数据0610（明道云数据）'!B:D,3,FALSE) -> 北京 | D114: =VLOOKUP(A114,房源最后还款日!A:B,2,FALSE) -> 46178 | E114: =VLOOKUP(A114,'2更新的资产数据表'!C:G,5,FALSE) -> 51278.33 | F114: =VLOOKUP(A114,提前还款!B:B,1,FALSE) -> #N/A | G114: =VLOOKUP(A114,信托逾期反馈!A:A,1,FALSE) -> #N/A
... A162: 101130796627 | B162: =VLOOKUP(A162,'3已发行数据0610（明道云数据）'!B:N,13,FALSE) -> 信托1号 | C162: =VLOOKUP(A162,'3已发行数据0610（明道云数据）'!B:D,3,FALSE) -> 北京 | D162: =VLOOKUP(A162,房源最后还款日!A:B,2,FALSE) -> 46171 | E162: =VLOOKUP(A162,'2更新的资产数据表'!C:G,5,FALSE) -> 72749 | F162: =VLOOKUP(A162,提前还款!B:B,1,FALSE) -> #N/A | G162: =VLOOKUP(A162,信托逾期反馈!A:A,1,FALSE) -> #N/A
A163: 101130798182 | B163: =VLOOKUP(A163,'3已发行数据0610（明道云数据）'!B:N,13,FALSE) -> 信托1号 | C163: =VLOOKUP(A163,'3已发行数据0610（明道云数据）'!B:D,3,FALSE) -> 北京 | D163: =VLOOKUP(A163,房源最后还款日!A:B,2,FALSE) -> 45947 | E163: =VLOOKUP(A163,'2更新的资产数据表'!C:G,5,FALSE) -> 71199.99 | F163: =VLOOKUP(A163,提前还款!B:B,1,FALSE) -> #N/A | G163: =VLOOKUP(A163,信托逾期反馈!A:A,1,FALSE) -> 101130798182 | H163: =VLOOKUP(G163,信托逾期反馈!A:G,7,FALSE) -> 待手动结算付款
A164: 101130804848 | B164: =VLOOKUP(A164,'3已发行数据0610（明道云数据）'!B:N,13,FALSE) -> 信托3号 | C164: =VLOOKUP(A164,'3已发行数据0610（明道云数据）'!B:D,3,FALSE) -> 北京 | D164: =VLOOKUP(A164,房源最后还款日!A:B,2,FALSE) -> 46171 | E164: =VLOOKUP(A164,'2更新的资产数据表'!C:G,5,FALSE) -> 60833.32 | F164: =VLOOKUP(A164,提前还款!B:B,1,FALSE) -> #N/A | G164: =VLOOKUP(A164,信托逾期反馈!A:A,1,FALSE) -> #N/A
A165: 101130832096 | B165: =VLOOKUP(A165,'3已发行数据0610（明道云数据）'!B:N,13,FALSE) -> 信托2号 | C165: =VLOOKUP(A165,'3已发行数据0610（明道云数据）'!B:D,3,FALSE) -> 北京 | D165: =VLOOKUP(A165,房源最后还款日!A:B,2,FALSE) -> 46178 | E165: =VLOOKUP(A165,'2更新的资产数据表'!C:G,5,FALSE) -> 34993 | F165: =VLOOKUP(A165,提前还款!B:B,1,FALSE) -> #N/A | G165: =VLOOKUP(A165,信托逾期反馈!A:A,1,FALSE) -> #N/A
A166: 101130832352 | B166: =VLOOKUP(A166,'3已发行数据0610（明道云数据）'!B:N,13,FALSE) -> 信托2号 | C166: =VLOOKUP(A166,'3已发行数据0610（明道云数据）'!B:D,3,FALSE) -> 北京 | D166: =VLOOKUP(A166,房源最后还款日!A:B,2,FALSE) -> 46178 | E166: =VLOOKUP(A166,'2更新的资产数据表'!C:G,5,FALSE) -> 48732 | F166: =VLOOKUP(A166,提前还款!B:B,1,FALSE) -> #N/A | G166: =VLOOKUP(A166,信托逾期反馈!A:A,1,FALSE) -> #N/A
A167: 101130834372 | B167: =VLOOKUP(A167,'3已发行数据0610（明道云数据）'!B:N,13,FALSE) -> 信托1号 | C167: =VLOOKUP(A167,'3已发行数据0610（明道云数据）'!B:D,3,FALSE) -> 北京 | D167: =VLOOKUP(A167,房源最后还款日!A:B,2,FALSE) -> 46171 | E167: =VLOOKUP(A167,'2更新的资产数据表'!C:G,5,FALSE) -> 0 | F167: =VLOOKUP(A167,提前还款!B:B,1,FALSE) -> 101130834372 | G167: =VLOOKUP(A167,信托逾期反馈!A:A,1,FALSE) -> #N/A
A168: 101130853603 | B168: =VLOOKUP(A168,'3已发行数据0610（明道云数据）'!B:N,13,FALSE) -> 信托1号 | C168: =VLOOKUP(A168,'3已发行数据0610（明道云数据）'!B:D,3,FALSE) -> 北京 | D168: =VLOOKUP(A168,房源最后还款日!A:B,2,FALSE) -> 46185 | E168: =VLOOKUP(A168,'2更新的资产数据表'!C:G,5,FALSE) -> 50191 | F168: =VLOOKUP(A168,提前还款!B:B,1,FALSE) -> #N/A | G168: =VLOOKUP(A168,信托逾期反馈!A:A,1,FALSE) -> #N/A
A169: 101130853906 | B169: =VLOOKUP(A169,'3已发行数据0610（明道云数据）'!B:N,13,FALSE) -> 信托2号 | C169: =VLOOKUP(A169,'3已发行数据0610（明道云数据）'!B:D,3,FALSE) -> 北京 | D169: =VLOOKUP(A169,房源最后还款日!A:B,2,FALSE) -> 46185 | E169: =VLOOKUP(A169,'2更新的资产数据表'!C:G,5,FALSE) -> 44224.87 | F169: =VLOOKUP(A169,提前还款!B:B,1,FALSE) -> #N/A | G169: =VLOOKUP(A169,信托逾期反馈!A:A,1,FALSE) -> #N/A
A170: 101130876309 | B170: =VLOOKUP(A170,'3已发行数据0610（明道云数据）'!B:N,13,FALSE) -> 信托1号 | C170: =VLOOKUP(A170,'3已发行数据0610（明道云数据）'!B:D,3,FALSE) -> 北京 | D170: =VLOOKUP(A170,房源最后还款日!A:B,2,FALSE) -> 46157 | E170: =VLOOKUP(A170,'2更新的资产数据表'!C:G,5,FALSE) -> 40513 | F170: =VLOOKUP(A170,提前还款!B:B,1,FALSE) -> #N/A | G170: =VLOOKUP(A170,信托逾期反馈!A:A,1,FALSE) -> #N/A
A171: 101130877911 | B171: =VLOOKUP(A171,'3已发行数据0610（明道云数据）'!B:N,13,FALSE) -> 信托1号 | C171: =VLOOKUP(A171,'3已发行数据0610（明道云数据）'!B:D,3,FALSE) -> 北京 | D171: =VLOOKUP(A171,房源最后还款日!A:B,2,FALSE) -> 46164 | E171: =VLOOKUP(A171,'2更新的资产数据表'!C:G,5,FALSE) -> 64463.33 | F171: =VLOOKUP(A171,提前还款!B:B,1,FALSE) -> #N/A | G171: =VLOOKUP(A171,信托逾期反馈!A:A,1,FALSE) -> #N/A
A172: 101130889310 | B172: =VLOOKUP(A172,'3已发行数据0610（明道云数据）'!B:N,13,FALSE) -> 信托3号 | C172: =VLOOKUP(A172,'3已发行数据0610（明道云数据）'!B:D,3,FALSE) -> 北京 | D172: =VLOOKUP(A172,房源最后还款日!A:B,2,FALSE) -> 46171 | E172: =VLOOKUP(A172,'2更新的资产数据表'!C:G,5,FALSE) -> 103750 | F172: =VLOOKUP(A172,提前还款!B:B,1,FALSE) -> #N/A | G172: =VLOOKUP(A172,信托逾期反馈!A:A,1,FALSE) -> #N/A
A173: 101130890220 | B173: =VLOOKUP(A173,'3已发行数据0610（明道云数据）'!B:N,13,FALSE) -> 信托1号 | C173: =VLOOKUP(A173,'3已发行数据0610（明道云数据）'!B:D,3,FALSE) -> 北京 | D173: =VLOOKUP(A173,房源最后还款日!A:B,2,FALSE) -> 46178 | E173: =VLOOKUP(A173,'2更新的资产数据表'!C:G,5,FALSE) -> 48680 | F173: =VLOOKUP(A173,提前还款!B:B,1,FALSE) -> #N/A | G173: =VLOOKUP(A173,信托逾期反馈!A:A,1,FALSE) -> #N/A
A174: 101130908844 | B174: =VLOOKUP(A174,'3已发行数据0610（明道云数据）'!B:N,13,FALSE) -> 信托1号 | C174: =VLOOKUP(A174,'3已发行数据0610（明道云数据）'!B:D,3,FALSE) -> 北京 | D174: =VLOOKUP(A174,房源最后还款日!A:B,2,FALSE) -> 46157 | E174: =VLOOKUP(A174,'2更新的资产数据表'!C:G,5,FALSE) -> 51743.33 | F174: =VLOOKUP(A174,提前还款!B:B,1,FALSE) -> #N/A | G174: =VLOOKUP(A174,信托逾期反馈!A:A,1,FALSE) -> #N/A
A175: 101130931941 | B175: =VLOOKUP(A175,'3已发行数据0610（明道云数据）'!B:N,13,FALSE) -> 信托2号 | C175: =VLOOKUP(A175,'3已发行数据0610（明道云数据）'!B:D,3,FALSE) -> 北京 | D175: =VLOOKUP(A175,房源最后还款日!A:B,2,FALSE) -> 46171 | E175: =VLOOKUP(A175,'2更新的资产数据表'!C:G,5,FALSE) -> 62640 | F175: =VLOOKUP(A175,提前还款!B:B,1,FALSE) -> #N/A | G175: =VLOOKUP(A175,信托逾期反馈!A:A,1,FALSE) -> #N/A
... A229: 101132324518 | B229: =VLOOKUP(A229,'3已发行数据0610（明道云数据）'!B:N,13,FALSE) -> 单一信托（2号） | C229: =VLOOKUP(A229,'3已发行数据0610（明道云数据）'!B:D,3,FALSE) -> 北京 | D229: =VLOOKUP(A229,房源最后还款日!A:B,2,FALSE) -> 46178 | E229: =VLOOKUP(A229,'2更新的资产数据表'!C:G,5,FALSE) -> 14200 | F229: =VLOOKUP(A229,提前还款!B:B,1,FALSE) -> #N/A | G229: =VLOOKUP(A229,信托逾期反馈!A:A,1,FALSE) -> #N/A
A230: 101132506745 | B230: =VLOOKUP(A230,'3已发行数据0610（明道云数据）'!B:N,13,FALSE) -> 单一信托（2号） | C230: =VLOOKUP(A230,'3已发行数据0610（明道云数据）'!B:D,3,FALSE) -> 北京 | D230: =VLOOKUP(A230,房源最后还款日!A:B,2,FALSE) -> #N/A | E230: =VLOOKUP(A230,'2更新的资产数据表'!C:G,5,FALSE) -> 23074 | F230: =VLOOKUP(A230,提前还款!B:B,1,FALSE) -> #N/A | G230: =VLOOKUP(A230,信托逾期反馈!A:A,1,FALSE) -> 101132506745 | H230: =VLOOKUP(G230,信托逾期反馈!A:G,7,FALSE) -> 0
A231: 101132542218 | B231: =VLOOKUP(A231,'3已发行数据0610（明道云数据）'!B:N,13,FALSE) -> 信托2号 | C231: =VLOOKUP(A231,'3已发行数据0610（明道云数据）'!B:D,3,FALSE) -> 北京 | D231: =VLOOKUP(A231,房源最后还款日!A:B,2,FALSE) -> 46171 | E231: =VLOOKUP(A231,'2更新的资产数据表'!C:G,5,FALSE) -> 51600 | F231: =VLOOKUP(A231,提前还款!B:B,1,FALSE) -> #N/A | G231: =VLOOKUP(A231,信托逾期反馈!A:A,1,FALSE) -> #N/A
A232: 101132653786 | B232: =VLOOKUP(A232,'3已发行数据0610（明道云数据）'!B:N,13,FALSE) -> 单一信托（2号） | C232: =VLOOKUP(A232,'3已发行数据0610（明道云数据）'!B:D,3,FALSE) -> 北京 | D232: =VLOOKUP(A232,房源最后还款日!A:B,2,FALSE) -> 46178 | E232: =VLOOKUP(A232,'2更新的资产数据表'!C:G,5,FALSE) -> 18564.67 | F232: =VLOOKUP(A232,提前还款!B:B,1,FALSE) -> #N/A | G232: =VLOOKUP(A232,信托逾期反馈!A:A,1,FALSE) -> #N/A
A233: 101132741271 | B233: =VLOOKUP(A233,'3已发行数据0610（明道云数据）'!B:N,13,FALSE) -> 单一信托（2号） | C233: =VLOOKUP(A233,'3已发行数据0610（明道云数据）'!B:D,3,FALSE) -> 北京 | D233: =VLOOKUP(A233,房源最后还款日!A:B,2,FALSE) -> 46178 | E233: =VLOOKUP(A233,'2更新的资产数据表'!C:G,5,FALSE) -> 29007 | F233: =VLOOKUP(A233,提前还款!B:B,1,FALSE) -> #N/A | G233: =VLOOKUP(A233,信托逾期反馈!A:A,1,FALSE) -> #N/A
A234: 101132799241 | B234: =VLOOKUP(A234,'3已发行数据0610（明道云数据）'!B:N,13,FALSE) -> 单一信托（2号） | C234: =VLOOKUP(A234,'3已发行数据0610（明道云数据）'!B:D,3,FALSE) -> 北京 | D234: =VLOOKUP(A234,房源最后还款日!A:B,2,FALSE) -> #N/A | E234: =VLOOKUP(A234,'2更新的资产数据表'!C:G,5,FALSE) -> 22393 | F234: =VLOOKUP(A234,提前还款!B:B,1,FALSE) -> #N/A | G234: =VLOOKUP(A234,信托逾期反馈!A:A,1,FALSE) -> 101132799241 | H234: =VLOOKUP(G234,信托逾期反馈!A:G,7,FALSE) -> 0
A235: 101132820635 | B235: =VLOOKUP(A235,'3已发行数据0610（明道云数据）'!B:N,13,FALSE) -> 单一信托（2号） | C235: =VLOOKUP(A235,'3已发行数据0610（明道云数据）'!B:D,3,FALSE) -> 北京 | D235: =VLOOKUP(A235,房源最后还款日!A:B,2,FALSE) -> 46178 | E235: =VLOOKUP(A235,'2更新的资产数据表'!C:G,5,FALSE) -> 12988 | F235: =VLOOKUP(A235,提前还款!B:B,1,FALSE) -> #N/A | G235: =VLOOKUP(A235,信托逾期反馈!A:A,1,FALSE) -> #N/A
A236: 101132934089 | B236: =VLOOKUP(A236,'3已发行数据0610（明道云数据）'!B:N,13,FALSE) -> 单一信托,信托3号 | C236: =VLOOKUP(A236,'3已发行数据0610（明道云数据）'!B:D,3,FALSE) -> 北京 | D236: =VLOOKUP(A236,房源最后还款日!A:B,2,FALSE) -> 46178 | E236: =VLOOKUP(A236,'2更新的资产数据表'!C:G,5,FALSE) -> 0 | F236: =VLOOKUP(A236,提前还款!B:B,1,FALSE) -> 101132934089 | G236: =VLOOKUP(A236,信托逾期反馈!A:A,1,FALSE) -> #N/A
A237: 101132954804 | B237: =VLOOKUP(A237,'3已发行数据0610（明道云数据）'!B:N,13,FALSE) -> 单一信托（2号） | C237: =VLOOKUP(A237,'3已发行数据0610（明道云数据）'!B:D,3,FALSE) -> 北京 | D237: =VLOOKUP(A237,房源最后还款日!A:B,2,FALSE) -> 46185 | E237: =VLOOKUP(A237,'2更新的资产数据表'!C:G,5,FALSE) -> 29288 | F237: =VLOOKUP(A237,提前还款!B:B,1,FALSE) -> #N/A | G237: =VLOOKUP(A237,信托逾期反馈!A:A,1,FALSE) -> #N/A
A238: 101132986247 | B238: =VLOOKUP(A238,'3已发行数据0610（明道云数据）'!B:N,13,FALSE) -> 单一信托（2号） | C238: =VLOOKUP(A238,'3已发行数据0610（明道云数据）'!B:D,3,FALSE) -> 北京 | D238: =VLOOKUP(A238,房源最后还款日!A:B,2,FALSE) -> 46178 | E238: =VLOOKUP(A238,'2更新的资产数据表'!C:G,5,FALSE) -> 12762 | F238: =VLOOKUP(A238,提前还款!B:B,1,FALSE) -> #N/A | G238: =VLOOKUP(A238,信托逾期反馈!A:A,1,FALSE) -> #N/A
A239: 101133090637 | B239: =VLOOKUP(A239,'3已发行数据0610（明道云数据）'!B:N,13,FALSE) -> 单一信托（2号） | C239: =VLOOKUP(A239,'3已发行数据0610（明道云数据）'!B:D,3,FALSE) -> 北京 | D239: =VLOOKUP(A239,房源最后还款日!A:B,2,FALSE) -> 46178 | E239: =VLOOKUP(A239,'2更新的资产数据表'!C:G,5,FALSE) -> 25307 | F239: =VLOOKUP(A239,提前还款!B:B,1,FALSE) -> #N/A | G239: =VLOOKUP(A239,信托逾期反馈!A:A,1,FALSE) -> #N/A
A240: 101133108300 | B240: =VLOOKUP(A240,'3已发行数据0610（明道云数据）'!B:N,13,FALSE) -> 信托3号 | C240: =VLOOKUP(A240,'3已发行数据0610（明道云数据）'!B:D,3,FALSE) -> 北京 | D240: =VLOOKUP(A240,房源最后还款日!A:B,2,FALSE) -> 46185 | E240: =VLOOKUP(A240,'2更新的资产数据表'!C:G,5,FALSE) -> 4750 | F240: =VLOOKUP(A240,提前还款!B:B,1,FALSE) -> #N/A | G240: =VLOOKUP(A240,信托逾期反馈!A:A,1,FALSE) -> #N/A
A241: 101133128507 | B241: =VLOOKUP(A241,'3已发行数据0610（明道云数据）'!B:N,13,FALSE) -> 单一信托（2号） | C241: =VLOOKUP(A241,'3已发行数据0610（明道云数据）'!B:D,3,FALSE) -> 北京 | D241: =VLOOKUP(A241,房源最后还款日!A:B,2,FALSE) -> 46178 | E241: =VLOOKUP(A241,'2更新的资产数据表'!C:G,5,FALSE) -> 19405 | F241: =VLOOKUP(A241,提前还款!B:B,1,FALSE) -> #N/A | G241: =VLOOKUP(A241,信托逾期反馈!A:A,1,FALSE) -> #N/A
A242: 101133144076 | B242: =VLOOKUP(A242,'3已发行数据0610（明道云数据）'!B:N,13,FALSE) -> 信托3号 | C242: =VLOOKUP(A242,'3已发行数据0610（明道云数据）'!B:D,3,FALSE) -> 北京 | D242: =VLOOKUP(A242,房源最后还款日!A:B,2,FALSE) -> 46185 | E242: =VLOOKUP(A242,'2更新的资产数据表'!C:G,5,FALSE) -> 73111.08 | F242: =VLOOKUP(A242,提前还款!B:B,1,FALSE) -> #N/A | G242: =VLOOKUP(A242,信托逾期反馈!A:A,1,FALSE) -> #N/A
A243: 101133308003 | B243: =VLOOKUP(A243,'3已发行数据0610（明道云数据）'!B:N,13,FALSE) -> 信托3号 | C243: =VLOOKUP(A243,'3已发行数据0610（明道云数据）'!B:D,3,FALSE) -> 北京 | D243: =VLOOKUP(A243,房源最后还款日!A:B,2,FALSE) -> 46178 | E243: =VLOOKUP(A243,'2更新的资产数据表'!C:G,5,FALSE) -> 77752.22 | F243: =VLOOKUP(A243,提前还款!B:B,1,FALSE) -> #N/A | G243: =VLOOKUP(A243,信托逾期反馈!A:A,1,FALSE) -> #N/A
A244: 101133365464 | B244: =VLOOKUP(A244,'3已发行数据0610（明道云数据）'!B:N,13,FALSE) -> 单一信托（2号） | C244: =VLOOKUP(A244,'3已发行数据0610（明道云数据）'!B:D,3,FALSE) -> 北京 | D244: =VLOOKUP(A244,房源最后还款日!A:B,2,FALSE) -> 46178 | E244: =VLOOKUP(A244,'2更新的资产数据表'!C:G,5,FALSE) -> 31050 | F244: =VLOOKUP(A244,提前还款!B:B,1,FALSE) -> #N/A | G244: =VLOOKUP(A244,信托逾期反馈!A:A,1,FALSE) -> #N/A
A245: 101133369559 | B245: =VLOOKUP(A245,'3已发行数据0610（明道云数据）'!B:N,13,FALSE) -> 单一信托（2号） | C245: =VLOOKUP(A245,'3已发行数据0610（明道云数据）'!B:D,3,FALSE) -> 北京 | D245: =VLOOKUP(A245,房源最后还款日!A:B,2,FALSE) -> 46178 | E245: =VLOOKUP(A245,'2更新的资产数据表'!C:G,5,FALSE) -> 39800 | F245: =VLOOKUP(A245,提前还款!B:B,1,FALSE) -> #N/A | G245: =VLOOKUP(A245,信托逾期反馈!A:A,1,FALSE) -> #N/A
A246: 101133382432 | B246: =VLOOKUP(A246,'3已发行数据0610（明道云数据）'!B:N,13,FALSE) -> 单一信托（2号） | C246: =VLOOKUP(A246,'3已发行数据0610（明道云数据）'!B:D,3,FALSE) -> 北京 | D246: =VLOOKUP(A246,房源最后还款日!A:B,2,FALSE) -> 46185 | E246: =VLOOKUP(A246,'2更新的资产数据表'!C:G,5,FALSE) -> 19860 | F246: =VLOOKUP(A246,提前还款!B:B,1,FALSE) -> #N/A | G246: =VLOOKUP(A246,信托逾期反馈!A:A,1,FALSE) -> #N/A
... A258: 101133756301 | B258: =VLOOKUP(A258,'3已发行数据0610（明道云数据）'!B:N,13,FALSE) -> 单一信托（2号） | C258: =VLOOKUP(A258,'3已发行数据0610（明道云数据）'!B:D,3,FALSE) -> 北京 | D258: =VLOOKUP(A258,房源最后还款日!A:B,2,FALSE) -> 46178 | E258: =VLOOKUP(A258,'2更新的资产数据表'!C:G,5,FALSE) -> 13140 | F258: =VLOOKUP(A258,提前还款!B:B,1,FALSE) -> #N/A | G258: =VLOOKUP(A258,信托逾期反馈!A:A,1,FALSE) -> #N/A
A259: 101133789300 | B259: =VLOOKUP(A259,'3已发行数据0610（明道云数据）'!B:N,13,FALSE) -> 单一信托（2号） | C259: =VLOOKUP(A259,'3已发行数据0610（明道云数据）'!B:D,3,FALSE) -> 北京 | D259: =VLOOKUP(A259,房源最后还款日!A:B,2,FALSE) -> #N/A | E259: =VLOOKUP(A259,'2更新的资产数据表'!C:G,5,FALSE) -> 23960 | F259: =VLOOKUP(A259,提前还款!B:B,1,FALSE) -> #N/A | G259: =VLOOKUP(A259,信托逾期反馈!A:A,1,FALSE) -> 101133789300 | H259: =VLOOKUP(G259,信托逾期反馈!A:G,7,FALSE) -> 0
A260: 101133792147 | B260: =VLOOKUP(A260,'3已发行数据0610（明道云数据）'!B:N,13,FALSE) -> 单一信托（2号） | C260: =VLOOKUP(A260,'3已发行数据0610（明道云数据）'!B:D,3,FALSE) -> 北京 | D260: =VLOOKUP(A260,房源最后还款日!A:B,2,FALSE) -> 46178 | E260: =VLOOKUP(A260,'2更新的资产数据表'!C:G,5,FALSE) -> 15130 | F260: =VLOOKUP(A260,提前还款!B:B,1,FALSE) -> #N/A | G260: =VLOOKUP(A260,信托逾期反馈!A:A,1,FALSE) -> #N/A
A261: 101133822347 | B261: =VLOOKUP(A261,'3已发行数据0610（明道云数据）'!B:N,13,FALSE) -> 信托3号 | C261: =VLOOKUP(A261,'3已发行数据0610（明道云数据）'!B:D,3,FALSE) -> 北京 | D261: =VLOOKUP(A261,房源最后还款日!A:B,2,FALSE) -> 46185 | E261: =VLOOKUP(A261,'2更新的资产数据表'!C:G,5,FALSE) -> 99979 | F261: =VLOOKUP(A261,提前还款!B:B,1,FALSE) -> #N/A | G261: =VLOOKUP(A261,信托逾期反馈!A:A,1,FALSE) -> #N/A
A262: 101133841636 | B262: =VLOOKUP(A262,'3已发行数据0610（明道云数据）'!B:N,13,FALSE) -> 单一信托（2号） | C262: =VLOOKUP(A262,'3已发行数据0610（明道云数据）'!B:D,3,FALSE) -> 北京 | D262: =VLOOKUP(A262,房源最后还款日!A:B,2,FALSE) -> 46178 | E262: =VLOOKUP(A262,'2更新的资产数据表'!C:G,5,FALSE) -> 24756 | F262: =VLOOKUP(A262,提前还款!B:B,1,FALSE) -> #N/A | G262: =VLOOKUP(A262,信托逾期反馈!A:A,1,FALSE) -> #N/A
A263: 101133931726 | B263: =VLOOKUP(A263,'3已发行数据0610（明道云数据）'!B:N,13,FALSE) -> 信托3号 | C263: =VLOOKUP(A263,'3已发行数据0610（明道云数据）'!B:D,3,FALSE) -> 北京 | D263: =VLOOKUP(A263,房源最后还款日!A:B,2,FALSE) -> 46178 | E263: =VLOOKUP(A263,'2更新的资产数据表'!C:G,5,FALSE) -> 82692.9 | F263: =VLOOKUP(A263,提前还款!B:B,1,FALSE) -> #N/A | G263: =VLOOKUP(A263,信托逾期反馈!A:A,1,FALSE) -> #N/A
A264: 101133932288 | B264: =VLOOKUP(A264,'3已发行数据0610（明道云数据）'!B:N,13,FALSE) -> 单一信托（2号） | C264: =VLOOKUP(A264,'3已发行数据0610（明道云数据）'!B:D,3,FALSE) -> 北京 | D264: =VLOOKUP(A264,房源最后还款日!A:B,2,FALSE) -> 46178 | E264: =VLOOKUP(A264,'2更新的资产数据表'!C:G,5,FALSE) -> 12340 | F264: =VLOOKUP(A264,提前还款!B:B,1,FALSE) -> #N/A | G264: =VLOOKUP(A264,信托逾期反馈!A:A,1,FALSE) -> #N/A
A265: 101133933156 | B265: =VLOOKUP(A265,'3已发行数据0610（明道云数据）'!B:N,13,FALSE) -> 信托3号 | C265: =VLOOKUP(A265,'3已发行数据0610（明道云数据）'!B:D,3,FALSE) -> 北京 | D265: =VLOOKUP(A265,房源最后还款日!A:B,2,FALSE) -> 46164 | E265: =VLOOKUP(A265,'2更新的资产数据表'!C:G,5,FALSE) -> 111599.98 | F265: =VLOOKUP(A265,提前还款!B:B,1,FALSE) -> #N/A | G265: =VLOOKUP(A265,信托逾期反馈!A:A,1,FALSE) -> #N/A
A266: 101133938983 | B266: =VLOOKUP(A266,'3已发行数据0610（明道云数据）'!B:N,13,FALSE) -> 单一信托（2号） | C266: =VLOOKUP(A266,'3已发行数据0610（明道云数据）'!B:D,3,FALSE) -> 北京 | D266: =VLOOKUP(A266,房源最后还款日!A:B,2,FALSE) -> 46178 | E266: =VLOOKUP(A266,'2更新的资产数据表'!C:G,5,FALSE) -> 10873 | F266: =VLOOKUP(A266,提前还款!B:B,1,FALSE) -> #N/A | G266: =VLOOKUP(A266,信托逾期反馈!A:A,1,FALSE) -> #N/A
A267: 101133949419 | B267: =VLOOKUP(A267,'3已发行数据0610（明道云数据）'!B:N,13,FALSE) -> 单一信托（2号） | C267: =VLOOKUP(A267,'3已发行数据0610（明道云数据）'!B:D,3,FALSE) -> 北京 | D267: =VLOOKUP(A267,房源最后还款日!A:B,2,FALSE) -> 46178 | E267: =VLOOKUP(A267,'2更新的资产数据表'!C:G,5,FALSE) -> 19820 | F267: =VLOOKUP(A267,提前还款!B:B,1,FALSE) -> #N/A | G267: =VLOOKUP(A267,信托逾期反馈!A:A,1,FALSE) -> #N/A
A268: 101133959860 | B268: =VLOOKUP(A268,'3已发行数据0610（明道云数据）'!B:N,13,FALSE) -> 信托3号 | C268: =VLOOKUP(A268,'3已发行数据0610（明道云数据）'!B:D,3,FALSE) -> 北京 | D268: =VLOOKUP(A268,房源最后还款日!A:B,2,FALSE) -> 46164 | E268: =VLOOKUP(A268,'2更新的资产数据表'!C:G,5,FALSE) -> 85499.99 | F268: =VLOOKUP(A268,提前还款!B:B,1,FALSE) -> #N/A | G268: =VLOOKUP(A268,信托逾期反馈!A:A,1,FALSE) -> #N/A
A269: 101134012737 | B269: =VLOOKUP(A269,'3已发行数据0610（明道云数据）'!B:N,13,FALSE) -> 信托3号 | C269: =VLOOKUP(A269,'3已发行数据0610（明道云数据）'!B:D,3,FALSE) -> 北京 | D269: =VLOOKUP(A269,房源最后还款日!A:B,2,FALSE) -> 46178 | E269: =VLOOKUP(A269,'2更新的资产数据表'!C:G,5,FALSE) -> 137363.32 | F269: =VLOOKUP(A269,提前还款!B:B,1,FALSE) -> #N/A | G269: =VLOOKUP(A269,信托逾期反馈!A:A,1,FALSE) -> #N/A
A270: 101134022848 | B270: =VLOOKUP(A270,'3已发行数据0610（明道云数据）'!B:N,13,FALSE) -> 单一信托（2号） | C270: =VLOOKUP(A270,'3已发行数据0610（明道云数据）'!B:D,3,FALSE) -> 北京 | D270: =VLOOKUP(A270,房源最后还款日!A:B,2,FALSE) -> 46178 | E270: =VLOOKUP(A270,'2更新的资产数据表'!C:G,5,FALSE) -> 18730 | F270: =VLOOKUP(A270,提前还款!B:B,1,FALSE) -> #N/A | G270: =VLOOKUP(A270,信托逾期反馈!A:A,1,FALSE) -> #N/A
A271: 101134082990 | B271: =VLOOKUP(A271,'3已发行数据0610（明道云数据）'!B:N,13,FALSE) -> 信托3号 | C271: =VLOOKUP(A271,'3已发行数据0610（明道云数据）'!B:D,3,FALSE) -> 北京 | D271: =VLOOKUP(A271,房源最后还款日!A:B,2,FALSE) -> 46171 | E271: =VLOOKUP(A271,'2更新的资产数据表'!C:G,5,FALSE) -> 44783.33 | F271: =VLOOKUP(A271,提前还款!B:B,1,FALSE) -> #N/A | G271: =VLOOKUP(A271,信托逾期反馈!A:A,1,FALSE) -> #N/A
... A278: 101134217969 | B278: =VLOOKUP(A278,'3已发行数据0610（明道云数据）'!B:N,13,FALSE) -> 单一信托,信托3号 | C278: =VLOOKUP(A278,'3已发行数据0610（明道云数据）'!B:D,3,FALSE) -> 北京 | D278: =VLOOKUP(A278,房源最后还款日!A:B,2,FALSE) -> 46157 | E278: =VLOOKUP(A278,'2更新的资产数据表'!C:G,5,FALSE) -> 18770 | F278: =VLOOKUP(A278,提前还款!B:B,1,FALSE) -> #N/A | G278: =VLOOKUP(A278,信托逾期反馈!A:A,1,FALSE) -> #N/A
A279: 101134229290 | B279: =VLOOKUP(A279,'3已发行数据0610（明道云数据）'!B:N,13,FALSE) -> 单一信托（2号） | C279: =VLOOKUP(A279,'3已发行数据0610（明道云数据）'!B:D,3,FALSE) -> 北京 | D279: =VLOOKUP(A279,房源最后还款日!A:B,2,FALSE) -> #N/A | E279: =VLOOKUP(A279,'2更新的资产数据表'!C:G,5,FALSE) -> 36617 | F279: =VLOOKUP(A279,提前还款!B:B,1,FALSE) -> #N/A | G279: =VLOOKUP(A279,信托逾期反馈!A:A,1,FALSE) -> 101134229290 | H279: =VLOOKUP(G279,信托逾期反馈!A:G,7,FALSE) -> 0
A280: 101134238969 | B280: =VLOOKUP(A280,'3已发行数据0610（明道云数据）'!B:N,13,FALSE) -> 信托3号 | C280: =VLOOKUP(A280,'3已发行数据0610（明道云数据）'!B:D,3,FALSE) -> 北京 | D280: =VLOOKUP(A280,房源最后还款日!A:B,2,FALSE) -> 46164 | E280: =VLOOKUP(A280,'2更新的资产数据表'!C:G,5,FALSE) -> 24560 | F280: =VLOOKUP(A280,提前还款!B:B,1,FALSE) -> #N/A | G280: =VLOOKUP(A280,信托逾期反馈!A:A,1,FALSE) -> #N/A
A281: 101134387614 | B281: =VLOOKUP(A281,'3已发行数据0610（明道云数据）'!B:N,13,FALSE) -> 单一信托（2号） | C281: =VLOOKUP(A281,'3已发行数据0610（明道云数据）'!B:D,3,FALSE) -> 北京 | D281: =VLOOKUP(A281,房源最后还款日!A:B,2,FALSE) -> 46178 | E281: =VLOOKUP(A281,'2更新的资产数据表'!C:G,5,FALSE) -> 32150 | F281: =VLOOKUP(A281,提前还款!B:B,1,FALSE) -> #N/A | G281: =VLOOKUP(A281,信托逾期反馈!A:A,1,FALSE) -> #N/A
A282: 101134405206 | B282: =VLOOKUP(A282,'3已发行数据0610（明道云数据）'!B:N,13,FALSE) -> 单一信托（2号） | C282: =VLOOKUP(A282,'3已发行数据0610（明道云数据）'!B:D,3,FALSE) -> 北京 | D282: =VLOOKUP(A282,房源最后还款日!A:B,2,FALSE) -> 46178 | E282: =VLOOKUP(A282,'2更新的资产数据表'!C:G,5,FALSE) -> 15620 | F282: =VLOOKUP(A282,提前还款!B:B,1,FALSE) -> #N/A | G282: =VLOOKUP(A282,信托逾期反馈!A:A,1,FALSE) -> #N/A
A283: 101134445166 | B283: =VLOOKUP(A283,'3已发行数据0610（明道云数据）'!B:N,13,FALSE) -> 信托3号 | C283: =VLOOKUP(A283,'3已发行数据0610（明道云数据）'!B:D,3,FALSE) -> 北京 | D283: =VLOOKUP(A283,房源最后还款日!A:B,2,FALSE) -> 46178 | E283: =VLOOKUP(A283,'2更新的资产数据表'!C:G,5,FALSE) -> 120296.89 | F283: =VLOOKUP(A283,提前还款!B:B,1,FALSE) -> #N/A | G283: =VLOOKUP(A283,信托逾期反馈!A:A,1,FALSE) -> #N/A
A284: 101134472187 | B284: =VLOOKUP(A284,'3已发行数据0610（明道云数据）'!B:N,13,FALSE) -> 单一信托,信托3号 | C284: =VLOOKUP(A284,'3已发行数据0610（明道云数据）'!B:D,3,FALSE) -> 北京 | D284: =VLOOKUP(A284,房源最后还款日!A:B,2,FALSE) -> 46171 | E284: =VLOOKUP(A284,'2更新的资产数据表'!C:G,5,FALSE) -> 23112.33 | F284: =VLOOKUP(A284,提前还款!B:B,1,FALSE) -> #N/A | G284: =VLOOKUP(A284,信托逾期反馈!A:A,1,FALSE) -> #N/A
A285: 101134529507 | B285: =VLOOKUP(A285,'3已发行数据0610（明道云数据）'!B:N,13,FALSE) -> 单一信托（2号） | C285: =VLOOKUP(A285,'3已发行数据0610（明道云数据）'!B:D,3,FALSE) -> 北京 | D285: =VLOOKUP(A285,房源最后还款日!A:B,2,FALSE) -> 46185 | E285: =VLOOKUP(A285,'2更新的资产数据表'!C:G,5,FALSE) -> 20728 | F285: =VLOOKUP(A285,提前还款!B:B,1,FALSE) -> #N/A | G285: =VLOOKUP(A285,信托逾期反馈!A:A,1,FALSE) -> #N/A
A286: 101134641780 | B286: =VLOOKUP(A286,'3已发行数据0610（明道云数据）'!B:N,13,FALSE) -> 单一信托（2号） | C286: =VLOOKUP(A286,'3已发行数据0610（明道云数据）'!B:D,3,FALSE) -> 北京 | D286: =VLOOKUP(A286,房源最后还款日!A:B,2,FALSE) -> 46178 | E286: =VLOOKUP(A286,'2更新的资产数据表'!C:G,5,FALSE) -> 15948 | F286: =VLOOKUP(A286,提前还款!B:B,1,FALSE) -> #N/A | G286: =VLOOKUP(A286,信托逾期反馈!A:A,1,FALSE) -> #N/A
A287: 101134681653 | B287: =VLOOKUP(A287,'3已发行数据0610（明道云数据）'!B:N,13,FALSE) -> 单一信托（2号） | C287: =VLOOKUP(A287,'3已发行数据0610（明道云数据）'!B:D,3,FALSE) -> 北京 | D287: =VLOOKUP(A287,房源最后还款日!A:B,2,FALSE) -> 46178 | E287: =VLOOKUP(A287,'2更新的资产数据表'!C:G,5,FALSE) -> 18290 | F287: =VLOOKUP(A287,提前还款!B:B,1,FALSE) -> #N/A | G287: =VLOOKUP(A287,信托逾期反馈!A:A,1,FALSE) -> #N/A
A288: 101134722478 | B288: =VLOOKUP(A288,'3已发行数据0610（明道云数据）'!B:N,13,FALSE) -> 单一信托（2号） | C288: =VLOOKUP(A288,'3已发行数据0610（明道云数据）'!B:D,3,FALSE) -> 北京 | D288: =VLOOKUP(A288,房源最后还款日!A:B,2,FALSE) -> 46178 | E288: =VLOOKUP(A288,'2更新的资产数据表'!C:G,5,FALSE) -> 44900 | F288: =VLOOKUP(A288,提前还款!B:B,1,FALSE) -> #N/A | G288: =VLOOKUP(A288,信托逾期反馈!A:A,1,FALSE) -> #N/A
A289: 101134728612 | B289: =VLOOKUP(A289,'3已发行数据0610（明道云数据）'!B:N,13,FALSE) -> 单一信托（2号） | C289: =VLOOKUP(A289,'3已发行数据0610（明道云数据）'!B:D,3,FALSE) -> 北京 | D289: =VLOOKUP(A289,房源最后还款日!A:B,2,FALSE) -> 46185 | E289: =VLOOKUP(A289,'2更新的资产数据表'!C:G,5,FALSE) -> 31030 | F289: =VLOOKUP(A289,提前还款!B:B,1,FALSE) -> #N/A | G289: =VLOOKUP(A289,信托逾期反馈!A:A,1,FALSE) -> #N/A
A290: 101134835323 | B290: =VLOOKUP(A290,'3已发行数据0610（明道云数据）'!B:N,13,FALSE) -> 单一信托（2号） | C290: =VLOOKUP(A290,'3已发行数据0610（明道云数据）'!B:D,3,FALSE) -> 北京 | D290: =VLOOKUP(A290,房源最后还款日!A:B,2,FALSE) -> 46185 | E290: =VLOOKUP(A290,'2更新的资产数据表'!C:G,5,FALSE) -> 22023 | F290: =VLOOKUP(A290,提前还款!B:B,1,FALSE) -> #N/A | G290: =VLOOKUP(A290,信托逾期反馈!A:A,1,FALSE) -> #N/A
...

Sheet 信托逾期反馈
A1: 房源编号 | B1: 最新一次付款日 | C1: 所属城市 | D1: 发行批次 | E1: 未回款明细 | F1: 原因 | G1: 解决方式
A2: 107112757529 | B2: =VLOOKUP(A2,逾期自检0618!A:D,2,FALSE) -> 信托1号 | C2: =VLOOKUP(A2,'3已发行数据0610（明道云数据）'!B:N,3,FALSE) -> 上海 | D2: =VLOOKUP(A2,'3已发行数据0610（明道云数据）'!B:N,13,FALSE) -> 信托1号 | E2: 0403~0605(10周) | F2: 解约重签，新房源107114866922， | G2: 待手动结算付款
A3: 107112235776 | B3: =VLOOKUP(A3,逾期自检0618!A:D,2,FALSE) -> 信托1号 | C3: =VLOOKUP(A3,'3已发行数据0610（明道云数据）'!B:N,3,FALSE) -> 上海 | D3: =VLOOKUP(A3,'3已发行数据0610（明道云数据）'!B:N,13,FALSE) -> 信托1号 | E3: 0403~0605(10周) | F3: 解约重签，新房源107114962154 | G3: 付款异常，待系统问题解决过后，手动结算付款（冠唯解约）
A4: 107112699615 | B4: =VLOOKUP(A4,逾期自检0618!A:D,2,FALSE) -> 信托1号 | C4: =VLOOKUP(A4,'3已发行数据0610（明道云数据）'!B:N,3,FALSE) -> 上海 | D4: =VLOOKUP(A4,'3已发行数据0610（明道云数据）'!B:N,13,FALSE) -> 信托1号 | E4: 0403~0605(10周) | F4: 解约账单未支付 | G4: 逾期，需要置换
A5: 107112622529 | B5: =VLOOKUP(A5,逾期自检0618!A:D,2,FALSE) -> 信托1号 | C5: =VLOOKUP(A5,'3已发行数据0610（明道云数据）'!B:N,3,FALSE) -> 上海 | D5: =VLOOKUP(A5,'3已发行数据0610（明道云数据）'!B:N,13,FALSE) -> 信托1号 | E5: 0403~0605(10周) | F5: 已现金支付 | G5: 待手动结算付款
A6: 107112700446 | B6: =VLOOKUP(A6,逾期自检0618!A:D,2,FALSE) -> 信托1号 | C6: =VLOOKUP(A6,'3已发行数据0610（明道云数据）'!B:N,3,FALSE) -> 上海 | D6: =VLOOKUP(A6,'3已发行数据0610（明道云数据）'!B:N,13,FALSE) -> 信托1号 | E6: 0403~0605(10周) | F6: 解约账单已付 | G6: 待手动结算付款
A7: 107112901979 | B7: =VLOOKUP(A7,逾期自检0618!A:D,2,FALSE) -> 信托1号 | C7: =VLOOKUP(A7,'3已发行数据0610（明道云数据）'!B:N,3,FALSE) -> 上海 | D7: =VLOOKUP(A7,'3已发行数据0610（明道云数据）'!B:N,13,FALSE) -> 信托1号 | E7: 0403、0417~0605(8周) | F7: 空置，6.6已代扣 | G7: 4月10日已付款，需要确认信托收款状态；6月6日已付款，本周结算付款
A8: 107112617499 | B8: =VLOOKUP(A8,逾期自检0618!A:D,2,FALSE) -> 信托1号 | C8: =VLOOKUP(A8,'3已发行数据0610（明道云数据）'!B:N,3,FALSE) -> 上海 | D8: =VLOOKUP(A8,'3已发行数据0610（明道云数据）'!B:N,13,FALSE) -> 信托1号 | E8: 0403~0417(3周)、0430~0605(6周) | F8: 正常扣款中 | G8: 4月24日有付款，需要确认信托收款状态；5月付款异常，待系统问题解决过后，手动结算付款
A9: 107112318319 | B9: =VLOOKUP(A9,逾期自检0618!A:D,2,FALSE) -> 信托1号 | C9: =VLOOKUP(A9,'3已发行数据0610（明道云数据）'!B:N,3,FALSE) -> 上海 | D9: =VLOOKUP(A9,'3已发行数据0610（明道云数据）'!B:N,13,FALSE) -> 信托1号 | E9: 0410~0424(3周)、0508~0605(5周) | F9: 正常扣款中 | G9: 5月1日有付款，需要确认信托收款状态；5月付款异常，待系统问题解决过后，手动结算付款
A10: 107112191225 | B10: =VLOOKUP(A10,逾期自检0618!A:D,2,FALSE) -> 信托1号 | C10: =VLOOKUP(A10,'3已发行数据0610（明道云数据）'!B:N,3,FALSE) -> 上海 | D10: =VLOOKUP(A10,'3已发行数据0610（明道云数据）'!B:N,13,FALSE) -> 信托1号 | E10: 0403~0424(4周)、0508~0605(5周) | F10: 待出租 | G10: 5月1日有付款，需要确认信托收款状态；出租中，出租后正常付款结算
A11: 107112290433 | B11: =VLOOKUP(A11,逾期自检0618!A:D,2,FALSE) -> 信托1号 | C11: =VLOOKUP(A11,'3已发行数据0610（明道云数据）'!B:N,3,FALSE) -> 上海 | D11: =VLOOKUP(A11,'3已发行数据0610（明道云数据）'!B:N,13,FALSE) -> 信托1号 | E11: 0410~0424(3周)、0508~0605(5周) | F11: 正常扣款中 | G11: 5月1日有付款，需要确认信托收款状态；5月付款异常，待系统问题解决过后，手动结算付款
A12: 101130798182 | B12: =VLOOKUP(A12,逾期自检0618!A:D,2,FALSE) -> 信托1号 | C12: =VLOOKUP(A12,'3已发行数据0610（明道云数据）'!B:N,3,FALSE) -> 北京 | D12: =VLOOKUP(A12,'3已发行数据0610（明道云数据）'!B:N,13,FALSE) -> 信托1号 | E12: 0403~0605(10周) | F12: 解约重签，新房源号101135047520 | G12: 待手动结算付款
A13: 101130093956 | B13: =VLOOKUP(A13,逾期自检0618!A:D,2,FALSE) -> 信托1号 | C13: =VLOOKUP(A13,'3已发行数据0610（明道云数据）'!B:N,3,FALSE) -> 北京 | D13: =VLOOKUP(A13,'3已发行数据0610（明道云数据）'!B:N,13,FALSE) -> 信托1号 | E13: 0403~0424(4周)、0508~0605(5周) | F13: 解约后支付了账单 | G13: 待手动结算付款
... A29: 101133578658 | B29: =VLOOKUP(A29,逾期自检0618!A:D,2,FALSE) -> 信托3号 | C29: =VLOOKUP(A29,'3已发行数据0610（明道云数据）'!B:N,3,FALSE) -> 北京 | D29: =VLOOKUP(A29,'3已发行数据0610（明道云数据）'!B:N,13,FALSE) -> 信托3号 | E29: 0508~0605(5周) | F29: 正常代扣 | G29: 待手动结算付款
A30: 107112427808 | B30: 107112427808-单一001 | C30: 上海 | D30: 176000 | E30: 0 | F30: 176000
A31: 101133789300 | B31: 101133789300-单一001 | C31: 北京 | D31: 23960 | E31: 0 | F31: 23960
A32: 101132799241 | B32: 101132799241-单一001 | C32: 北京 | D32: 22393 | E32: 0 | F32: 22393
A33: 101134229290 | B33: 101134229290-单一001 | C33: 北京 | D33: 36617 | E33: 0 | F33: 36617
A34: 101132506745 | B34: 101132506745-单一001 | C34: 北京 | D34: 23074 | E34: 0 | F34: 23074
A35: 101127311840 | B35: 101127311840-单一001 | C35: 北京 | D35: 49999.84 | E35: 0 | F35: 49999.84 | G35: 5月29日已经有回款
A36: 101127524235 | B36: 101127524235-单一001 | C36: 北京 | D36: 64845 | E36: 0 | F36: 64845 | G36: 5月22日已经有回款
A37: 107112396048 | B37: 107112396048-单一001 | C37: 上海 | D37: 184540 | E37: 0 | F37: 184540 | G37: 6月5日已经有回款

Sheet 结算系统待清理
A1: 预计代扣周期-最初 | B1: 房源编码 | C1: 房源地址 | D1: 所属城市 | E1: 品牌 | F1: 签约日期 | G1: 实际成交价（应收账款合同金额） | H1: 代扣金额 | I1: 装修付款形式 | J1: 业主付款金额 | K1: 施工方名称 | L1: 入池批次 | M1: 信托计划期数 | N1: 当前信托计划（已发行）
B2: 107112825000 | C2: 上海市闵行区浦申路633弄19号501 | D2: 上海 | E2: 山念 | F2: 45806 | G2: 180000 | I2: 业主付款 | J2: 180000 | K2: 上海庆苑建筑装饰集团有限公司 | L2: 第三批预备池 | M2: 第三批预备池
B3: 107112665590 | C3: 上海静安北市场小区国庆路3弄02甲单元0703 | D3: 上海 | E3: 山念 | I3: 租金代扣 | K3: 上海美速家建筑装饰有限公司
B4: 101130069266 | C4: 西城区新街口外大街甲8号21-1门8号 | D4: 北京 | E4: 焕新租 | F4: 45791 | G4: 90000 | H4: 90000 | I4: 租金代扣 | K4: 北京省心装工程管理有限公司 | L4: 第三批预备池 | M4: 第三批预备池
B5: 107113121321 | C5: 上海市浦东新区龙居路150弄23号304室 | D5: 上海 | E5: 山念 | F5: 45815 | G5: 85000 | H5: 0 | I5: 业主付款 | J5: 85000 | K5: 上海沪怡佳装饰设计工程有限公司 | L5: 第三批预备池 | M5: 第三批预备池
B6: 107112370763 | C6: 上海市闵行区保利联发光合臻园25号1602 | D6: 上海 | E6: 山念 | F6: 45739 | G6: 17000 | I6: 业主付款 | J6: 17000 | K6: 南京和艺优装饰工程有限公司 | L6: 第三批预备池 | M6: 第三批预备池
B7: 107112379310 | C7: 上海市浦东新区东育路1665弄5号701室 | D7: 上海 | E7: 山念 | F7: 45738 | G7: 114000 | I7: 业主付款 | J7: 114000 | K7: 上海庆苑建筑装饰集团有限公司 | L7: 第三批预备池 | M7: 第三批预备池
B8: 107112379019 | C8: 上海杨浦民星二村民星二村04号楼民星二村04单元0504 | D8: 上海 | E8: 山念 | F8: 45738 | G8: 80000 | H8: 0 | I8: 业主付款 | J8: 80000 | K8: 上海美速家建筑装饰有限公司 | L8: 第三批预备池 | M8: 第三批预备池
B9: 107112336027 | C9: 上海市浦东新区257弄15号单元1402室(东区) | D9: 上海 | E9: 怡穗 | F9: 45736 | G9: 27380 | I9: 业主付款 | J9: 0 | K9: 上海欣暄装饰工程设计有限公司 | L9: 第三批预备池 | M9: 第三批预备池
B10: 107111994631 | C10: 上海市闵行区绿莲路99弄6号401 | D10: 上海 | E10: 山念 | F10: 45731 | G10: 14998 | I10: 业主付款 | J10: 14998 | K10: 南京和艺优装饰工程有限公司 | L10: 第三批预备池 | M10: 第三批预备池
B11: 107111839361 | C11: 上海市徐汇区马赛花园80弄2号902 | D11: 上海 | E11: 山念 | F11: 45731 | G11: 8458 | I11: 业主付款 | J11: 8458 | K11: 南京和艺优装饰工程有限公司 | L11: 第三批预备池 | M11: 第三批预备池
B12: 107112260445 | C12: 上海市长宁区中园小区8号501 | D12: 上海 | E12: 山念 | F12: 45728 | G12: 75000 | I12: 业主付款 | J12: 75000 | K12: 上海沪慧荣建筑装饰有限公司 | L12: 第三批预备池 | M12: 第三批预备池
B13: 107112224014 | C13: 上海市徐汇区漕溪一村8号104 | D13: 上海 | E13: 山念 | F13: 45727 | G13: 5025 | I13: 业主付款 | J13: 5025 | K13: 南京和艺优装饰工程有限公司 | L13: 第三批预备池 | M13: 第三批预备池
B14: 107112814492 | C14: 上海市闵行区吴中路830弄5号501 | D14: 上海 | E14: 山念 | F14: 45846 | G14: 11506 | I14: 业主付款 | J14: 11506 | K14: 南京和艺优装饰工程有限公司 | L14: 第三批预备池 | M14: 第三批预备池
B15: 107112205779 | C15: 上海市浦东新区海洋一路777弄(科澜观邸)8号1402室 | D15: 上海 | E15: 山念 | F15: 45721 | G15: 27761 | H15: 0 | I15: 业主付款 | J15: 27761 | K15: 上海庆苑建筑装饰集团有限公司 | L15: 第三批预备池 | M15: 第三批预备池
B16: 107112157342 | C16: 上海市长宁区新泾三村 31 号 601 | D16: 上海 | E16: 山念 | F16: 45720 | G16: 80888 | I16: 业主付款 | J16: 80888 | K16: 上海沪慧荣建筑装饰有限公司 | L16: 第三批预备池 | M16: 第三批预备池
B17: 101129973542 | C17: 海淀区曙光花园望山园3号楼306 | D17: 北京 | E17: 怡穗 | F17: 45698 | G17: 154153 | I17: 业主付款 | J17: 154153 | K17: 中筑宏图（北京）建设工程有限公司 | L17: 第三批预备池 | M17: 第三批预备池
B18: 11111 | C18: 北京市西城区后桃园胡同10号楼1层3门311室 | D18: 北京 | E18: 怡穗 | I18: 业主付款 | J18: 92000 | K18: 天津熙市建筑工程有限公司
B19: 107111564790 | C19: 上海市浦东新区南泉路1111弄15号601室 | D19: 上海 | E19: 怡穗 | F19: 45640 | G19: 81000 | I19: 业主付款 | J19: 81000 | K19: 上海欣暄装饰工程设计有限公司 | L19: 第三批预备池 | M19: 第三批预备池
B20: 107112317233 | C20: 上海市浦东新区梅园七街坊乳山路237弄6号401室 | D20: 上海 | E20: 山念 | F20: 45775 | G20: 10870 | H20: 0 | I20: 业主付款 | J20: 10870 | K20: 上海庆苑建筑装饰集团有限公司 | L20: 第三批预备池 | M20: 第三批预备池
B21: 107112904680 | C21: 上海市闵行区天安一号20号902 | D21: 上海 | E21: 怡穗 | F21: 45794 | G21: 33620 | H21: 0 | I21: 业主付款 | J21: 33620 | K21: 南京和艺优装饰工程有限公司 | L21: 第三批预备池 | M21: 第三批预备池
B22: 101129559202 | C22: 北京市海淀区交大东路41号院1号楼1164 | D22: 北京 | E22: 焕新租 | F22: 45791 | G22: 140000 | H22: 0 | I22: 租金代扣 | J22: 0 | K22: 北京省心装工程管理有限公司
A23: 25 | B23: 107114104632 | C23: 上海杨浦控江二村107弄小区27号楼27单元0105 | D23: 上海 | F23: 45925 | G23: 77397 | H23: 77397 | I23: 租金代扣 | K23: 上海筑家家建筑装饰有限公司 | L23: 第四批预备池 | M23: 第四批预备池
A24: 25 | B24: 107114226545 | C24: 上海市虹口区车站南路407弄1号302室 | D24: 上海 | E24: 悦居 | F24: 45944 | G24: 105000 | H24: 105000 | I24: 租金代扣 | K24: 上海筑家家建筑装饰有限公司 | L24: 第四批预备池 | M24: 第四批预备池
A25: 25 | B25: 107114191687 | C25: 上海杨浦政立路580弄2号403室 | D25: 上海 | E25: 山念 | F25: 45943 | G25: 98916 | H25: 98916 | I25: 租金代扣 | K25: 上海筑家家建筑装饰有限公司 | L25: 第四批预备池 | M25: 第四批预备池
A26: 25 | B26: 107114187663 | C26: 上海杨浦开鲁五村8号501室 | D26: 上海 | E26: 悦居 | F26: 45941 | G26: 100724 | H26: 100724 | I26: 租金代扣 | K26: 上海筑家家建筑装饰有限公司 | L26: 第四批预备池 | M26: 第四批预备池
A27: 9 | B27: 101134624801 | C27: 北京市朝阳区芳园里13号楼5门73 | D27: 北京 | E27: 舒里简逸 | F27: 45997 | G27: 26000 | H27: 26000 | I27: 租金代扣 | K27: 北京米屋科技有限公司北京第一分公司 | L27: 第四批预备池 | M27: 第四批预备池
A28: 25 | B28: 107114386253 | C28: 上海杨浦延吉五村延吉五村51号楼51单元0103 | D28: 上海 | E28: 悦居 | F28: 45965 | G28: 109000 | H28: 109000 | I28: 租金代扣 | K28: 上海筑家家建筑装饰有限公司 | L28: 第四批预备池 | M28: 第四批预备池
B29: 101129360184 | C29: 北京西城佟麟阁路62号院10号楼12层2门1204 | D29: 北京 | E29: 焕新租 | F29: 45735 | G29: 73000 | H29: 0 | I29: 租金代扣 | J29: 0 | K29: 北京省心装工程管理有限公司 | L29: 第三批预备池 | M29: 第三批预备池
A30: 11 | B30: 107114287129 | C30: 上海市浦东新区棠梨路66弄13号502 | D30: 上海 | E30: 山念 | F30: 45956 | G30: 20000 | H30: 20000 | I30: 租金代扣 | K30: 上海弘曳建筑装饰工程有限公司 | L30: 第四批预备池 | M30: 第四批预备池
A31: 29 | B31: 107114064750 | C31: 上海市虹口区红馥里小区三门 路 1177 弄 25 号1702 室 | D31: 上海 | E31: 山念 | F31: 45920 | G31: 106000 | H31: 106000 | I31: 租金代扣 | K31: 上海千盛邦建筑装饰有限公司 | L31: 第四批预备池 | M31: 第四批预备池
A32: 24 | B32: 107113947624 | C32: 上海市静安区康定路1588弄4号702室 | D32: 上海 | E32: 山念 | F32: 45921 | G32: 73000 | H32: 73000 | I32: 租金代扣 | K32: 住与家（上海）装饰设计有限公司 | L32: 第四批预备池 | M32: 第四批预备池
A33: 26 | B33: 107114054074 | C33: 上海市浦东新区东三里桥路170弄3号503室 | D33: 上海 | E33: 悦居 | F33: 45929 | G33: 90000 | H33: 90000 | I33: 租金代扣 | K33: 上海弘曳建筑装饰工程有限公司 | L33: 第四批预备池 | M33: 第四批预备池
A34: 25 | B34: 107114115032 | C34: 上海市徐汇区嘉善路140弄17号楼17单元二层前间 | D34: 上海 | E34: 悦居 | F34: 45940 | G34: 78290 | H34: 78290 | I34: 租金代扣 | K34: 住与家（上海）装饰设计有限公司 | L34: 第四批预备池 | M34: 第四批预备池
A35: 25 | B35: 107114154324 | C35: 上海杨浦上理小区304号楼304单元0403 | D35: 上海 | E35: 悦居 | F35: 45934 | G35: 110005 | H35: 110005 | I35: 租金代扣 | K35: 上海筑家家建筑装饰有限公司 | L35: 第四批预备池 | M35: 第四批预备池
A36: 25 | B36: 107114158317 | C36: 上海浦东依水园一期林展路411弄04号楼04单元2302 | D36: 上海 | E36: 山念 | F36: 45934 | G36: 102000 | H36: 102000 | I36: 租金代扣 | K36: 北京中宇华晟建筑工程有限公司 | L36: 第四批预备池 | M36: 第四批预备池
A37: 25 | B37: 107114138556 | C37: 上海市徐汇区钦州路111弄22号402室 | D37: 上海 | E37: 山念 | F37: 45935 | G37: 83000 | H37: 83000 | I37: 租金代扣 | K37: 南京弘德装饰工程有限公司 | L37: 第四批预备池 | M37: 第四批预备池
A38: 24 | B38: 107114153955 | C38: 上海杨浦市光四村119号502室 | D38: 上海 | E38: 悦居 | F38: 45937 | G38: 82600 | H38: 82600 | I38: 租金代扣 | K38: 上海筑家家建筑装饰有限公司 | L38: 第四批预备池 | M38: 第四批预备池
A39: 26 | B39: 107114083017 | C39: 上海宝山宝景苑通南路55弄11号楼通南路11单元0102 | D39: 上海 | E39: 山念 | F39: 45938 | G39: 128000 | H39: 128000 | I39: 租金代扣 | K39: 上海千盛邦建筑装饰有限公司 | L39: 第四批预备池 | M39: 第四批预备池
A40: 26 | B40: 107114136520 | C40: 上海市浦东新区崂山西路51号404 室 | D40: 上海 | E40: 悦居 | F40: 45938 | G40: 82000 | H40: 82000 | I40: 租金代扣 | K40: 上海弘曳建筑装饰工程有限公司 | L40: 第四批预备池 | M40: 第四批预备池
A41: 24 | B41: 107114224457 | C41: 上海杨浦榆林路610号单栋单栋0202 | D41: 上海 | E41: 悦居 | F41: 45941 | G41: 81000 | H41: 81000 | I41: 租金代扣 | K41: 上海筑家家建筑装饰有限公司 | L41: 第四批预备池 | M41: 第四批预备池
A42: 25 | B42: 107114233550 | C42: 上海市徐汇区襄北大楼丙楼丙楼单元0703室 | D42: 上海 | E42: 悦居 | F42: 45945 | G42: 94951 | H42: 94951 | I42: 租金代扣 | J42: 0 | K42: 住与家（上海）装饰设计有限公司 | L42: 第四批预备池 | M42: 第四批预备池
A43: 27 | B43: 107114230272 | C43: 上海市宝山区大华路901弄3号502 | D43: 上海 | E43: 悦居 | F43: 45950 | G43: 93000 | H43: 93000 | I43: 租金代扣 | K43: 上海千盛邦建筑装饰有限公司 | L43: 第四批预备池 | M43: 第四批预备池
A44: 26 | B44: 107114285268 | C44: 上海市杨浦区殷行路571弄22号602室 | D44: 上海 | E44: 悦居 | F44: 45951 | G44: 85023 | H44: 85023 | I44: 租金代扣 | K44: 上海筑家家建筑装饰有限公司 | L44: 第四批预备池 | M44: 第四批预备池
A45: 25 | B45: 107114314622 | C45: 上海市黄浦区宁波路120弄20号203 | D45: 上海 | E45: 山念 | F45: 45955 | G45: 87166 | H45: 87166 | I45: 租金代扣 | K45: 住与家（上海）装饰设计有限公司 | L45: 第四批预备池 | M45: 第四批预备池
A46: 26 | B46: 107114281789 | C46: 上海嘉定区丰庄北路82弄33号601室 | D46: 上海 | E46: 悦居 | F46: 45961 | G46: 82783 | H46: 82783 | I46: 租金代扣 | K46: 上海优匠优装饰工程有限公司 | L46: 第四批预备池 | M46: 第四批预备池
A47: 27 | B47: 107114375637 | C47: 上海市浦东新区新场镇汇豪路73弄2号402室 | D47: 上海 | E47: 山念 | F47: 45964 | G47: 58501 | H47: 58501 | I47: 租金代扣 | K47: 上海弘曳建筑装饰工程有限公司 | L47: 第四批预备池 | M47: 第四批预备池
A48: 27 | B48: 107114406160 | C48: 上海市静安区芷江西路26弄2号202 | D48: 上海 | E48: 悦居 | F48: 45968 | G48: 100000 | H48: 100000 | I48: 租金代扣 | K48: 上海筑家家建筑装饰有限公司 | L48: 第四批预备池 | M48: 第四批预备池
A49: 14 | B49: 101134080064 | C49: 北京市海淀区海淀南路2号楼8门203 | D49: 北京 | E49: 焕新租 | F49: 45966 | G49: 100000 | H49: 100000 | I49: 租金代扣 | K49: 北京优尔装饰工程有限公司 | L49: 第四批预备池 | M49: 第四批预备池
A50: 26 | B50: 107114237344 | C50: 上海市杨浦区延吉二村33单元504-505 | D50: 上海 | E50: 悦居 | F50: 45945 | G50: 104929 | H50: 104929 | I50: 租金代扣 | K50: 上海筑家家建筑装饰有限公司 | L50: 第四批预备池 | M50: 第四批预备池
A51: 29 | B51: 107114340226 | C51: 上海市长宁区平塘路700弄7号304 | D51: 上海 | E51: 悦居 | F51: 45970 | G51: 105000 | H51: 105000 | I51: 租金代扣 | K51: 安徽中瑾辰建设工程有限公司 | L51: 第四批预备池 | M51: 第四批预备池
A52: 28 | B52: 107114227767 | C52: 上海市长宁区虹古路377弄30支弄3号504室 | D52: 上海 | E52: 悦居 | F52: 45948 | G52: 79162 | H52: 79162 | I52: 租金代扣 | K52: 安徽中瑾辰建设工程有限公司 | L52: 第四批预备池 | M52: 第四批预备池
A53: 28 | B53: 107114120450 | C53: 上海市长宁区福泉路495弄86号501室 | D53: 上海 | E53: 悦居 | F53: 45947 | G53: 96000 | H53: 96000 | I53: 租金代扣 | K53: 安徽中瑾辰建设工程有限公司 | L53: 第四批预备池 | M53: 第四批预备池
A54: 29 | B54: 107114509194 | C54: 上海市黄浦区淡水路266弄8号301室 | D54: 上海 | E54: 山念 | F54: 45982 | G54: 86000 | H54: 86000 | I54: 租金代扣 | K54: 住与家（上海）装饰设计有限公司 | L54: 第四批预备池 | M54: 第四批预备池
B55: 107114215223 | C55: 上海市青浦区中核锦悦府二期11号1单元302室 | D55: 上海 | E55: 山念 | F55: 45943 | G55: 31316 | I55: 租金代扣 | K55: 安徽中瑾辰建设工程有限公司 | L55: 第四批预备池 | M55: 第四批预备池
B56: 107113391692 | C56: 上海市浦东新区福山路100弄5号604室 | D56: 上海 | E56: 悦居 | F56: 45977 | G56: 92910 | I56: 租金代扣 | K56: 上海弘曳建筑装饰工程有限公司 | L56: 第三批预备池 | M56: 第三批预备池
A57: 28 | B57: 107114437516 | C57: 上海市南苏州路1393弄1号404室 | D57: 上海 | E57: 悦居 | F57: 45972 | G57: 78000 | H57: 78000 | I57: 租金代扣 | K57: 住与家（上海）装饰设计有限公司 | L57: 第四批预备池 | M57: 第四批预备池
A58: 29 | B58: 107114365086 | C58: 上海市浦东新区浦城路580弄2号202室 | D58: 上海 | E58: 悦居 | F58: 45971 | G58: 113975 | H58: 113975 | I58: 租金代扣 | K58: 上海弘曳建筑装饰工程有限公司 | L58: 第四批预备池 | M58: 第四批预备池
A59: 28 | B59: 107114392467 | C59: 上海市黄浦区蒙自西路72弄10号305室 | D59: 上海 | E59: 悦居 | F59: 45966 | G59: 72765 | H59: 72765 | I59: 租金代扣 | K59: 住与家（上海）装饰设计有限公司 | L59: 第四批预备池 | M59: 第四批预备池
A60: 0 | B60: 107114368047 | C60: 上海市虹口区汶水东路510弄42号502室 | D60: 上海 | E60: 悦居 | F60: 45962 | G60: 116704 | H60: 2080 | I60: 租金代扣 | K60: 上海筑家家建筑装饰有限公司
A61: 28 | B61: 107114366047 | C61: 上海市静安区谈家桥路151弄3号1703室 | D61: 上海 | E61: 悦居 | F61: 45962 | G61: 71635 | H61: 71635 | I61: 租金代扣 | K61: 上海筑家家建筑装饰有限公司 | L61: 第四批预备池 | M61: 第四批预备池
B62: 107114327806 | C62: 上海市黄浦区丽园路842弄北蒙三小区26号楼504室 | D62: 上海 | E62: 悦居 | F62: 45961 | G62: 75000 | I62: 租金代扣 | K62: 住与家（上海）装饰设计有限公司 | L62: 第三批预备池 | M62: 第三批预备池
A63: 14 | B63: 107114271678 | C63: 上海市浦东新区张杨路 158 号 1418(N)室 | D63: 上海 | E63: 山念 | F63: 45960 | G63: 75381 | H63: 75380 | I63: 租金代扣 | K63: 上海弘曳建筑装饰工程有限公司 | L63: 第四批预备池 | M63: 第四批预备池
A64: 14 | B64: 107114272050 | C64: 上海市浦东新区张杨路 158 号 1417(N)室 | D64: 上海 | E64: 山念 | F64: 45960 | G64: 75381 | H64: 75380 | I64: 租金代扣 | K64: 上海弘曳建筑装饰工程有限公司 | L64: 第四批预备池 | M64: 第四批预备池
B65: 107113971727 | C65: 上海市浦东新区长岛路1560弄7号305室 | D65: 上海 | E65: 悦居 | F65: 45959 | G65: 104524 | I65: 租金代扣 | J65: 0 | K65: 上海沪怡佳装饰设计工程有限公司 | L65: 第三批预备池 | M65: 第三批预备池
A66: 28 | B66: 107114334568 | C66: 上海市长宁区中山西路450号1502 | D66: 上海 | E66: 悦居 | F66: 45959 | G66: 80000 | H66: 80000 | I66: 租金代扣 | K66: 住与家（上海）装饰设计有限公司 | L66: 第四批预备池 | M66: 第四批预备池
A67: 28 | B67: 107114110386 | C67: 上海市静安区常德路545弄172号502室 | D67: 上海 | E67: 悦居 | F67: 45953 | G67: 73562.4 | H67: 73562 | I67: 租金代扣 | K67: 住与家（上海）装饰设计有限公司 | L67: 第四批预备池 | M67: 第四批预备池
A68: -10 | B68: 101131405399 | C68: 北京市海淀区甘家口26号楼3层2门东309 | D68: 北京 | E68: 舒里简逸 | F68: 45829 | G68: 26800 | H68: 26800 | I68: 业主付款 | K68: 北京米屋科技有限公司北京第一分公司
A69: 28 | B69: 107114470114 | C69: 上海市杨浦区国和二村28号402室 | D69: 上海 | E69: 悦居 | F69: 45983 | G69: 122501 | H69: 122501 | I69: 租金代扣 | K69: 上海筑家家建筑装饰有限公司 | L69: 第四批预备池 | M69: 第四批预备池
A70: 27 | B70: 107114461948 | C70: 上海市杨浦区国定路505弄8号602室 | D70: 上海 | E70: 悦居 | F70: 45976 | G70: 95739 | H70: 95739 | I70: 租金代扣 | K70: 上海筑家家建筑装饰有限公司 | L70: 第四批预备池 | M70: 第四批预备池
A71: 28 | B71: 107114363479 | C71: 上海市宝山区泰和西路3499弄60号601室 | D71: 上海 | E71: 悦居 | F71: 45962 | G71: 85451 | H71: 85451 | I71: 租金代扣 | K71: 上海千盛邦建筑装饰有限公司 | L71: 第四批预备池 | M71: 第四批预备池
A72: 28 | B72: 107114313264 | C72: 上海市宝山区泰和路309弄7号106室 | D72: 上海 | E72: 悦居 | F72: 45955 | G72: 77263 | H72: 77263 | I72: 租金代扣 | K72: 上海千盛邦建筑装饰有限公司 | L72: 第四批预备池 | M72: 第四批预备池
A73: 27 | B73: 107114564075 | C73: 上海市静安区大沽路368弄 1号3108室 | D73: 上海 | E73: 山念 | F73: 45990 | G73: 130000 | H73: 130000 | I73: 租金代扣 | K73: 住与家（上海）装饰设计有限公司 | L73: 第四批预备池 | M73: 第四批预备池
A74: 28 | B74: 107114493749 | C74: 上海市长宁区定西路390弄2号402室 | D74: 上海 | E74: 山念 | F74: 45981 | G74: 82000 | H74: 82000 | I74: 租金代扣 | K74: 住与家（上海）装饰设计有限公司 | L74: 第四批预备池 | M74: 第四批预备池
A75: 28 | B75: 107114386601 | C75: 上海宝山乾溪新村乾溪路250弄19号楼乾溪路250弄19单元0603 | D75: 上海 | E75: 悦居 | F75: 45621 | G75: 92200 | H75: 92200 | I75: 租金代扣 | K75: 上海长聚建筑工程有限公司 | L75: 第四批预备池 | M75: 第四批预备池
B76: 107114199394 | C76: 上海市浦东新区崂山新村69号楼603 | D76: 上海 | E76: 山念 | F76: 45824 | G76: 93600 | H76: 0 | I76: 业主付款 | K76: 上海弘曳建筑装饰工程有限公司 | L76: 第四批预备池 | M76: 第四批预备池
A77: 0 | B77: 107113379449 | C77: 上海市徐汇区中山南二路945弄7号203（业主自费） | D77: 上海 | E77: 山念 | F77: 45845 | G77: 72773 | H77: 6300 | I77: 业主付款 | K77: 南京弘德装饰工程有限公司 | L77: 第二批 | M77: 第二批
A78: 28 | B78: 107114573851 | C78: 上海市浦东新区大同路128弄高桥一村21栋501 | D78: 上海 | E78: 悦居 | F78: 45991 | G78: 82919 | H78: 82919 | I78: 租金代扣 | K78: 上海坤鹏源科技有限公司 | L78: 第四批预备池 | M78: 第四批预备池
A79: 28 | B79: 107114520946 | C79: 上海市浦东新区浦三路775弄3号1003室 | D79: 上海 | E79: 悦居 | F79: 45984 | G79: 110000 | H79: 110000 | I79: 租金代扣 | K79: 上海弘曳建筑装饰工程有限公司 | L79: 第四批预备池 | M79: 第四批预备池
B80: 107113539048 | C80: 上海市浦东新区康桥半岛新城四期(东区)秀沿路1177弄7支弄215号楼 | D80: 上海 | E80: 山念 | F80: 45860 | G80: 21111 | I80: 租金代扣 | K80: 上海弘曳建筑装饰工程有限公司 | L80: 第三批预备池 | M80: 第三批预备池
A81: 27 | B81: 107114678846 | C81: 上海市普陀区宜昌路727号401 | D81: 上海 | E81: 悦居 | F81: 46005 | G81: 74477 | H81: 74477 | I81: 租金代扣 | K81: 上海鑫宇阳建设工程有限公司 | L81: 第四批预备池 | M81: 第四批预备池
A82: 30 | B82: 107114014880 | C82: 上海市浦东新区严桥路55弄5号702室 | D82: 上海 | E82: 悦居 | F82: 45986 | G82: 107093 | H82: 107093 | I82: 租金代扣 | K82: 上海弘曳建筑装饰工程有限公司 | L82: 第四批预备池 | M82: 第四批预备池
A83: 30 | B83: 107114574759 | C83: 上海市浦东新区康桥镇创业路66弄7号601室 | D83: 上海 | E83: 山念 | F83: 46014 | G83: 120433 | H83: 120433 | I83: 租金代扣 | K83: 上海弘曳建筑装饰工程有限公司
A84: 28 | B84: 107114117565 | C84: 上海市浦东新区永泰路136弄19号1704室 | D84: 上海 | E84: 山念 | F84: 45941 | G84: 160497 | H84: 160479 | I84: 租金代扣 | J84: 18 | K84: 上海弘曳建筑装饰工程有限公司 | L84: 第四批预备池 | M84: 第四批预备池
A85: 28 | B85: 107114468833 | C85: 上海市浦东新区南码头路1696弄33号602室 | D85: 上海 | E85: 山念 | F85: 45985 | G85: 87000 | H85: 87000 | I85: 租金代扣 | K85: 上海弘曳建筑装饰工程有限公司 | L85: 第四批预备池 | M85: 第四批预备池
A86: 28 | B86: 107114421933 | C86: 上海市闵行区都市路2501弄358号202室 | D86: 上海 | E86: 山念 | F86: 45970 | G86: 121479 | H86: 121479 | I86: 租金代扣 | K86: 品优美居（北京）科技有限公司 | L86: 第四批预备池 | M86: 第四批预备池
A87: 28 | B87: 107114568330 | C87: 上海市浦东新区上南三村80号503室 | D87: 上海 | E87: 悦居 | F87: 45990 | G87: 94976 | H87: 94976 | I87: 租金代扣 | K87: 上海弘曳建筑装饰工程有限公司 | L87: 第四批预备池 | M87: 第四批预备池
A88: 29 | B88: 107114498368 | C88: 上海市浦东新区陈春路221弄9号602室 | D88: 上海 | E88: 山念 | F88: 45981 | G88: 250991 | H88: 210991 | I88: 业主付款+租金代扣 | J88: 40000 | K88: 上海弘曳建筑装饰工程有限公司 | L88: 第四批预备池 | M88: 第四批预备池
B89: 101131539500 | C89: 北京市西城区人定湖西里10号楼2单元102 | D89: 北京 | E89: 焕新租 | F89: 45834 | G89: 89940 | H89: 89940 | I89: 租金代扣 | K89: 北京省心装工程管理有限公司 | L89: 第三批预备池 | M89: 第三批预备池
A90: 30 | B90: 107114479827 | C90: 上海市浦东新区江耀路122弄3号1层103室 | D90: 上海 | E90: 山念 | F90: 45993 | G90: 222999 | H90: 222999 | I90: 租金代扣 | K90: 上海弘曳建筑装饰工程有限公司 | L90: 第四批预备池 | M90: 第四批预备池
B91: 107111383669 | C91: 上海市宝山区高境一村87号楼0402 | D91: 上海 | E91: 山念 | F91: 45736 | G91: 5353 | I91: 租金代扣 | J91: 0 | K91: 上海千盛邦建筑装饰有限公司 | L91: 第四批预备池 | M91: 第四批预备池
A92: 28 | B92: 107114426380 | C92: 上海市浦东新区西营路33弄6支弄9号404室 | D92: 上海 | E92: 悦居 | F92: 45990 | G92: 96000 | H92: 96000 | I92: 租金代扣 | K92: 上海弘曳建筑装饰工程有限公司 | L92: 第四批预备池 | M92: 第四批预备池
A93: 28 | B93: 107114541025 | C93: 上海市浦东新区浦东南路1038弄3号601室 | D93: 上海 | E93: 山念 | F93: 45987 | G93: 189900 | H93: 189900 | I93: 租金代扣 | K93: 上海弘曳建筑装饰工程有限公司 | L93: 第四批预备池 | M93: 第四批预备池
A94: 28 | B94: 107114494597 | C94: 上海市浦东新区苗桥路935弄32号704室 | D94: 上海 | E94: 山念 | F94: 45979 | G94: 128657 | H94: 128657 | I94: 租金代扣 | K94: 上海弘曳建筑装饰工程有限公司 | L94: 第四批预备池 | M94: 第四批预备池
A95: 28 | B95: 107114788517 | C95: 上海市普陀区兰田新村7号202-3 | D95: 上海 | E95: 悦居 | F95: 46022 | G95: 89917 | H95: 89917 | I95: 租金代扣 | K95: 上海鑫宇阳建设工程有限公司 | L95: 第四批预备池 | M95: 第四批预备池
A96: 28 | B96: 107114634422 | C96: 曹杨八村134号101室 | D96: 上海 | E96: 山念 | F96: 46001 | G96: 75200 | H96: 75200 | I96: 租金代扣 | K96: 上海鑫宇阳建设工程有限公司 | L96: 第四批预备池 | M96: 第四批预备池
A97: 28 | B97: 107114727845 | C97: 上海市普陀区信安新村133号601-2 | D97: 上海 | E97: 悦居 | F97: 46013 | G97: 99336 | H97: 99336 | I97: 租金代扣 | K97: 上海鑫宇阳建设工程有限公司 | L97: 第四批预备池 | M97: 第四批预备池
A98: 28 | B98: 107114801368 | C98: 上海市普陀区杨柳青路735弄27号204 | D98: 上海 | E98: 悦居 | F98: 46025 | G98: 79600 | H98: 79600 | I98: 租金代扣 | K98: 上海鑫宇阳建设工程有限公司 | L98: 第四批预备池 | M98: 第四批预备池
A99: 28 | B99: 107114443049 | C99: 上海市徐汇区大木桥路450弄1号502 | D99: 上海 | E99: 山念 | F99: 45838 | G99: 74781 | H99: 74781 | I99: 租金代扣 | J99: 0 | K99: 住与家（上海）装饰设计有限公司 | L99: 第四批预备池 | M99: 第四批预备池
A100: 28 | B100: 107114331550 | C100: 上海市黄浦区黄河路65号112室 | D100: 上海 | E100: 山念 | F100: 45957 | G100: 132000 | H100: 132000 | I100: 租金代扣 | J100: 0 | K100: 住与家（上海）装饰设计有限公司
...

Sheet 待检查发行状态
A1: 托管房源编号
A2: 101116255967
A3: 101127099270
A4: 101130772992
A5: 101131038474
A6: 101131063048
A7: 101131095241
A8: 101131380283
A9: 101131447146
A10: 101131517600
A11: 101131597357
A12: 101132324518
... A65: 107114266874
